Workbook

Sheet Result
A1: keyword | B1: occurrences | C1: total link strength
A2: microbial fuel cell | B2: 151 | C2: 589
A3: bioelectrochemical system | B3: 28 | C3: 123
A4: wastewater treatment | B4: 17 | C4: 70
A5: extracellular electron transfer | B5: 14 | C5: 63
A6: biosensor | B6: 13 | C6: 58
A7: wastewater | B7: 12 | C7: 41
A8: biofilm | B8: 10 | C8: 37
A9: renewable energy | B9: 10 | C9: 43
A10: bioelectricity | B10: 9 | C10: 37 | D10: Energy generation
A11: bioenergy | B11: 9 | C11: 36 | D11: Energy generation
A12: power density | B12: 9 | C12: 37 | D12: Energy generation
A13: shewanella | B13: 9 | C13: 37 | D13: Bacteria (keyword/strains)
A14: electricity generation | B14: 8 | C14: 33 | D14: Energy generation
A15: geobacter | B15: 8 | C15: 42 | D15: Bacteria (keyword/strains)
A16: microbial electrolysis cell | B16: 8 | C16: 30 | D16: Synthesis/Catalysis
A17: biocatalysis | B17: 7 | C17: 28 | D17: Synthesis/Catalysis
A18: electrochemistry | B18: 7 | C18: 31 | D18: Analysis tools
A19: electrode | B19: 7 | C19: 29 | D19: System (Configuration/Application)
A20: electron transfer | B20: 7 | C20: 35 | D20: Mechanisms (Electron Transfer)
A21: remediation | B21: 6 | C21: 30 | D21: Environmental
... A25: exoelectrogen | B25: 6 | C25: 31 | D25: Mechanisms (Electron Transfer)
A26: resource recovery | B26: 5 | C26: 21 | D26: Environmental | E26: Sub-Categories | F26: Occurrences | G26: Keywords | H26: Percentage (Total)
A27: anaerobic digestion | B27: 5 | C27: 24 | D27: Synthesis/Catalysis | E27: Synthesis/Catalysis | F27: =SUMIF($D$2:$D$467,E27,$B$2:$B$467) -> 106 | G27: =COUNTIF(D:D,E27) -> 64 | H27: =F27/SUM($F$27:$F$39) -> 0.14002642
A28: ceramic membrane | B28: 5 | C28: 20 | D28: System (Materials/Fabrication) | E28: System (Materials/Fabrication) | F28: =SUMIF($D$2:$D$467,E28,$B$2:$B$467) -> 92 | G28: =COUNTIF(D:D,E28) -> 59 | H28: =F28/SUM($F$27:$F$39) -> 0.12153236
A29: electroactive biofilm | B29: 5 | C29: 22 | D29: Biofilm | E29: System (Configuration/Application) | F29: =SUMIF($D$2:$D$467,E29,$B$2:$B$467) -> 85 | G29: =COUNTIF(D:D,E29) -> 52 | H29: =F29/SUM($F$27:$F$39) -> 0.11228534
A30: escherichia coli | B30: 5 | C30: 18 | D30: Bacteria (keyword/strains) | E30: Energy generation | F30: =SUMIF($D$2:$D$467,E30,$B$2:$B$467) -> 74 | G30: =COUNTIF(D:D,E30) -> 32 | H30: =F30/SUM($F$27:$F$39) -> 0.097754293
A31: graphene | B31: 5 | C31: 22 | D31: System (Materials/Fabrication) | E31: Mechanisms (Electron Transfer) | F31: =SUMIF($D$2:$D$467,E31,$B$2:$B$467) -> 70 | G31: =COUNTIF(D:D,E31) -> 35 | H31: =F31/SUM($F$27:$F$39) -> 0.092470277
A32: nanotechnology | B32: 5 | C32: 21 | D32: System (Materials/Fabrication) | E32: Analysis tools | F32: =SUMIF($D$2:$D$467,E32,$B$2:$B$467) -> 52 | G32: =COUNTIF(D:D,E32) -> 33 | H32: =F32/SUM($F$27:$F$39) -> 0.068692206
A33: stack Configuration/Application | B33: 5 | C33: 24 | D33: System (Configuration/Application) | E33: Bacteria (keyword/strains) | F33: =SUMIF($D$2:$D$467,E33,$B$2:$B$467) -> 49 | G33: =COUNTIF(D:D,E33) -> 19 | H33: =F33/SUM($F$27:$F$39) -> 0.064729194
A34: urine | B34: 5 | C34: 23 | D34: Other | E34: Other microorganism | F34: =SUMIF($D$2:$D$467,E34,$B$2:$B$467) -> 42 | G34: =COUNTIF(D:D,E34) -> 22 | H34: =F34/SUM($F$27:$F$39) -> 0.055482166
A35: electron transport | B35: 5 | C35: 24 | D35: Mechanisms (Electron Transfer) | E35: Environmental | F35: =SUMIF($D$2:$D$467,E35,$B$2:$B$467) -> 36 | G35: =COUNTIF(D:D,E35) -> 21 | H35: =F35/SUM($F$27:$F$39) -> 0.047556143
A36: bacteria | B36: 4 | C36: 14 | D36: Bacteria (keyword/strains) | E36: Other Biomolecules | F36: =SUMIF($D$2:$D$467,E36,$B$2:$B$467) -> 19 | G36: =COUNTIF(D:D,E36) -> 11 | H36: =F36/SUM($F$27:$F$39) -> 0.025099075
A37: bioelectrocatalysis | B37: 4 | C37: 14 | D37: Synthesis/Catalysis | E37: Biofilm | F37: =SUMIF($D$2:$D$467,E37,$B$2:$B$467) -> 8 | G37: =COUNTIF(D:D,E37) -> 4 | H37: =F37/SUM($F$27:$F$39) -> 0.010568032
A38: bioelectrosynthesis | B38: 4 | C38: 22 | D38: Synthesis/Catalysis | E38: Other | F38: =SUMIF($D$2:$D$467,E38,$B$2:$B$467) -> 104 | G38: =COUNTIF(D:D,E38) -> 84 | H38: =F38/SUM($F$27:$F$39) -> 0.13738441
A39: cathode | B39: 4 | C39: 25 | D39: System (Configuration/Application) | E39: Unrelated | F39: =SUMIF($D$2:$D$467,E39,$B$2:$B$467) -> 20 | G39: =COUNTIF(D:D,E39) -> 19 | H39: =F39/SUM($F$27:$F$39) -> 0.026420079
A40: continuous flow | B40: 4 | C40: 18 | D40: Other | F40: =SUM(F27:F39) -> 757 | G40: =SUM(G27:G39) -> 455 | H40: =SUM(H27:H39) -> 1
A41: coulombic efficiency | B41: 4 | C41: 15 | D41: Analysis tools
A42: electroactive bacteria | B42: 4 | C42: 15 | D42: Bacteria (keyword/strains) | E42: Main | F42: =SUM(B2:B9) -> 255 | H42: =F42/SUM($F$42:$F$45) -> 0.25197628
A43: energy production | B43: 4 | C43: 16 | D43: Energy generation | E43: Sub | F43: =SUM(F27:F37) -> 633 | H43: =F43/SUM($F$42:$F$45) -> 0.62549407
A44: enzymatic biofuel cell | B44: 4 | C44: 19 | D44: Other Biomolecules | E44: Other | F44: =F38 -> 104 | H44: =F44/SUM($F$42:$F$45) -> 0.1027668
A45: enzyme | B45: 4 | C45: 18 | D45: Other Biomolecules | E45: Unrelated | F45: =F39 -> 20 | H45: =F45/SUM($F$42:$F$45) -> 0.019762846
A46: microbial community | B46: 4 | C46: 16 | D46: Other microorganism
A47: oxygen reduction | B47: 4 | C47: 16 | D47: Synthesis/Catalysis | F47: =SUM(F42:F45) -> 1012 | H47: =SUM(H42:H45) -> 1
A48: proton exchange membrane | B48: 4 | C48: 13 | D48: System (Materials/Fabrication)
A49: pseudomonas | B49: 4 | C49: 17 | D49: Bacteria (keyword/strains)
A50: scale-up | B50: 4 | C50: 18 | D50: System (Configuration/Application)
A51: direct electron transfer | B51: 4 | C51: 19 | D51: Mechanisms (Electron Transfer)
A52: redox mediator | B52: 4 | C52: 23 | D52: Mechanisms (Electron Transfer)
A53: 3d printing | B53: 3 | C53: 11 | D53: System (Materials/Fabrication)
A54: air cathode | B54: 3 | C54: 12 | D54: System (Configuration/Application)
A55: anode | B55: 3 | C55: 19 | D55: System (Configuration/Application)
A56: biogas | B56: 3 | C56: 12 | D56: Synthesis/Catalysis
A57: biohydrogen | B57: 3 | C57: 14 | D57: Synthesis/Catalysis
A58: biomass | B58: 3 | C58: 10 | D58: Synthesis/Catalysis
A59: carbon | B59: 3 | C59: 10 | D59: System (Materials/Fabrication)
... A467: redox mediator | B467: 2 | C467: 8 | D467: Mechanisms (Electron Transfer)

Sheet Year by year keywords
A3: Count of KEYWORD | B3: Column Labels
A4: Row Labels | B4: 2013 | C4: 2014 | D4: 2015 | E4: 2016 | F4: 2017 | G4: 2018 | H4: Grand Total
A5: Analysis tools | B5: 6 | C5: 4 | D5: 6 | E5: 2 | F5: 8 | G5: 5 | H5: 31
A6: Bacteria (keyword/strains) | B6: 2 | C6: 4 | D6: 3 | E6: 3 | F6: 9 | G6: 4 | H6: 25
A7: bioelectrochemical system | B7: 1 | C7: 3 | D7: 4 | E7: 4 | F7: 4 | G7: 6 | H7: 22
A8: Biofilm | B8: 1 | C8: 1 | D8: 3 | E8: 1 | F8: 1 | G8: 2 | H8: 9
A9: biosensor | D9: 4 | E9: 2 | F9: 1 | G9: 2 | H9: 9
A10: Energy generation | B10: 3 | C10: 6 | D10: 7 | E10: 14 | F10: 11 | G10: 9 | H10: 50
A11: Environmental | C11: 2 | D11: 6 | E11: 4 | F11: 5 | G11: 8 | H11: 25
A12: extracellular electron transfer | C12: 1 | D12: 4 | E12: 1 | F12: 1 | G12: 3 | H12: 10
A13: Mechanisms (Electron Transfer) | B13: 5 | C13: 3 | D13: 10 | E13: 5 | F13: 18 | G13: 9 | H13: 50
A14: microbial fuel cell | B14: 9 | C14: 14 | D14: 17 | E14: 17 | F14: 24 | G14: 19 | H14: 100
A15: Other Biomolecules | B15: 2 | C15: 2 | D15: 3 | E15: 2 | F15: 2 | H15: 11
A16: Other microorganism | B16: 3 | C16: 3 | D16: 3 | E16: 5 | F16: 5 | G16: 7 | H16: 26
A17: renewable energy | B17: 2 | D17: 2 | F17: 1 | G17: 2 | H17: 7
A18: Synthesis/Catalysis | B18: 4 | C18: 18 | D18: 10 | E18: 10 | F18: 15 | G18: 6 | H18: 63
A19: System (Configuration/Application) | B19: 7 | C19: 5 | D19: 10 | E19: 10 | F19: 12 | G19: 17 | H19: 61
A20: System (Materials/Fabrication) | B20: 4 | C20: 6 | D20: 11 | E20: 6 | F20: 15 | G20: 12 | H20: 54
A21: wastewater | B21: 1 | D21: 1 | E21: 3 | F21: 1 | G21: 3 | H21: 9
A22: wastewater treatment | B22: 1 | C22: 2 | D22: 1 | E22: 3 | F22: 2 | G22: 1 | H22: 10
A23: Grand Total | B23: 51 | C23: 74 | D23: 105 | E23: 92 | F23: 135 | G23: 115 | H23: 572

Sheet Year by year keywords-Selected
A3: Count of KEYWORD | B3: Column Labels
A4: Row Labels | B4: 2013 | C4: 2014 | D4: 2015 | E4: 2016 | F4: 2017 | G4: 2018 | H4: Grand Total
A5: bioelectrochemical system | B5: 1 | C5: 3 | D5: 4 | E5: 4 | F5: 4 | G5: 6 | H5: 22
A6: biofilm | B6: 1 | D6: 1 | E6: 1 | G6: 2 | H6: 5
A7: biosensor | D7: 4 | E7: 2 | F7: 1 | G7: 2 | H7: 9
A8: extracellular electron transfer | C8: 1 | D8: 4 | E8: 1 | F8: 1 | G8: 3 | H8: 10
A9: microbial fuel cell | B9: 9 | C9: 14 | D9: 17 | E9: 17 | F9: 24 | G9: 19 | H9: 100
A10: renewable energy | B10: 2 | D10: 2 | F10: 1 | G10: 2 | H10: 7
A11: wastewater | B11: 1 | D11: 1 | E11: 3 | F11: 1 | G11: 3 | H11: 9
A12: wastewater treatment | B12: 1 | C12: 2 | D12: 1 | E12: 3 | F12: 2 | G12: 1 | H12: 10
A13: Grand Total | B13: 15 | C13: 20 | D13: 34 | E13: 31 | F13: 34 | G13: 38 | H13: 172

Sheet Publication type Vs Year
A3: Count of DT | B3: Column Labels
A4: Row Labels | B4: Article | C4: Article; Book Chapter | D4: Article; Proceedings Paper | E4: Editorial Material | F4: Editorial Material; Book Chapter | G4: Proceedings Paper | H4: Review | I4: Review; Book Chapter | J4: Grand Total
A5: 2009 | B5: 1 | D5: 1 | G5: 1 | J5: 3
A6: 2010 | B6: 4 | C6: 1 | D6: 1 | G6: 1 | H6: 8 | J6: 15
A7: 2011 | B7: 6 | C7: 2 | G7: 3 | H7: 2 | J7: 13
A8: 2012 | B8: 12 | C8: 7 | D8: 3 | H8: 7 | J8: 29
A9: 2013 | B9: 12 | D9: 3 | E9: 1 | H9: 4 | J9: 20
A10: 2014 | B10: 19 | C10: 1 | G10: 2 | H10: 5 | J10: 27
A11: 2015 | B11: 10 | C11: 3 | G11: 1 | H11: 14 | J11: 28
A12: 2016 | B12: 13 | C12: 3 | D12: 1 | E12: 2 | G12: 4 | H12: 7 | J12: 30
A13: 2017 | B13: 16 | C13: 1 | D13: 4 | G13: 1 | H13: 20 | I13: 1 | J13: 43
A14: 2018 | B14: 13 | C14: 7 | D14: 1 | E14: 1 | F14: 1 | G14: 1 | H14: 11 | I14: 1 | J14: 36
A15: 2019 | B15: 14 | C15: 8 | D15: 1 | E15: 1 | H15: 7 | J15: 31
A16: Grand Total | B16: 120 | C16: 33 | D16: 15 | E16: 5 | F16: 1 | G16: 14 | H16: 85 | I16: 2 | J16: 275

Sheet Bibliographic data
A1: PPR ID | B1: DOI | C1: PT | D1: AU | E1: BA | F1: BE | G1: GP | H1: AF | I1: BF | J1: CA | K1: TI | L1: SO | M1: SE | N1: BS | O1: LA | P1: DT | Q1: CT | R1: CY | S1: CL | T1: SP | U1: HO | V1: DE | W1: ID | X1: AB | Y1: C1 | Z1: RP | AA1: EM | AB1: RI | AC1: OI | AD1: FU | AE1: FX | AF1: CR | AG1: NR | AH1: TC | AI1: Z9 | AJ1: U1 | AK1: U2 | AL1: PU | AM1: PI | AN1: PA | AO1: SN | AP1: EI | AQ1: BN | AR1: J9 | AS1: JI | AT1: PD | AU1: PY | AV1: VL | AW1: IS | AX1: PN | AY1: SU | AZ1: SI | BA1: MA | BB1: BP | BC1: EP | BD1: AR | BE1: DI | BF1: D2 | BG1: EA | BH1: EY | BI1: PG | BJ1: WC | BK1: SC | BL1: GA | BM1: UT | BN1: PM | BO1: OA | BP1: HC | BQ1: HP | BR1: DA
A2: 1 | B2: 10.1098/rspb.1911.0073 | C2: J | D2: Potter, MC | H2: Potter, MC | K2: Electrical effects accompanying the decomposition of organic compounds | L2: PROCEEDINGS OF THE ROYAL SOCIETY OF LONDON SERIES B-CONTAINING PAPERS OF A BIOLOGICAL CHARACTER | O2: English | P2: Article | AF2: Haacke O., 1892, FLORA, V75; Klein B., 1898, BERICHTE DTSCH BOT G, V16; POTTER MC, 1910, DURHAM U PHIL SOC P, V3; WALLER AD, 1910, CALIFORNIAN LECT; WALLER AD, 1903, SIGNS LIFE | AG2: 5 | AH2: 333 | AI2: 362 | AJ2: 3 | AK2: 79 | AL2: ROYAL SOC LONDON | AM2: LONDON | AN2: 6 CARLTON HOUSE TERRACE, LONDON SW1Y 5AG, ENGLAND | AO2: 0950-1193 | AR2: P R SOC LOND B-CONTA | AT2: SEP | AU2: 1911 | AV2: 84 | AW2: 571 | BB2: 260 | BC2: 276 | BE2: 10.1098/rspb.1911.0073 | BI2: 17 | BJ2: Biology | BK2: Life Sciences & Biomedicine - Other Topics | BL2: V05PR | BM2: WOS:000200378700006 | BO2: Bronze | BR2: 43698
A3: 2 | B3: 10.1097/00010694-192004000-00001 | C3: J | D3: Gillespie, LJ | H3: Gillespie, LJ | K3: Reduction potentials of bacterial cultures and of water-logged soils | L3: SOIL SCIENCE | O3: English | P3: Article | AF3: Bancroft WD, 1892, Z PHYS CHEM, V10, P387; BOSE, 1901, Z PHYS CHEM, V38, P28; Cannon WA, 1917, SCIENCE, V45, P178, DOI 10.1126/science.45.1156.178; Cole R, 1914, J EXP MED, V20, P363, DOI 10.1084/jem.20.4.363; Ehrlich P., 1885, SAUERSTOFFBEDURFNIS; Forbes GS, 1917, J AM CHEM SOC, V39, P1140, DOI 10.1021/ja02251a005; Forbes GS, 1914, J AM CHEM SOC, V36, P2030, DOI 10.1021/ja02187a006; Frary FC, 1915, J AM CHEM SOC, V37, P2246, DOI 10.1021/ja02175a001; FRED EB, 1916, J AGR RES, V5, P1161; Fredenhagen C, 1902, Z ANORG CHEM, V29, P396, DOI 10.1002/zaac.19020290132; GARRETSEN FC, 1915, MEDED PROEFSTAT JAVA, V5, P317; Gillespie LJ, 1918, SOIL SCI, V6, P219, DOI 10.1097/00010694-191809000-00002; Harden A, 1915, BIOCHEM J, V9, P379, DOI 10.1042/bj0090379; Hildebrand JH, 1913, J AM CHEM SOC, V35, P847, DOI 10.1021/ja02196a001; HONING JA, 1917, B PROEFSTAT MEDAN, V8; Keyes FG, 1912, J BIOL CHEM, V13, P305; KUHR CAH, 1915, RCH SUIKERINDUS NED, V23, P501; Lewis GN, 1906, J AM CHEM SOC, V28, P158, DOI 10.1021/ja01968a003; Lewis GN, 1909, J AM CHEM SOC, V31, P355, DOI 10.1021/ja01933a005; Michaelis L, 1912, BIOCHEM Z, V46, P131; Michaelis L., 1914, WASSERSTOFFIONENKONZ; NEUMANN B, 1894, Z PHYS CHEM, V14, P193; OBERSTADT, 1913, Z HYG, V75, P1; OSTWALDLUTHER, 1910, PHYSIKOCHEMISCHE MES; PETERS R, 1898, Z PHYS CHEM, V26, P193; Potter MC, 1911, P R SOC LOND B-CONTA, V84, P260, DOI 10.1098/rspb.1911.0073; POTTER MC, 1912, P U DURHAM PHIL SOC, V4, P230; Rogers LA, 1914, J INFECT DIS, V14, P411, DOI 10.1093/infdis/14.3.411; RUSSEL, 1915, J AGRIC SCI, V7, P1; SCHREINER O, 1910, USDA BUR SOILS B, V73; SCHREINER O, 1914, USDA B, V108; SCHREINER O, 1909, USDA BUR SOILS B, V56; SKINNER JJ, 1914, USDG B, V42; STIEGLITZ J, 1912, ELEMENTS QUALITATIVE, V1; SULLIVAN MX, 1914, SCIENCE, V39, P958; SULLIVAN MX, 1911, J IND ENG CHEM, V3, P1; VANLAAR JJ, 1907, LEHRBUCH THEORETISCH; WELLS RC, 1914, US GEOL SURVEY B, V548; White WP, 1914, J AM CHEM SOC, V36, P2011, DOI 10.1021/ja02187a004; 1918, AGR J INDIA 1, V13, P148 | AG3: 40 | AH3: 58 | AI3: 61 | AJ3: 0 | AK3: 2 | AL3: LIPPINCOTT WILLIAMS & WILKINS | AM3: PHILADELPHIA | AN3: 530 WALNUT ST, PHILADELPHIA, PA 19106-3621 USA | AO3: 0038-075X | AR3: SOIL SCI | AS3: Soil Sci. | AT3: APR | AU3: 1920 | AV3: 9 | AW3: 4 | BB3: 199 | BC3: 216 | BE3: 10.1097/00010694-192004000-00001 | BI3: 18 | BJ3: Soil Science | BK3: Agriculture | BL3: V5871 | BM3: WOS:000187706700001 | BR3: 43703
A4: 3 | B4: 10.1021/ja01395a001 | C4: J | D4: Davis, CE; Davidson, GM | H4: Davis, CE; Davidson, GM | K4: Studies of hydrogen ion concentration measurements. I. Methods of measurements | L4: JOURNAL OF THE AMERICAN CHEMICAL SOCIETY | O4: English | P4: Article | Y4: Natl Biscuit Co, Res Lab, New York, NY USA | AF4: BEANS, 1920, J AM CHEM SOC, V42, P2116; CARHART, 1900, ELECT MEASUREMENTS, P188; DAVIS, 1923, IND ENG CHEM, V15, P182; MELLOR FW, 1919, HIGHER MATH STUDENTS; Potter MC, 1911, P R SOC LOND B-CONTA, V84, P260, DOI 10.1098/rspb.1911.0073; WHITE, 1906, PHYS REV, V23, P382; ZELENY, 1906, PHYS REV, V23, P399 | AG4: 7 | AH4: 2 | AI4: 2 | AJ4: 0 | AK4: 0 | AL4: AMER CHEMICAL SOC | AM4: WASHINGTON | AN4: 1155 16TH ST, NW, WASHINGTON, DC 20036 USA | AO4: 0002-7863 | AR4: J AM CHEM SOC | AS4: J. Am. Chem. Soc. | AU4: 1928 | AV4: 50 | AX4: 2 | BB4: 2053 | BC4: 2065 | BE4: 10.1021/ja01395a001 | BI4: 13 | BJ4: Chemistry, Multidisciplinary | BK4: Chemistry | BL4: V8444 | BM4: WOS:000188448200142 | BR4: 43703
A5: 4 | B5: 10.1084/jem.49.5.711 | C5: J | D5: Coulter, CB; Isaacs, ML | H5: Coulter, CB; Isaacs, ML | K5: Oxidation-reduction equilibria in biological systems. II. Potentials of aerobic cultures of B-tyhosus. | L5: JOURNAL OF EXPERIMENTAL MEDICINE | O5: English | P5: Article | Y5: Columbia Univ, Coll Phys & Surg, Dept Bacteriol, New York, NY USA | AF5: CANNAN RK, 1926, PUB HEALTH REP S, P55; Cohen B, 1928, J GEN PHYSIOL, V11, P585, DOI 10.1085/jgp.11.5.585; Coulter CB, 1928, J GEN PHYSIOL, V12, P139, DOI 10.1085/jgp.12.1.139; Dixon M, 1927, P R SOC LOND B-CONTA, V101, P57, DOI 10.1098/rspb.1927.0005; Dixon M, 1923, J CHEM SOC, V123, P2943, DOI 10.1039/ct9232302943; Dubos R, 1929, J EXP MED, V49, P507, DOI 10.1084/jem.49.3.507; Gillespie LJ, 1920, SOIL SCI, V9, P199, DOI 10.1097/00010694-192004000-00001; MICHAELIS L., 1928, JOUR BIOL CHEM, V79, P689; Neill JM, 1926, J EXP MED, V44, P215, DOI 10.1084/jem.44.2.215; Neill JM, 1926, J EXP MED, V44, P227, DOI 10.1084/jem.44.2.227; Potter MC, 1911, P R SOC LOND B-CONTA, V84, P260, DOI 10.1098/rspb.1911.0073 | AG5: 11 | AH5: 12 | AI5: 12 | AJ5: 0 | AK5: 0 | AL5: ROCKEFELLER UNIV PRESS | AM5: NEW YORK | AN5: 1114 FIRST AVE, 4TH FL, NEW YORK, NY 10021 USA | AO5: 0022-1007 | AR5: J EXP MED | AS5: J. Exp. Med. | AT5: MAY | AU5: 1929 | AV5: 49 | AW5: 5 | BB5: 711 | BC5: 725 | BE5: 10.1084/jem.49.5.711 | BI5: 15 | BJ5: Immunology; Medicine, Research & Experimental | BK5: Immunology; Research & Experimental Medicine | BL5: V28TM | BM5: WOS:000201943400002 | BN5: 19869577 | BO5: Bronze, Green Published | BR5: 43703
A6: 5 | B6: 10.1042/bj0281894 | C6: J | D6: Messing, WA | H6: Messing, WA | K6: The mechanism of bacterial anaerobiosis. III. The oxidation-reduction potential of the butyric bacillus in presence of sulphydryl compounds. | L6: BIOCHEMICAL JOURNAL | O6: English | P6: Article | AF6: AUBEL, 1929, ANN PHYS PHYSICHOCHI, V5, P1; BAMBERGER, 1933, J GEN PHYSL, V16; CLARK, 1924, J WASH AC SC, V14, P123; COULTER, 1929, J EXP MED, V49, P711; FILDES, 1929, BRIT J EXP PATH, V10, P151; GILLESPIE, 1920, SOIL SCI, V9, P199; HEWITT, 1930, OXIDATION REDUCTION, P41; HOPKINS, 1931, P ROY SOC LOND B, V109, P58; HOSOYA, 1925, BACTERIAL METABOLISM, P79; KNIGHT, 1930, BIOCH J, V24, P1496; LEPPER, 1930, BRIT J EXP PATH, V11, P137; MESSING, 1933, MICROBIOLOGICA IMMUN; PLOTZ, 1930, ANN I PASTEUR, V45, P613; Potter MC, 1911, P R SOC LOND B-CONTA, V84, P260, DOI 10.1098/rspb.1911.0073; QUASTEL, 1926, BIOCHEM J, V20, P1126; QUASTEL, 1929, BIOCH J, V23, P115; TAROZZI, 1905, CENTR BAKT ABT 1, V38, P619; WURMSER, 1930, OXYDATIONS REDUCTION, P343 | AG6: 18 | AH6: 3 | AI6: 3 | AJ6: 0 | AK6: 0 | AL6: PORTLAND PRESS | AM6: LONDON | AN6: 59 PORTLAND PLACE, LONDON W1N 3AJ, ENGLAND | AO6: 0264-6021 | AR6: BIOCHEM J | AS6: Biochem. J. | AU6: 1934 | AV6: 28 | AX6: 2 | BB6: 1894 | BC6: 1900 | BE6: 10.1042/bj0281894 | BI6: 7 | BJ6: Biochemistry & Molecular Biology | BK6: Biochemistry & Molecular Biology | BL6: V4092 | BM6: WOS:000187145100094 | BN6: 16745587 | BR6: 43703
A7: 6 | C7: J | D7: Elema, B; Kluyver, AJ; van Dalfsen, JW | H7: Elema, B; Kluyver, AJ; van Dalfsen, JW | K7: The connection between the metabolism procedures of the micro organisms and of the oxido reduction potential in the medium I Announcement - Trials with denitrified bacteria | L7: BIOCHEMISCHE ZEITSCHRIFT | O7: German | P7: Article | Y7: Tech Hsch, Lab Mikrobiol, Delft, HOLLAND | AF7: BEIJERINCK MW, 1910, CENTRALBL BAKTERIO 2, V25, P30; Borsook H, 1931, J BIOL CHEM, V92, P535; Boyland E, 1930, BIOCHEM J, V24, P703, DOI 10.1042/bj0240703; COONS OC, 1931, IND ENG CHEM ANAL ED, V3, P407; ELEINA B, 1932, BEPALING OXYDATIE RE; Elema B, 1931, RECL TRAV CHIM PAY-B, V50, P807; ELEMA B, 1932, CHEM WEEKBL, V29, P638; ELEMA B, 1931, CHEM WEEKBL, V28, P219; Gayon U., 1882, CR HEBD ACAD SCI, V95, P644; HEWITT LF, 1931, OXIDATION REDUCTION; Kluyver A. J., 1931, CHEM ACTIVITIES MICR; KLUYVER AJ, 1926, CHEM GEWEBE, V13, P189; KUSNETZOW SJ, 1931, CENTRALBL BAKT, V83, P37; Lehmann J, 1930, SKAND ARCH PHYSIOL, V58, P173, DOI 10.1111/j.1748-1716.1930.tb00924.x; Lipmann F, 1934, BIOCHEM Z, V268, P205; Potter MC, 1911, P R SOC LOND B-CONTA, V84, P260, DOI 10.1098/rspb.1911.0073; Quastel JH, 1924, BIOCHEM J, V18, P519, DOI 10.1042/bj0180519; RASCHIG BF, 1924, SCHWEFEL STICKSTOFFS, P97; SZENTGYORGYI A, 1933, Z PHYSL CHEM, V217, P51; THUNBERG T, 1925, SKAND ARCH PHYSL, V46, P339; VANITERSON JG, 1904, CENTRALBL BAKT, V12, P106; VANNIEUWENBURG CJ, 1927, CHEM WEEKBL, V24, P202; WIDMARK EMP, 1922, BIOCHEM Z, V131, P471; Wurmser R, 1930, OXYDATIONS REDUCTION; WURMSER R, 1932, CR HEBD ACAD SCI, V194, P888 | AG7: 25 | AH7: 18 | AI7: 18 | AJ7: 0 | AK7: 0 | AL7: SPRINGER | AM7: NEW YORK | AN7: 233 SPRING STREET, NEW YORK, NY 10013 USA | AO7: 0366-0753 | AR7: BIOCHEM Z | AS7: Biochem. Z. | AU7: 1934 | AV7: 270 | BB7: 317 | BC7: 340 | BI7: 24 | BJ7: Biochemistry & Molecular Biology | BK7: Biochemistry & Molecular Biology | BL7: V12RW | BM7: WOS:000200857600033 | BR7: 43703
A8: 7 | C8: J | D8: Kluyver, AJ; Hoogerheide, JC | H8: Kluyver, AJ; Hoogerheide, JC | K8: Some remarks on the reduction intensity of living cells | L8: PROCEEDINGS OF THE KONINKLIJKE AKADEMIE VAN WETENSCHAPPEN TE AMSTERDAM | O8: English | P8: Article | AF8: AVERY RC, 1922, BACT ABSTRACTS, V6, P31; Borsook H, 1931, J BIOL CHEM, V92, P535; CLARK WM, 1925, 8 PUBL HLTH WASH, V40, P1131; CLARK WM, 1928, PUBLIC HLTH SERVICE, V151; EHRLICH P, 1885, FARBEN ANAL STUDIE; Elema B, 1934, BIOCHEM Z, V270, P317; ELEMA B, 1932, BEPALING OXYDATIE RE; Fromageot C, 1935, BIOCHEM Z, V279, P34; Gillespie LJ, 1920, SOIL SCI, V9, P199, DOI 10.1097/00010694-192004000-00001; HELMHOLTZ H, 1844, J PRAKT CHEM, V31, P429; HEWITT LF, 1935, OXIDATION REDUCTION; HOOGERHEIDE JC, 1935, BIJDRAGE KENNIS REAC; Kluyver AJ, 1934, BIOCHEM Z, V272, P197; LEHMANN J, 1925, SKAND ARCH PHYSL, V46, P339; MICHAELIS L, 1933, OXYDATIONS REDUCTION; Potter MC, 1911, P R SOC LOND B-CONTA, V84, P260, DOI 10.1098/rspb.1911.0073; Quastel JH, 1924, BIOCHEM J, V18, P519, DOI 10.1042/bj0180519; RUDOLF J, 1926, CENTRALBL BAKT 1, V100, P147; SHERMAN JM, 1918, J BACTERIOL, V3, P168; SZENTGYORGYI A, 1933, Z PHYSL CHEM, V217, P51; Wurmser R, 1932, CR HEBD ACAD SCI, V195, P81; WURMSER R, 1935, ELECTROACTIVITE CHIM; Wurmser R, 1930, OXYDATIONS REDUCTION; Yudkin J, 1935, BIOCHEM J, V29, P1130, DOI 10.1042/bj0291130 | AG8: 24 | AH8: 0 | AI8: 0 | AJ8: 1 | AK8: 2 | AL8: ELSEVIER SCIENCE BV | AM8: AMSTERDAM | AN8: PO BOX 211, 1000 AE AMSTERDAM, NETHERLANDS | AR8: P K AKAD WET-AMSTERD | AS8: Proc. K. Akad. Wet.-Amsterdam | AU8: 1936 | AV8: 39 | AW8: 43586 | BB8: 298 | BC8: 305 | BI8: 8 | BJ8: Multidisciplinary Sciences | BK8: Science & Technology - Other Topics | BL8: V37IW | BM8: WOS:000202524200041 | BR8: 43703
A9: 8 | B9: 10.2307/2436655 | C9: J | D9: McAlister, DF | H9: McAlister, DF | K9: Effect of fungi on the oxidation-reduction potentials of liquid culture media | L9: AMERICAN JOURNAL OF BOTANY | O9: English | P9: Article | Y9: US Dept Agr, Bureau Plant Ind, Logan, UT USA | AF9: AUBEL E, 1929, ANN PHYSL PHYSICOCHI, V5, P1; CANNAN RK, 1926, US PUBLIC HLTH REP S, V55; CLARK WM, 1923, US PUB HLTH REPTS, V38, P666; Haber F, 1909, Z PHYS CHEM-STOCH VE, V67, P385; HEWITT LF, 1933, OXIDATION REDUCTION; Kluyver AJ, 1934, BIOCHEM Z, V272, P197; Partridge HM, 1929, J AM CHEM SOC, V51, P1, DOI 10.1021/ja01376a001; Pinckard JA, 1935, J AGRIC RES, V50, P0933; Potter MC, 1911, P R SOC LOND B-CONTA, V84, P260, DOI 10.1098/rspb.1911.0073; RICHARDS HM, 1997, JB WISSENSCHAFTLICHE, V30, P665; Robbins WJ, 1937, AM J BOT, V24, P243, DOI 10.2307/2436609; Tang PS, 1936, J CELL COMPAR PHYSL, V9, P149, DOI 10.1002/jcp.1030090113 | AG9: 12 | AH9: 4 | AI9: 4 | AJ9: 0 | AK9: 0 | AL9: BOTANICAL SOC AMER INC | AM9: COLUMBUS | AN9: OHIO STATE UNIV-DEPT BOTANY, 1735 NEIL AVE, COLUMBUS, OH 43210 USA | AO9: 0002-9122 | AR9: AM J BOT | AS9: Am. J. Bot. | AT9: APR | AU9: 1938 | AV9: 25 | AW9: 4 | BB9: 286 | BC9: 295 | BE9: 10.2307/2436655 | BI9: 10 | BJ9: Plant Sciences | BK9: Plant Sciences | BL9: V06XF | BM9: WOS:000200465900008 | BR9: 43703
A10: 9 | C10: J | D10: Ward, WE | H10: Ward, WE | K10: The apparent oxidation-reduction potentials of bright platinum electrodes in synthetic media cultures of bacteria | L10: JOURNAL OF BACTERIOLOGY | O10: English | P10: Article | Y10: Univ Chicago, Dept Bacteriol & Parasitol, Chicago, IL USA | AF10: Allyn WP, 1932, J BACTERIOL, V23, P369; Elema B, 1934, BIOCHEM Z, V270, P317; GILLESPIE RWH, 1934, J BACTERIOL, V31, P14; KLUYVER AJ, 1936, ENZYMOLOGIA, V1, P1; Knight BCJG, 1937, BIOCHEM J, V31, P731, DOI 10.1042/bj0310731; Koser SA, 1935, J INFECT DIS, V56, P305, DOI 10.1093/infdis/56.3.305; Koser SA, 1936, J INFECT DIS, V58, P121, DOI 10.1093/infdis/58.1.121; Longsworth LG, 1936, J BACTERIOL, V32, P567; Mudge CS, 1933, P SOC EXP BIOL MED, V31, P154; Mueller JH, 1937, J BACTERIOL, V34, P381; Mueller JH, 1937, J BACTERIOL, V34, P429; Potter MC, 1911, P R SOC LOND B-CONTA, V84, P260, DOI 10.1098/rspb.1911.0073; Sahyun M, 1936, J INFECT DIS, V58, P28, DOI 10.1093/infdis/58.1.28 | AG10: 13 | AH10: 5 | AI10: 5 | AJ10: 0 | AK10: 0 | AL10: AMER SOC MICROBIOLOGY | AM10: WASHINGTON | AN10: 1752 N ST NW, WASHINGTON, DC 20036-2904 USA | AO10: 0021-9193 | AR10: J BACTERIOL | AS10: J. Bacteriol. | AT10: OCT | AU10: 1938 | AV10: 36 | AW10: 4 | BB10: 337 | BC10: 355 | BI10: 19 | BJ10: Microbiology | BK10: Microbiology | BL10: V00ZC | BM10: WOS:000200065200001 | BN10: 16560157 | BR10: 43703
A11: 10 | C11: J | D11: Gillespie, RWH; Rettger, LF | H11: Gillespie, RWH; Rettger, LF | K11: Bacterial oxidation-reduction studies I Differentiation of species of the spore-forming anaerobes by potentiometric technique | L11: JOURNAL OF BACTERIOLOGY | O11: English | P11: Article | Y11: Yale Univ, Dept Bacteriol, New Haven, CT USA | AF11: BOYD ELDON M., 1931, CANADIAN JOUR RES, V4, P605; BOYD ELDON M., 1931, CANADIAN JOUR RES, V4, P54; Burrows W, 1936, J INFECT DIS, V58, P259, DOI 10.1093/infdis/58.3.259; Burrows W, 1935, J INFECT DIS, V56, P255, DOI 10.1093/infdis/56.3.255; CANNAN RK, 1926, STUDIES OXIDATION S, V55; CLARK WM, 1923, STUDIES OXIDATION RE, V38, P933; CLARK WM, 1923, STUDIES OXIDATION RE, V38, P666; DuBois D, 1930, J BIOL CHEM, V88, P729; Gillespie LJ, 1920, SOIL SCI, V9, P199, DOI 10.1097/00010694-192004000-00001; GILLESPIE RWH, 1936, J BACTERIOL, V31, P101; GILLESPIE RWH, 1936, J BACTERIOL, V31, P14; GILLESPIE RWH, 1937, J BACTERIOL, V33, P112; Hewitt LF, 1930, BIOCHEM J, V24, P1551, DOI 10.1042/bj0241551; Hewitt LF, 1931, BIOCHEM J, V25, P1452, DOI 10.1042/bj0251452; Hewitt LF, 1931, BIOCHEM J, V25, P2068, DOI 10.1042/bj0252068; Hewitt LF, 1931, BIOCHEM J, V25, P1641, DOI 10.1042/bj0251641; Hewitt LF, 1931, BIOCHEM J, V25, P1447, DOI 10.1042/bj0251447; Hewitt LF, 1930, BIOCHEM J, V24, P669, DOI 10.1042/bj0240669; Hewitt LF, 1930, BIOCHEM J, V24, P676, DOI 10.1042/bj0240676; Hewitt LF, 1931, BIOCHEM J, V25, P858, DOI 10.1042/bj0250858; Hewitt LF, 1930, BIOCHEM J, V24, P512, DOI 10.1042/bj0240512; Hewitt LF, 1931, BIOCHEM J, V25, P169, DOI 10.1042/bj0250169; HEWITT LF, 1933, OXIDATION REDUCTION, P81; Knight BCJG, 1930, BIOCHEM J, V24, P1075, DOI 10.1042/bj0241075; Knight BCJG, 1930, BIOCHEM J, V24, P1066, DOI 10.1042/bj0241066; Lepper E, 1930, BRIT J EXP PATHOL, V11, P140; Lepper EH, 1931, BIOCHEM J, V25, P45, DOI 10.1042/bj0250045; PLOTZ HARRY, 1930, ANN INST PASTEUR [PARIS], V45, P613; Potter MC, 1911, P R SOC LOND B-CONTA, V84, P260, DOI 10.1098/rspb.1911.0073; Sagen HE, 1934, J BACTERIOL, V28, P571; Tuttle CD, 1934, J INFECT DIS, V54, P259, DOI 10.1093/infdis/54.2.259 | AG11: 31 | AH11: 7 | AI11: 7 | AJ11: 0 | AK11: 0 | AL11: AMER SOC MICROBIOLOGY | AM11: WASHINGTON | AN11: 1752 N ST NW, WASHINGTON, DC 20036-2904 USA | AO11: 0021-9193 | AR11: J BACTERIOL | AS11: J. Bacteriol. | AT11: DEC | AU11: 1938 | AV11: 36 | AW11: 6 | BB11: 605 | BC11: 620 | BI11: 16 | BJ11: Microbiology | BK11: Microbiology | BL11: V00ZE | BM11: WOS:000200065400004 | BN11: 16560179 | BR11: 43703
A12: 11 | B12: 10.1126/science.137.3530.615 | C12: J | D12: DAVIS, JB; YARBROUGH, HF | H12: DAVIS, JB; YARBROUGH, HF | K12: PRELIMINARY EXPERIMENTS ON A MICROBIAL FUEL CELL | L12: SCIENCE | O12: English | P12: Article | AF12: Cohen B., 1931, J BACTERIOL, V21, P18; HANSEN RW, 1957, SCIENCE, V125, P1198, DOI 10.1126/science.125.3259.1198; MASON HS, 1957, ADV ENZYMOL REL S BI, V19, P79; Potter MC, 1911, P R SOC LOND B-CONTA, V84, P260, DOI 10.1098/rspb.1911.0073; STEWART JE, 1959, J BACTERIOL, V78, P441 | AG12: 5 | AH12: 88 | AI12: 91 | AJ12: 2 | AK12: 99 | AL12: AMER ASSOC ADVANCEMENT SCIENCE | AM12: WASHINGTON | AN12: 1200 NEW YORK AVE, NW, WASHINGTON, DC 20005 | AO12: 0036-8075 | AR12: SCIENCE | AS12: Science | AU12: 1962 | AV12: 137 | AW12: 3530 | BB12: 615 | BC12: & | BE12: 10.1126/science.137.3530.615 | BI12: 0 | BJ12: Multidisciplinary Sciences | BK12: Science & Technology - Other Topics | BL12: 3025C | BM12: WOS:A19623025C00005 | BN12: 17836545 | BR12: 43703
A13: 12 | B13: 10.1002/jobm.3630050105 | C13: J | D13: JACOB, HE; HORN, G | H13: JACOB, HE; HORN, G | K13: KONTINUIERLICHE REGISTRIERUNG PHYSIKOCHEMISCHER MESSGROSSEN IN BAKTERIENKULTUREN .2. DER EINFLUSS VON GELOSTSAUERSTOFF AUF REDOXPOTENTIALMESSUNGEN IN BAKTERIENKULTUREN | L13: ZEITSCHRIFT FUR ALLGEMEINE MIKROBIOLOGIE | O13: English | P13: Article | AF13: ALDERTON G, 1945, J BIOL CHEM, V157, P43; ALDERTON G, 1946, J BIOL CHEM, V164, P1; Breed RS, 1957, BERGEYS MANUAL DETER; CAPPELLATO M., 1960, BOLL IST SIERQTERAP MILAN, V39, P40; CATER DB, 1957, PROC R SOC SER B-BIO, V146, P382, DOI 10.1098/rspb.1957.0019; CATER DB, 1957, PROC R SOC SER B-BIO, V146, P400, DOI 10.1098/rspb.1957.0020; FLASCHENTRAGER B, 1951, PHYSIOLOGISCHE CHEMI; Fleming A, 1922, P R SOC LOND B-CONTA, V93, P306, DOI 10.1098/rspb.1922.0023; Gillespie LJ, 1920, SOIL SCI, V9, P199, DOI 10.1097/00010694-192004000-00001; GOLDBACH W, 1963, ACTA BIOL MED GER, V10, P579; GOLDBACH W, 1961, 2 ATT S INT LIS FLEM, P131; GOLDBACH W, 1962, Z ALLG MIKROBIOL, V2, P185; HAVEMANN R, 1959, Z PHYS CHEM, V211, P267; Hewitt L.F., 1950, OXIDATION REDUCTION; HORN G, 1963, MONATSBERICHTE DEUTS, V5, P227; HORN G, 1964, CHEM TECHN, V16, P237; HORN G, IN PREPARATION; HOUBENWEIL, 1955, METHODEN ORGANISCHEN; INOUE K, 1959, BIKEN J, V2, P1; JACOB HE, IN PREPARATION; JACOB HE, 1964, HYG 1, V192, P315; JACOB HE, 1964, ABH AKAD WISS BERLIN, P320; JOLLES P, 1960, BIOCHIM BIOPHYS ACTA, V39, P212, DOI 10.1016/0006-3002(60)90155-4; JOLLES P, 1957, CR SOC BIOL, V151, P1368; JOLLES P, 1964, ANGEW CHEM, V76, P20; KONIG E, 1964, Z CHEM, V4, P95; KOVACS E, 1958, NATURWISSENSCHAFTEN, V45, P285, DOI 10.1007/BF00622873; KOVACS E, 1957, NATURWISSENSCHAFTEN, V44, P280, DOI 10.1007/BF00597329; LENGYEL Z, 1962, AEROB FERMENTACIOK O; MALKE H., 1964, Z ALLG MIRROBIOL, V4, P88, DOI 10.1002/jobm.3630040108; MATKOVICS B, 1958, NATURWISSENSCHAFTEN, V45, P168, DOI 10.1007/BF00622011; MATKOVICS B., 1959, SCHWEIZ ZEITSCHR ALLG PATH U BAKT, V22, P214; Meyer K, 1936, J BIOL CHEM, V113, P303; MICHAELIS L, 1933, OXYDATIONS REDUKTION; MUSCHEL LH, 1959, J IMMUNOL, V82, P38; NETTER H, 1959, THEORETISCHE BIOCHEM; Potter MC, 1911, P R SOC LOND B-CONTA, V84, P260, DOI 10.1098/rspb.1911.0073; RABOTNOWA I, 1963, BEDEUTUNG PHYSIKALIS; RICHMOND MH, 1957, J GEN MICROBIOL, V16, pR4; RUMMENI G, 1954, WISS Z U JENA MN, V4, P611; RUMMENI G, 1954, BER DTSCH BOT GES, V67, P335; SALTON MRJ, 1957, BACTERIOL REV, V21, P82; SMITH EL, 1955, J BIOL CHEM, V215, P67; SMITH GN, 1949, ARCH BIOCHEM, V21, P383; SQUIRES RW, 1958, IND ENG CHEM, V50, P1263, DOI 10.1021/ie50585a032; Steinhaus EA, 1949, PRINCIPLES INSECT PA; STROHBACH G, 1963, THESIS JENA; TENGERDY RP, 1962, J BIOCHEM MICROBIOL, V3, P255; TENGERDY RP, 1962, J BIOCH MICROBIOL TE, V3, P241; TODT F, 1958, ELEKTROCHEMISCHE SAU; VETTER K, 1961, ELEKTROCHEMISCHE KIN; VONSTACKELBERG M, 1955, METHODEN ORGANISCHEN; WAGNER RR, 1961, BACTERIOL REV, V25, P100; WARTENBERG H, 1953, WISS Z SCHILLER U JE, V2, P53; WARTENBERG HANS, 1957, BER DEUTSCH BOT GES, V70, P79; WEIDEL W, 1958, J GEN MICROBIOL, V18, P513, DOI 10.1099/00221287-18-2-513; ZIEGLER E, 1960, ARZNEIMITTEL FORSCHU | AG13: 57 | AH13: 10 | AI13: 10 | AJ13: 0 | AK13: 0 | AL13: AKADEMIE VERLAG GMBH | AM13: BERLIN | AN13: MUHLENSTRASSE 33-34, D-13187 BERLIN, GERMANY | AO13: 0044-2208 | AR13: Z ALLG MIKROBIOL | AU13: 1965 | AV13: 5 | AW13: 1 | BB13: 33 | BC13: & | BE13: 10.1002/jobm.3630050105 | BI13: 0 | BJ13: Biotechnology & Applied Microbiology; Microbiology | BK13: Biotechnology & Applied Microbiology; Microbiology | BL13: 63699 | BM13: WOS:A19656369900004 | BN13: 4961479 | BR13: 43703
A14: 13 | B14: 10.1002/bit.260080410 | C14: J | D14: YOUNG, TG; HADJIPETROU, L; LILLY, MD | H14: YOUNG, TG; HADJIPETROU, L; LILLY, MD | K14: THEORETICAL ASPECTS OF BIOCHEMICAL FUEL CELLS | L14: BIOTECHNOLOGY AND BIOENGINEERING | O14: English | P14: Article | AF14: BENJAMIN L, 1955, REPORT CENTR ELECTRI; Clark W. M., 1960, OXIDATION REDUCTION; Cohen B., 1931, J BACTERIOL, V21, P18; DELDUCA MG, 1962, P ANNU POWER SOURCE, V16, P81; GOLDMER BH, 1962, P ANNU POWER SOURCE, V16, P70; Gunsalus I. C., 1961, BACTERIA, V2, P1; Hewitt L.F., 1950, OXIDATION REDUCTION; LILLY M, 1965, BIOCHEM J, V95, pP45; LONGMUIR IS, 1954, BIOCHEM J, V57, P81, DOI 10.1042/bj0570081; MAY PS, 1964, P ANNU POWER SOURCE, V18, P1; Michaelis L, 1913, BIOCHEM Z, V49, P333; Monod J., 1942, RECHERCHES CROISSANC; Potter MC, 1911, P R SOC LOND B-CONTA, V84, P260, DOI 10.1098/rspb.1911.0073; Wood WA, 1961, BACTERIA, VII, P59 | AG14: 14 | AH14: 13 | AI14: 13 | AJ14: 2 | AK14: 5 | AL14: WILEY | AM14: HOBOKEN | AN14: 111 RIVER ST, HOBOKEN 07030-5774, NJ USA | AO14: 0006-3592 | AP14: 1097-0290 | AR14: BIOTECHNOL BIOENG | AS14: Biotechnol. Bioeng. | AU14: 1966 | AV14: 8 | AW14: 4 | BB14: 581 | BC14: + | BE14: 10.1002/bit.260080410 | BI14: 1 | BJ14: Biotechnology & Applied Microbiology | BK14: Biotechnology & Applied Microbiology | BL14: 86984 | BM14: WOS:A19668698400009 | BR14: 43703
A15: 14 | C15: J | D15: CENEK, M | H15: CENEK, M | K15: BIOCHEMICAL FUEL CELLS | L15: CHEMICKE LISTY | O15: English | P15: Review | AF15: ALLEN MJ, 1963, ELECTROCHIM ACTA, V8, P419; BERK RS, 1964, APPL MICROBIOL, V12, P10; BLANCHARD GC, 1963, 17 P ANN POW SOURC C; BOYER MH, 1964, STUDY BASIC BIOELECT; BOYER MH, 1963, STUDY BASIC BIOELECT; BRAKE JM, 1963, 3 MAGN CORP QUART PR; BRAKE JM, 1963, 5 MAGN CORP QUART PR; BRAKE JM, 1963, 17 ANN P POW SOURC C; BRAKE JM, 1963, 4 MAGN CORP QUART PR; CAVALLO JJ, 1964, 7 MAGN CORP QUART PR; CLARK WM, 1960, OXIDATIONREDUCTION P; Cohen B., 1931, J BACTERIOL, V21, P18; COHN ME, 1963, DEV IND MICROBIOL, V4, P53; ELLIS GE, 1963, 2 MARQ CORP QUART RE; ELLIS GE, 1963, 1 MARQ CORP QUART PR; ELLIS GE, 1964, 3 MARQ CORP QUART PR; EULER J, 1964, ETZB, V16, P16; HAACKE O, 1892, FLORA, P75; HAMPEL CA, 1964, ENCYCLOPEDIA ELECTRO, P103; KARLSON P, 1965, ZAKLADY BIOCHEMIE, P206; KONIKOFF JJ, 1963, ELECTRICAL ENERGY BI; KOSTIR J, 1965, CHEMIE FYSIKA ZIVYCH, P215; Potter MC, 1911, P R SOC LOND B-CONTA, V84, P260, DOI 10.1098/rspb.1911.0073; ROHRBACK GH, 1962, 16 ANN P POW SOURC C; ROSENWALD AJ, 1962, APPL MICROBIOL, V10, P345; SCOTT WR, 1962, SEP P EL WORK GROUP; SHAW M, 1963, 17 ANN P POW SOURC C; SISLER FD, 1961, NEW SCI, V12, P256; SISLER FD, 1964, GLOBAL IMPACTS APPLI; SUZUKI, 1964, CHEM CHEM IND, V17, P1359; SUZUKI M, 1964, J CHEM SOC JAP, V67, P410; SUZUKI M, 1962, J CHEM SOC JAP, V65, P1606; SUZUKI M, 1964, 31 C EL SOC JAP; SUZUKI M, 1964, J CHEM SOC JAP, V67, P1887; TAYLOR JE, 1963, CHEM ING PROGR, V59, P10; WILLIAM KR, 1966, INTRODUCTION FUEL CE, P256; WILSON BJ, 1962, NOV P BIOCH FUEL CEL; YAHIRO AT, 1964, BIOCHIM BIOPHYS ACTA, V88, P375, DOI 10.1016/0926-6577(64)90192-5; 1964, ELEC REV, V10, P46 | AG15: 39 | AH15: 15 | AI15: 15 | AJ15: 0 | AK15: 0 | AL15: CHEMICKE LISTY | AM15: PRAGUE 6 | AN15: PELLEOVA 24, PRAGUE 6 160 00, CZECH REPUBLIC | AO15: 0009-2770 | AR15: CHEM LISTY | AS15: Chem. Listy | AU15: 1968 | AV15: 62 | AW15: 8 | BB15: 927 | BC15: & | BI15: 0 | BJ15: Chemistry, Multidisciplinary | BK15: Chemistry | BL15: B6999 | BM15: WOS:A1968B699900003 | BR15: 43703
A16: 15 | B16: 10.1177/00220345690480053101 | C16: J | D16: PARKER, RB | H16: PARKER, RB | K16: BIOELECTRIC PHENOMENA IN DENTAL DECAY | L16: JOURNAL OF DENTAL RESEARCH | O16: English | P16: Article | AF16: BARKER RB, 1964, LIFE SCI, V3, P1275; BECKER RO, 1964, INT S BONE DYNAMICS, P209; BRIDGMAN WK, 1961, T ODONT SOC GR BRIT, V111, P369; CHICK AO, 1963, J DENT RES, V42, P934, DOI 10.1177/00220345630420041801; FUKADA E, 1957, J PHYS SOC JPN, V12, P1158, DOI 10.1143/JPSJ.12.1158; HORVATH J, 1960, ACTA CHIM HUNG, V25, P65; Klein H, 1929, J DENT RES, V9, P667; LEWIS K, 1966, BACTERIOL REV, V30, P101; MANLY RS, 1966, ARCH ORAL BIOL, V11, P931, DOI 10.1016/0003-9969(66)90083-5; MAYUZUMI Y, 1964, J DENT RES, V43, P941; PARKER RB, 1967, ARCH ORAL BIOL, V12, P131, DOI 10.1016/0003-9969(67)90149-5; Potter MC, 1911, P R SOC LOND B-CONTA, V84, P260, DOI 10.1098/rspb.1911.0073; RINDNER W, 1962, B AM PHYS SOC, V7, P65; WOOLLEY L, 1966, THESIS U OREGON DENT | AG16: 14 | AH16: 0 | AI16: 1 | AJ16: 0 | AK16: 0 | AL16: AMER ASSOC DENTAL RESEARCH | AM16: ALEXANDRIA | AN16: 1619 DUKE ST, ALEXANDRIA, VA 22314 | AO16: 0022-0345 | AR16: J DENT RES | AS16: J. Dent. Res. | AU16: 1969 | AV16: 48 | AW16: 5P1S | BB16: 795 | BC16: & | BE16: 10.1177/00220345690480053101 | BI16: 0 | BJ16: Dentistry, Oral Surgery & Medicine | BK16: Dentistry, Oral Surgery & Medicine | BL16: E4365 | BM16: WOS:A1969E436500030 | BN16: 5259419 | BR16: 43703
A17: 16 | B17: 10.1149/1.2408290 | C17: J | D17: BLANCHARD, GC; FOLEY, RT | H17: BLANCHARD, GC; FOLEY, RT | K17: OPERATION OF AN ION-MEMBRANE FUEL CELL WITH MICROBIALLY-PRODUCED HYDROGEN | L17: JOURNAL OF THE ELECTROCHEMICAL SOCIETY | O17: English | P17: Article | AF17: ABEL K, 1964, ANAL CHEM, V36, P954, DOI 10.1021/ac60210a085; BLANCHARD GC, 1963, 17 P ANN POW SOURC C; BLANCHARD GC, TO BE PUBLISHED; BLANCHARD GC, 1965, 149 AM CHEM SOC M DE; BOYD ELDON M., 1931, CANADIAN JOUR RES, V4, P605; Clifton CE, 1934, J BACTERIOL, V28, P541; Cohen B., 1931, J BACTERIOL, V21, P18; HAYNES WC, 1955, APPL MICROBIOL, V3, P361; Johnstone KI, 1942, J PATHOL BACTERIOL, V54, P25, DOI 10.1002/path.1700540104; KRICHEVSKY M, 1961, J BIOL CHEM, V236, P2520; LEWIS K, 1966, BACTERIOL REV, V30, P101; MAY PJ, 1964, 18 P ANN POW SOURC C; PERRY J, 1965, 19 P ANN POW SOURC C, P19; Potter MC, 1911, P R SOC LOND B-CONTA, V84, P260, DOI 10.1098/rspb.1911.0073; QUINN LY, 1964, PERSONAL COMMUNICATI; ROHRBACK GH, 1962, 16 ANN POW SOURC C A; SILVERMAN HP, 1962, DA36039SC90866 CONTR; SISLER FD, 1961, NEW SCIENTIST, V12, P110; WILSON BJ, 1963, NRL5998 REP | AG17: 19 | AH17: 3 | AI17: 3 | AJ17: 0 | AK17: 1 | AL17: ELECTROCHEMICAL SOC INC | AM17: PENNINGTON | AN17: 65 SOUTH MAIN STREET, PENNINGTON, NJ 08534 USA | AO17: 0013-4651 | AP17: 1945-7111 | AR17: J ELECTROCHEM SOC | AS17: J. Electrochem. Soc. | AU17: 1971 | AV17: 118 | AW17: 7 | BB17: 1232 | BC17: + | BE17: 10.1149/1.2408290 | BI17: 1 | BJ17: Electrochemistry; Materials Science, Coatings & Films | BK17: Electrochemistry; Materials Science | BL17: J6909 | BM17: WOS:A1971J690900050 | BR17: 43703
A18: 17 | B18: 10.1002/jobm.3630110809 | C18: J | D18: JACOB, HE | H18: JACOB, HE | K18: REDOX POTENTIAL IN BACTERIA CULTURES | L18: ZEITSCHRIFT FUR ALLGEMEINE MIKROBIOLOGIE | O18: German | P18: Article | AF18: BARD AJ, 1961, ANAL CHEM, V33, P11, DOI 10.1021/ac60169a002; BARTELS H, 1959, NATURWISSENSCHAFTEN, V46, P672, DOI 10.1007/BF00594822; BAUMBERGER IH, 1939, COLD SPRING HARBOR S, V7, P318; BELJUSTIN AA, 1964, BER AKAD WISS USSR, V154, P404; BERG HC, IN PRESS; BOCKRIS JO, 1970, MODERN ELECTROCHEMIS; Breed RS, 1957, BERGEYS MANUAL DETER; BREITER MW, 1962, J ELECTROCHEM SOC, V109, P425, DOI 10.1149/1.2425436; BREITER MW, 1962, ELECTROCHIM ACTA, V7, P601; CATER DB, 1957, PROC R SOC SER B-BIO, V146, P382, DOI 10.1098/rspb.1957.0019; CATER DB, 1957, P ROY SOC LONDON B, V146, P288; CLARK LC, 1953, J APPL PHYSIOL, V6, P189; Clark W. M., 1960, OXIDATION REDUCTION; COHEN B, 1957, MANUAL MICROBIOLOGIC, P72; DRAWERT H, 1956, HDB PFLANZENPHYSIOLO, P252; Gillespie LJ, 1920, SOIL SCI, V9, P199, DOI 10.1097/00010694-192004000-00001; GINER VJ, 1960, Z ELEKTROCHEM, V64, P491; Gray-Young T., 1966, BIOTECHNOL BIOENG, V8, P581; GRECHUSHKINA N. N., 1965, MIKROBIOLOGIYA, V34, P200; GROSZ HJ, 1967, NATURE, V213, P717, DOI 10.1038/213717a0; Harrop GA, 1928, J EXP MED, V48, P207, DOI 10.1084/jem.48.2.207; HAVEMANN R, 1959, Z PHYS CHEM, V211, P267; HEIDENREICH J, 1970, EXPERIENTIA, V26, P257, DOI 10.1007/BF01900080; Hewitt L.F., 1950, OXIDATION REDUCTION; HOARE JP, 1963, J ELECTROCHEM SOC, V110, P1019, DOI 10.1149/1.2425914; HOARE JP, 1965, J ELECTROCHEM SOC, V112, P602, DOI 10.1149/1.2423616; HORN H, 1964, Z ALLG MIKR, V4, P1; HORN H, 1966, ANTIBIOTICS ADVANCES, P761; Jacob H.E., 1970, METHOD MICROBIOL, V2, P91; JACOB HE, 1967, Z ALLG MIKROBIOL, V7, P407, DOI 10.1002/jobm.3630070510; JACOB HE, 1965, Z ALLG MIKROBIOL, V5, P33, DOI 10.1002/jobm.3630050105; JACOB HE, 1969, ENZYMOLOGIA, V36, P313; JACOB HE, 1969, STUD BIOPHYS, V14, P151; JACOB HE, 1966, MBER DTSCH AKAD WISS, V8, P924; KANTERE VM, 1971, 1 INT S BIOL ASP E; KONIG E, 1964, Z CHEM, V4, P95; KORDATZKI W, 1953, ARCH PHARM, V286, P43; KOVACS E, 1958, NATURWISSENSCHAFTEN, V45, P285, DOI 10.1007/BF00622873; LEMAN A, 1965, ARCH MIKROBIOL, V50, P357, DOI 10.1007/BF00509577; LEMAN A, 1965, ARCH MIKROBIOL, V50, P194, DOI 10.1007/BF00409128; LEMAN A, 1965, ARCH MIKROBIOL, V55, P134; LENGYEL ZL, 1965, BIOTECHNOL BIOENG, V7, P91, DOI 10.1002/bit.260070120; LENGYEL ZL, 1961, 5 INT C BIOL CHEM MO; LEPETIT G, 1962, CHEM TECHN, V14, P471; Lepper E, 1930, BRIT J EXP PATHOL, V11, P140; Lepper EH, 1931, BIOCHEM J, V25, P45, DOI 10.1042/bj0250045; LOESCHE WJ, 1969, APPL MICROBIOL, V18, P723; MAREK N, 1966, ACTA BIOL ACAD SCI H, V16, P319; MATVOVICS B, 1959, SCHWEIZ Z ALLG PATHO, V22, P214; MEISEL MN, 1952, MIKROBIOLOGIA, V11, P51; MICHAELIS L, 1929, OXYDATIONS REDUKTION; Potter MC, 1911, P R SOC LOND B-CONTA, V84, P260, DOI 10.1098/rspb.1911.0073; POTTER MC, 1910, DURHAM U PHIL SOC P, V3; RABOTNOWA I, 1963, BEDEUTUNG PHYSIKALIS; SCHLEGEL HG, 1969, ALLGEMEINE MIKROBIOL; SCHULDINER S, 1966, J ELECTROCHEM SOC, V113, P573, DOI 10.1149/1.2424029; SQUIRES RW, 1958, IND ENG CHEM, V50, P1263, DOI 10.1021/ie50585a032; TELCS I, 1968, ACTA CHIM HUNG, V58, P417; TENGERDY RP, 1961, J BIOCHEM MICROBIOL, V3, P241, DOI 10.1002/jbmte.390030304; THIMANN KV, 1964, LEBEN BAKTERIEN; VETTER K, 1961, ELEKTROCHEMISCHE KIN; Wartenberg H, 1939, BIOCHEM Z, V302, P262; WARTENBERG H, 1958, WISS Z FRIEDRICH MIV, V8, P193; WARTENBERG HANS, 1957, BER DEUTSCH BOT GES, V70, P79; WIMPENNY JW, 1969, BIOTECHNOL BIOENG, V11, P623, DOI 10.1002/bit.260110409; WROBLOWA H, 1967, J ELECTROANAL CHEM, V15, P139, DOI 10.1016/0022-0728(67)85018-6 | AG18: 66 | AH18: 7 | AI18: 7 | AJ18: 0 | AK18: 0 | AL18: AKADEMIE VERLAG GMBH | AM18: BERLIN | AN18: MUHLENSTRASSE 33-34, D-13187 BERLIN, GERMANY | AO18: 0044-2208 | AR18: Z ALLG MIKROBIOL | AU18: 1971 | AV18: 11 | AW18: 8 | BB18: 691 | BC18: & | BE18: 10.1002/jobm.3630110809 | BI18: 0 | BJ18: Biotechnology & Applied Microbiology; Microbiology | BK18: Biotechnology & Applied Microbiology; Microbiology | BL18: L6508 | BM18: WOS:A1971L650800008 | BN18: 4947991 | BR18: 43703
A19: 18 | B19: 10.1002/bit.260171011 | C19: J | D19: VIDELA, HA; ARVIA, AJ | H19: VIDELA, HA; ARVIA, AJ | K19: RESPONSE OF A BIOELECTROCHEMICAL CELL WITH SACCHAROMYCES-CEREVISIAE METABOLIZING GLUCOSE UNDER VARIOUS FERMENTATION CONDITIONS | L19: BIOTECHNOLOGY AND BIOENGINEERING | O19: English | P19: Article | Y19: UNIV NACL LA PLATA,FAC CIENCIAS EXACTAS,INST INVEST FISICOQUIM TEORICAS & APLICADAS,DIV,LA PLATA,ARGENTINA | AF19: Gray-Young T., 1966, BIOTECHNOL BIOENG, V8, P581; JACOB HE, 1970, METHODS MICROBIOLOGY, V2, P105; JOHNSON MJ, 1964, BIOTECHNOL BIOENG, V6, P457, DOI 10.1002/bit.260060407; MARTINS ME, 1969, AN ASOC QUIM ARGENT, V57, P91; MAXON WD, 1953, IND ENG CHEM, V45, P2554, DOI 10.1021/ie50527a051; PAUS G, 1971, AN SOC CIENT ARGENT, V192, P35; Potter MC, 1911, P R SOC LOND B-CONTA, V84, P260, DOI 10.1098/rspb.1911.0073; RUIZAMIL M, 1956, ARCH MIKROBIOL, V55, P46; SOLS A, 1971, YEASTS, V2, P282; SUOMALAINEN H, 1971, YEASTS, V2, P28; van Uden N, 1971, YEASTS, V2, P75; Videla H. A., 1971, EXPERIENTIA S, V18, P667; VIDELA HA, IN PRESS; WHITE J, 1954, YEAST TECHNOLOGY, P243; WHITE J, 1954, YEAST TECHNOLOGY, P63 | AG19: 15 | AH19: 29 | AI19: 29 | AJ19: 0 | AK19: 0 | AL19: JOHN WILEY & SONS INC | AM19: NEW YORK | AN19: 605 THIRD AVE, NEW YORK, NY 10158-0012 | AO19: 0006-3592 | AR19: BIOTECHNOL BIOENG | AS19: Biotechnol. Bioeng. | AU19: 1975 | AV19: 17 | AW19: 10 | BB19: 1529 | BC19: 1543 | BE19: 10.1002/bit.260171011 | BI19: 15 | BJ19: Biotechnology & Applied Microbiology | BK19: Biotechnology & Applied Microbiology | BL19: AX169 | BM19: WOS:A1975AX16900010 | BN19: 241440 | BR19: 43703
A20: 19 | B20: 10.1097/00010694-197501000-00011 | C20: J | D20: DEELMAN, JC | H20: DEELMAN, JC | K20: BACTERIAL SULFATE REDUCTION AFFECTING CARBONATE SEDIMENTS | L20: SOIL SCIENCE | O20: English | P20: Article | Y20: UNIV HEIDELBERG,MINERAL PETRO INST,LAB SEDIMENT FORSCH,BERLINR STR 19,6900 HEIDELBERG,FED REP GER | AF20: ALLEN RC, 1969, J SEDIMENT PETROL, V39, P136, DOI 10.1306/74D71BF9-2B21-11D7-8648000102C1865D; BAARS JK, 1930, THESIS MEINEMA; Baas-Becking L.G.M., 1960, J GEOL, V68, P243; Bavendamm W, 1932, ARCH MIKROBIOLOGIE, V3, P205; Beijerinck M.W., 1895, CENTRALBL BAKTERIO 2, P1; BERNER RA, 1969, MAR GEOL, V7, P253, DOI 10.1016/0025-3227(69)90011-5; BERNER RA, 1971, PRINCIPLES CHEMICAL; Beyerinck M. W., 1895, CENTRALBL BAKTERIO 2, V1, P104; BEYERINCK MW, 1895, CENTRAL BAKT, V1, P49; CONNELL WE, 1969, SOIL SCI SOC AM PRO, V33, P711, DOI 10.2136/sssaj1969.03615995003300050026x; CONNELL WE, 1968, SCIENCE, V159, P86, DOI 10.1126/science.159.3810.86; FRIEDMAN GM, 1972, AM ASSOC PETR GEOL B, V56, P1072; Gillespie LJ, 1920, SOIL SCI, V9, P199, DOI 10.1097/00010694-192004000-00001; HATHAWAY JC, 1969, SCIENCE, V165, P690, DOI 10.1126/science.165.3894.690; HEWITT LF, 1931, OXIDATION REDUCTION; Lalou C, 1957, J SEDIMENT PETROL, V27, P190; LECHAVELIER HA, 1971, MICROBES; Mansfield C. W., 1960, OXIDATION REDUCTION; MOLISH H, 1925, CENTRBL BAKT, V65, P130; Monaghan P, 1956, J SEDIMENT PETROL, V26, P111; NADSON G. A., 1928, ARCH HYDROBIOL, V19, P154; POP LJJ, 1936, THESIS LEIDEN; Potter MC, 1911, P R SOC LOND B-CONTA, V84, P260, DOI 10.1098/rspb.1911.0073; PRESLEY BJ, 1968, GEOCHIM COSMOCHIM AC, V32, P1037, DOI 10.1016/0016-7037(68)90106-3; Rittenberg SC, 1940, J MAR RES, V3, P191; STATSHCHUK MF, 1972, OXIDATION REDUCTION; SWEENEY RE, 1973, ECON GEOL, V68, P618, DOI 10.2113/gsecongeo.68.5.618; SZENTGYORGYI A, 1968, BIOELECTRONICS; VANDELDEN A, 1904, CENT BAKT INFEKT 2, V11, P81; VANDELDEN A, 1904, CENT BAKT INFEKT 2, V11, P113; WOLZOGENKUHR CAH, 1923, P KONINKL AKAD WETEN, V25, P188; ZoBell C.E., 1946, MARINE MICROBIOLOGY; Zobell C. E., 1938, J SEDIMENT PETROL, V8, P10 | AG20: 33 | AH20: 5 | AI20: 5 | AJ20: 0 | AK20: 0 | AL20: WILLIAMS & WILKINS | AM20: BALTIMORE | AN20: 351 WEST CAMDEN ST, BALTIMORE, MD 21201-2436 | AO20: 0038-075X | AR20: SOIL SCI | AS20: Soil Sci. | AU20: 1975 | AV20: 119 | AW20: 1 | BB20: 73 | BC20: 80 | BE20: 10.1097/00010694-197501000-00011 | BI20: 8 | BJ20: Soil Science | BK20: Agriculture | BL20: V8118 | BM20: WOS:A1975V811800010 | BR20: 43703
A21: 20 | B21: 10.1002/jobm.3630150705 | C21: J | D21: JACOB, HE; STUR, JK; MAREK, N | H21: JACOB, HE; STUR, JK; MAREK, N | K21: INTERPRETATION OF REDOX POTENTIAL OF BIOLOGICAL OBJECTS .7. DETERMINATION WITH DIFFERENT PLATINUM-ELECTRODES IN SOLUTIONS OF ELECTROLYTES | L21: ZEITSCHRIFT FUR ALLGEMEINE MIKROBIOLOGIE | O21: German | P21: Article | Y21: DAWB,ZENT INST MIKROBIOL & EXPTL THERAPIE,FORSCH ZENTRUM MOLEKULARBIOL & MED,BEUTHENBERG STR 11,JENA,GER DEM REP; MED UNIV SZEGED,INST MED CHEM,SZEGED,HUNGARY | AF21: CLARK LC, 1953, J APPL PHYSIOL, V6, P189; Clark W. M., 1960, OXIDATION REDUCTION; CLARK WM, 1920, P SOC AM BACTERIOL, V4, P2; GALGOCZY B, IN PRESS; Gillespie LJ, 1920, SOIL SCI, V9, P199, DOI 10.1097/00010694-192004000-00001; Hewitt L.F., 1950, OXIDATION REDUCTION; HONGO M, 1972, AGR BIOL CHEM TOKYO, V36, P273; HORN G, 1964, 3RD INT C POL SOUTH, P943; Jacob H. E., 1974, BIOTECHNOL BIOENG S, V4, P781; JACOB HE, 1967, Z ALLG MIKROBIOL, V7, P407, DOI 10.1002/jobm.3630070510; JACOB HE, 1965, Z ALLG MIKROBIOL, V5, P33, DOI 10.1002/jobm.3630050105; JACOB HE, 1971, Z ALLG MIKROBIOL, V11, P691, DOI 10.1002/jobm.3630110809; JACOB HE, 1970, PATHOL MICROBIOL, V36, P57, DOI 10.1159/000162420; LENGYEL Z, 1962, AEROB FERMENTACIOK O; MAREK N, 1966, ACTA BIOL ACAD SCI H, V16, P319; MAREK N, 1967, THEORETISCHE EXPTL U, V6, P223; MAREK N, 1967, STUDIA BIOPHYS, V3, P255; MATKOVICS B., 1959, SCHWEIZ ZEITSCHR ALLG PATH U BAKT, V22, P214; MICHAELIS L, 1933, OXYDATIONS REDUKTION; Potter MC, 1911, P R SOC LOND B-CONTA, V84, P260, DOI 10.1098/rspb.1911.0073; RABOTNOWA I, 1963, BEDEUTUNG PHYSIKALIS; SQUIRES RW, 1958, IND ENG CHEM, V50, P1263, DOI 10.1021/ie50585a032; TENGERDY RP, 1962, J BIOCH MICROBIOL TE, V3, P241 | AG21: 23 | AH21: 0 | AI21: 0 | AJ21: 0 | AK21: 0 | AL21: AKADEMIE VERLAG GMBH | AM21: BERLIN | AN21: MUHLENSTRASSE 33-34, D-13187 BERLIN, GERMANY | AO21: 0044-2208 | AR21: Z ALLG MIKROBIOL | AU21: 1975 | AV21: 15 | AW21: 7 | BB21: 513 | BC21: 522 | BE21: 10.1002/jobm.3630150705 | BI21: 10 | BJ21: Biotechnology & Applied Microbiology; Microbiology | BK21: Biotechnology & Applied Microbiology; Microbiology | BL21: BA967 | BM21: WOS:A1975BA96700004 | BN21: 1210352 | BR21: 43703
A22: 21 | C22: J | D22: VIDELA, HA; ARVIA, AJ | H22: VIDELA, HA; ARVIA, AJ | K22: STUDY ON BIOLOGICAL FUEL CELL COUPLED TO DISCONTINUOUS FERMENTATION PROCESS | L22: ANALES DE LA ASOCIACION QUIMICA ARGENTINA | O22: Spanish | P22: Article | Z22: VIDELA, HA (reprint author), UNIV NACL LA PLATA,FAC CIENCIAS EXACTAS,INST INVEST FISICOQUIM TEORICAS & APLICADAS,LA PLATA,ARGENTINA. | AF22: ALLEN MJ, 1966, BACTERIOL REV, V30, P80; ALLEN MJ, 1964, ELECTROCHIM ACTA, V9, P1423; BOCKRIS JOM, 1969, FUEL CELLS THEIR ELE, P612; CENEK M, 1968, CHEM LISTY, V62, P927; COHEN B, 1931, J BACTERIOL, V18, P21; ERTOLA R, 1967, IND QUIM, V25, P224; HEINEKEN FG, 1970, BIOTECHNOL BIOENG, V12, P145, DOI 10.1002/bit.260120113; JOHNSON MJ, 1967, BIOTECHNOL BIOENG, V9, P635; JOHNSON MJ, 1970, BIOTECHNOL BIOENG, V12, P145; LEWIS K, 1966, BACTERIOL REV, V30, P101; Potter MC, 1911, P R SOC LOND B-CONTA, V84, P260, DOI 10.1098/rspb.1911.0073; SHAW M, 1963, P ANN POWER SOURCES, V17, P53; Sisler F D, 1971, Prog Ind Microbiol, V9, P1; SOKATCH JR, 1969, BACTERIAL PHYSL META, P157; Videla H. A., 1971, EXPERIENTIA S, V18, P667; WANG DIC, 1968, CHEM ENG, V75, P99; YOUNG TG, 1966, BIOTECHNOL BIOENG, V8, P581, DOI 10.1002/bit.260080410; 1967, Patent No. 1062816 | AG22: 18 | AH22: 4 | AI22: 4 | AJ22: 0 | AK22: 0 | AL22: ASOC QUIMICA ARGENTINA | AM22: BUENOS AIRES | AN22: SANCHEZ DE BUSTAMANTE 1749, 1425 BUENOS AIRES, ARGENTINA | AO22: 0365-0375 | AR22: AN ASOC QUIM ARGENT | AS22: An. Asoc. Quim. Argent. | AU22: 1976 | AV22: 64 | AW22: 2 | BB22: 85 | BC22: 94 | BI22: 10 | BJ22: Chemistry, Multidisciplinary | BK22: Chemistry | BL22: EJ724 | BM22: WOS:A1976EJ72400002 | BR22: 43703
A23: 22 | B23: 10.1080/00021369.1979.10863776 | C23: J | D23: HONGO, M; IWAHARA, M | H23: HONGO, M; IWAHARA, M | K23: ELECTROCHEMICAL STUDIES ON FERMENTATION .1. APPLICATION OF ELECTRO-ENERGIZING METHOD TO L-GLUTAMIC ACID FERMENTATION | L23: AGRICULTURAL AND BIOLOGICAL CHEMISTRY | O23: English | P23: Article | Z23: HONGO, M (reprint author), KUMAMOTO UNIV,DEPT APPL MICROBIAL TECHNOL,KUMAMOTO 860,JAPAN. | AF23: Allen M. J., 1966, ELECTROCHIM ACTA, V11, P1503; ALLEN MJ, 1967, ELECTROCHIM ACTA, V12, P563, DOI 10.1016/0013-4686(67)80025-2; ALLEN MJ, 1967, ELECTROCHIM ACTA, V12, P569, DOI 10.1016/0013-4686(67)80026-4; ALLEN MJ, 1964, ELECTROCHIM ACTA, V9, P1429; ALLEN MJ, 1966, ELECTROCHIM ACTA, V11, P7; ALLEN MJ, 1966, ELECTROCHIM ACTA, V11, P15; ALLEN MJ, 1966, ELECTROCHIM ACTA, V11, P1; BERK RS, 1963, APPL MICROBIOL, V12, P10; Clark W. M., 1960, OXIDATION REDUCTION; Cohen B., 1931, J BACTERIOL, V21, P18; CONWAY EJ, 1955, BIOCHEM J, V61, P32, DOI 10.1042/bj0610032; DAVIS JB, 1962, SCIENCE, V137, P615, DOI 10.1126/science.137.3530.615; DELDUCA DG, 1963, DEV IND MICROBIOL, V4, P81; FEDOROV MV, 1950, DOKL AKAD NAUK SSSR+, V72, P1139; Friedemann TE, 1943, J BIOL CHEM, V147, P415; HANKE ME, 1943, ARCH BIOCHEM BIOPHYS, V2, P183; Hewitt L.F., 1950, OXIDATION REDUCTION; HIROSE Y, 1966, AGR BIOL CHEM TOKYO, V30, P49, DOI 10.1080/00021369.1966.10858554; HONGO M, 1972, AGR BIOL CHEM TOKYO, V36, P273; HONGO M, 1972, AGR BIOL CHEM TOKYO, V36, P269, DOI 10.1080/00021369.1972.10860244; HONGO M, 1972, AGR BIOL CHEM TOKYO, V36, P141, DOI 10.1080/00021369.1972.10860221; HONGO M, 1972, AGR BIOL CHEM TOKYO, V36, P279; HONGO M, 1973, Patent No. 33394; HONGO M, 1960, AMINO ACID, V2, P62; HONGO M, 1957, NIPPON NOGEIKAGAKU K, V31, P816; HONGO M, 1958, NIPPON NOGEIKAGAKU K, V32, pA113; HONGO M, 1968, ANNUAL M AGRICULTURA, P155; HONGO M, 1957, NIPPON NOGEI KAGAKU, V31, P735; HONGO M, 1975, HAKKOKIYOUKAISHI, V33, P398; HONGO M, 1972, Patent No. 15745; HONGO M, 1958, NIPPON NOGEIKAGAKU K, V32, pA101; HONGO M, 1958, NIPPON NOGEIKAGAKU K, V32, P29; HONGO M, 1958, NIPPON NOGEIKAGAKU K, V32, P155; HONGO M, 1957, NIPPON NOGIEKAKU KAI, V31, P731; HONGO M, 1957, NIPPON NOGEIKAGAKU K, V31, P811; HOSHINO K, 1943, NIPPON NOGEIKAGAKU K, V19, P405; HUANG SY, 1974, J FERMENT TECHNOL, V52, P818; ISHIZAKI A, 1974, AGR BIOL CHEM TOKYO, V38, P2399, DOI 10.1080/00021369.1974.10861537; ISHIZAKI A, 1974, AGRIC BIOL CHEM, V38, P2407; JOSLYN MA, 1949, IND ENG CHEM, V41, P587, DOI 10.1021/ie50471a031; JOSLYN MA, 1935, FRUITS PRODUCTS J, V20, P294; JOSLYN MA, 1935, FRUITS PRODUCTS J, V20, P277; JOSLYN MA, 1935, FRUITS PRODUCTS J, V20, P288; KARUBE I, 1978, ANNUAL M FERMENTATIO, P161; KLEBEL W, 1948, BRAUWISSENSCHAFT, V69, P215; KLUYVER AJ, 1937, ENZYMOL, V1, P1; KUBO H, 1947, SANKAKANGEN DENI; LANGLYKKE AF, 1948, IND ENG CHEM, V20, P1716; LEWIS K, 1966, BACTERIOL REV, V30, P101; MIKHLIN E D, 1954, Biokhimiia, V19, P549; MIYACHI N, 1961, NIPPON NOG KAG KAISH, V35, P1207; MIYACHI N, 1957, NIPPON NOGEIKAGAKU K, V31, P229; MIYACHI N, 1956, NIPPON NOGEIKAGAKU K, V30, P485; MIYACHI N, 1957, NIPPON NOGEIKAGAKU K, V31, P61; MIYACHI N, 1963, NIPPON NOGEIKAGAKU K, V37, P287; MIYACHI N, 1956, NIPPON NOGEIKAGAKU K, V30, P770; MIYACHI N, 1957, NIPPON NOGEIKAGAKU K, V31, P145; MIYACHI N, 1962, NIPPON NOGEIKAGAKU K, V36, P91; MIZUGUCHI J, 1964, KOGYO KAGAKU ZASSHI, V67, P410; MIZUGUCHI J, 1962, KOGYO KAGAKU ZASSHI, V65, P1606; MIZUGUCHI J, 1970, KOGYO KAGAKU ZASSHI, V73, P912; MIZUGUCHI J, 1968, KOGYO KAGAKU ZASSHI, V71, P640; MIZUGUCHI J, 1970, KOGYO KAGAKU ZASSHI, V73, P908; MIZUGUCHI J, 1967, KOGYO KAGAKU ZASSHI, V70, P296; MIZUGUCHI J, 1967, KOGYO KAGAKU ZASSHI, V70, P1072; PEEL JL, 1972, METHOD MICROBIOLOG B, V6, P14; Potter MC, 1911, P R SOC LOND B-CONTA, V84, P260, DOI 10.1098/rspb.1911.0073; RIPPON JW, 1968, APPL MICROBIOL, V16, P114; SADOFF HL, 1956, APPL MICROBIOL, V4, P164; SCHLEGEL HG, 1966, FERMENTATION ADV, P807; SHIIO I, 1959, J BIOCHEM-TOKYO, V46, P1597, DOI 10.1093/oxfordjournals.jbchem.a126957; SIEBEL FP, 1949, IND ENG CHEM, V27, P1042; SOMOGYI M, 1952, J BIOL CHEM, V195, P19; TAMURA G, 1952, J AGRIC CHEM SOC JAP, V26, P464; TANAKA M, 1967, HAKKO KENKYUSHO HOKO, V32, P55; VANHEES W, 1965, J ELECTROCHEM SOC, V112, P258, DOI 10.1149/1.2423519; WATANABE Y, 1960, NIPPON NOGEIKAGAKU K, V34, P620; WILLIAMS VR, 1947, J BIOL CHEM, V170, P399; WURMSER R, 1942, SEITAI SANKAKANGEN; YAMABE S, 1970, SEITAI SANKAKANGEN; YAMADA A, 1943, OSAKA IGAKU KAISHI, V42, P1820 | AG23: 81 | AH23: 50 | AI23: 52 | AJ23: 0 | AK23: 13 | AL23: JAPAN SOC BIOSCI BIOTECHN AGROCHEM | AM23: TOKYO | AN23: JAPAN ACAD SOC CTR BLDG, 2-4-6 YAYOI BUNKYO-KU, TOKYO 113, JAPAN | AO23: 0002-1369 | AR23: AGR BIOL CHEM TOKYO | AU23: 1979 | AV23: 43 | AW23: 10 | BB23: 2075 | BC23: 2081 | BE23: 10.1080/00021369.1979.10863776 | BI23: 7 | BJ23: Agronomy; Biochemistry & Molecular Biology | BK23: Agriculture; Biochemistry & Molecular Biology | BL23: HS206 | BM23: WOS:A1979HS20600010 | BR23: 43703
A24: 23 | C24: J | D24: SEIP, WF; EVANS, GL | H24: SEIP, WF; EVANS, GL | K24: ATMOSPHERIC ANALYSIS AND REDOX POTENTIALS OF CULTURE MEDIA IN THE GASPAK SYSTEM | L24: JOURNAL OF CLINICAL MICROBIOLOGY | O24: English | P24: Article | Y24: BECTON DICKINSON & CO,BBL MICROBIOL SYST,RES & DEV,COCKEYSVILLE,MD 21030 | AF24: ARANKI A, 1969, APPL MICROBIOL, V17, P568; BARTLETT RC, 1974, CUMITECH 1 BLOOD CUL; BOKKENHEUSER V, 1969, HEALTH LAB SCI, V6, P162; BREWER JH, 1965, SCIENCE, V147, P1033, DOI 10.1126/science.147.3661.1033-a; BREWER JH, 1966, APPL MICROBIOL, V14, P985; BREWER JH, 1966, APPL MICROBIOL, V14, P135; CARLSSON J, 1978, APPL ENVIRON MICROB, V36, P223; CLARKE WM, 1960, OXIDATION REDUCTION, P131; COLLEE JG, 1972, J APPL BACTERIOL, V35, P71, DOI 10.1111/j.1365-2672.1972.tb03675.x; ELLNER PD, 1973, APPL MICROBIOL, V26, P904; ERICSSON HM, 1971, ACTA PATHOL M B S217, P34; FERGUSON IR, 1975, J APPL BACTERIOL, V39, P167, DOI 10.1111/j.1365-2672.1975.tb00558.x; Gillespie RWH, 1938, J BACTERIOL, V36, P605; Holdeman LV, 1977, ANAEROBE LABORATORY; HOLLAND JW, 1977, J CLIN MICROBIOL, V5, P20; KILLGORE GE, 1973, AM J CLIN PATHOL, V59, P552; LOESCHE WJ, 1969, APPL MICROBIOL, V18, P723; MCGARRITY RJ, 1973, IN VITRO, V9, P17; MCMINN MT, 1970, APPL MICROBIOL, V19, P207; MOORE WEC, 1969, J INFECT DIS, V119, P641, DOI 10.1093/infdis/119.6.641; ONDERDONK AB, 1976, APPL ENVIRON MICROB, V31, P168; Potter MC, 1911, P R SOC LOND B-CONTA, V84, P260, DOI 10.1098/rspb.1911.0073; ROLFE RD, 1978, APPL ENVIRON MICROB, V36, P306; STALONS DR, 1974, APPL MICROBIOL, V27, P1098; Sutter V L, 1973, Prog Clin Pathol, V5, P219; TABATABAI LB, 1970, APPL MICROBIOL, V20, P441; WALDEN WC, 1975, APPL MICROBIOL, V30, P781; WATT B, 1973, J MED MICROBIOL, V6, P307, DOI 10.1099/00222615-6-3-307; WESTCOTT CC, 1976, 952EC766T BECKM INST; WILLIS AT, 1977, ANAEROBIC BACTERIOLO, P9 | AG24: 30 | AH24: 52 | AI24: 54 | AJ24: 0 | AK24: 1 | AL24: AMER SOC MICROBIOLOGY | AM24: WASHINGTON | AN24: 1325 MASSACHUSETTS AVENUE, NW, WASHINGTON, DC 20005-4171 | AO24: 0095-1137 | AR24: J CLIN MICROBIOL | AS24: J. Clin. Microbiol. | AU24: 1980 | AV24: 11 | AW24: 3 | BB24: 226 | BC24: 233 | BI24: 8 | BJ24: Microbiology | BK24: Microbiology | BL24: JK827 | BM24: WOS:A1980JK82700006 | BN24: 6769944 | BR24: 43703
A25: 24 | C25: J | D25: GOVIL, G; SARAN, A | H25: GOVIL, G; SARAN, A | K25: BIOCHEMICAL FUEL-CELLS | L25: JOURNAL OF THE INDIAN CHEMICAL SOCIETY | O25: English | P25: Article | Z25: GOVIL, G (reprint author), TATA INST FUNDAMENTAL RES,BIOCHEM FUEL CELL PROJECT,HOMI BHABHA RD,BOMBAY 400005,INDIA. | AF25: BEREZIN IV, 1979, APPLIED BIOCH BIOENG, V2, P259; BLANCHARD GC, 1971, J ELECTROCHEM SOC, V118, P1232, DOI 10.1149/1.2408290; Cohen B., 1931, J BACTERIOL, V21, P18; COLICHMAN EL, 1963, P IEEE, P812; DAVIS JB, 1962, SCIENCE, V137, P615, DOI 10.1126/science.137.3530.615; HOWARD J, 1971, NEW SCI, V48, P528; LEWIS K, 1966, BACTERIOL REV, V30, P101; PHADKE RS, UNPUB; Potter MC, 1911, P R SOC LOND B-CONTA, V84, P260, DOI 10.1098/rspb.1911.0073; Sisler F D, 1971, Prog Ind Microbiol, V9, P1; SISLER FD, 1961, NEW SCIENTIST, V12, P110; VANHEES W, 1965, J ELECTROCHEM SOC, V112, P258, DOI 10.1149/1.2423519; WILSON BJ, 1963, NRL5998 REP; WINGARD LB, 1971, BIOTECHNOL BIOENG, V13, P629, DOI 10.1002/bit.260130504; 1980, B INDIAN PHYSICS ASS, V11 | AG25: 15 | AH25: 7 | AI25: 7 | AJ25: 0 | AK25: 0 | AL25: INDIAN CHEMICAL SOC | AM25: CALCUTTA | AN25: 92 ACHARYA PRAFULLA CHANDRA RD ATTN:DR INDRAJIT KAR/EXEC SEC, CALCUTTA 700009, INDIA | AO25: 0019-4522 | AR25: J INDIAN CHEM SOC | AS25: J. Indian Chem. Soc. | AU25: 1982 | AV25: 59 | AW25: 43476 | BB25: 1226 | BC25: 1228 | BI25: 3 | BJ25: Chemistry, Multidisciplinary | BK25: Chemistry | BL25: RB291 | BM25: WOS:A1982RB29100006 | BR25: 43703
A26: 25 | B26: 10.1016/0300-9467(86)80023-5 | C26: J | D26: YUE, PL; LOWTHER, K | H26: YUE, PL; LOWTHER, K | K26: ENZYMATIC OXIDATION OF C1 COMPOUNDS IN A BIOCHEMICAL FUEL-CELL | L26: CHEMICAL ENGINEERING JOURNAL AND THE BIOCHEMICAL ENGINEERING JOURNAL | O26: English | P26: Article | Z26: YUE, PL (reprint author), UNIV BATH,SCH CHEM ENGN,CLAVERTON DOWN,BATH BA2 7AY,AVON,ENGLAND. | AF26: ASTON WJ, 1984, BIOTECHNOL GENET ENG, V1, P89, DOI 10.1080/02648725.1984.10647782; DAVIS G, 1983, ENZYME MICROB TECH, V5, P383, DOI 10.1016/0141-0229(83)90013-3; Fickett A. P., 1978, Scientific American, V239, P54; Grove W. R., 1839, PHILOS MAG, P127, DOI DOI 10.1080/14786443908649684; HELMUTH NA, 1967, Patent No. 3340094; HIGGINS IJ, 1980, HYDROCARBONS BIOTECH, P181; HILL HAO, 1981, PHILOS T R SOC A, V302, P267, DOI 10.1098/rsta.1981.0166; KARUBE I, 1981, ANN NY ACAD SCI, V369, P91; PLOTKIN EV, 1981, BIOTECHNOL LETT, V3, P187; Potter MC, 1911, P R SOC LOND B-CONTA, V84, P260, DOI 10.1098/rspb.1911.0073; Sisler F. D., 1969, Patent, Patent No. [3,477,879, 3477879]; TOFIELD BC, 1981, APPL ENERG, V8, P89, DOI 10.1016/0306-2619(81)90014-3; Turner APF, 1982, BIOTECHNOL BIOENG S, V12, P401; WARBURG O, 1957, METHOD ENZYMOL, V3, P451; Wingard L B Jr, 1978, Hindustan Antibiot Bull, V20, P109; WINGARD LB, 1982, ENZYME MICROB TECH, V4, P137, DOI 10.1016/0141-0229(82)90104-1 | AG26: 16 | AH26: 10 | AI26: 10 | AJ26: 0 | AK26: 0 | AL26: ELSEVIER SCIENCE SA LAUSANNE | AM26: LAUSANNE 1 | AN26: PO BOX 564, 1001 LAUSANNE 1, SWITZERLAND | AO26: 0923-0467 | AR26: CHEM ENG J BIOCH ENG | AS26: Chem. Eng. J. Biochem. Eng. J. | AT26: DEC | AU26: 1986 | AV26: 33 | AW26: 3 | BB26: B69 | BC26: B77 | BE26: 10.1016/0300-9467(86)80023-5 | BI26: 9 | BJ26: Engineering, Chemical | BK26: Engineering | BL26: F4449 | BM26: WOS:A1986F444900010 | BR26: 43703
A27: 26 | C27: J | D27: SHVETSTENETAGURY, TB; NOVIKOVA, MR; TVERITSKAYA, IN; KHONITCHEVA, NM | H27: SHVETSTENETAGURY, TB; NOVIKOVA, MR; TVERITSKAYA, IN; KHONITCHEVA, NM | K27: ELECTRICAL-ACTIVITY OF THE BRAIN - IS IT ALWAYS ELECTRICAL - (ON THE FACTORS WHICH CREATE A POTENTIAL OF A METAL-ELECTRODE BEING IN A DIRECT CONTACT WITH THE BRAIN-TISSUE) | L27: ZHURNAL VYSSHEI NERVNOI DEYATELNOSTI IMENI I P PAVLOVA | O27: Russian | P27: Note | X27: In the paper are analysed the factors creating slow potential changes of a metal electrode directly contacting with the living tissue. In the paper are presented the data according to which electrochemical tissue activity participates in creating the electrode potential besides the electrical activity. The paper carries a discussional character. | Z27: SHVETSTENETAGURY, TB (reprint author), RUSSIAN ACAD SCI,INST HIGHER NERVOUS ACT & NEUROPHYSIOL,MOSCOW,RUSSIA. | AF27: ALADZHALOVA NA, 1962, MEDLENNYE ELEKTRICHE; ALLEN MG, 1976, TOP BIOELECTROCHEM B, V1, P37; BERRY MN, 1981, FEBS LETT, V134, P133, DOI 10.1016/0014-5793(81)80585-6; BOCKRIS YOM, 1980, BIOELECTROCHEMISTRY, P5; BOKARIUS V B, 1989, Fiziologicheskii Zhurnal SSSR Imeni I M Sechenova, V75, P582; BRESNAHAN WT, 1980, EXPERIENTIA, V36, P1249, DOI 10.1007/BF01969579; CASPERS H, 1959, PFLUG ARCH GES PHYS, V270, P103, DOI 10.1007/BF00362843; Cooper R., 1969, EEG TECHNOLOGY; DEBOER RW, 1978, MED BIOL ENG COMPUT, V16, P1; DELAKHEI P, 1967, DVOINOI SLOI KINETIK; FETTER K, 1967, ELEKTROKHIMICHESKAYA; Frumkin A. N., 1952, KINETIKA ELEKTRODNYK; Garcia Ramos J, 1967, Curr Mod Biol, V1, P125; GEDDES LA, 1972, ELECTRODES MEASUREME; GRIGOR'EV V A, 1990, Fiziologicheskii Zhurnal SSSR Imeni I M Sechenova, V76, P1449; Ilyukhina V.A., 1983, SVERKHMEDLENNAYA UPR; Ilyukhina V.A., 1986, SVERKHMEDLENNYE FIZI; KUCHERENKO NE, 1982, BIOENERGETIKA; KUZNETSOVA GD, 1978, OCHAGI STATSIONARNOG; Potter MC, 1911, P R SOC LOND B-CONTA, V84, P260, DOI 10.1098/rspb.1911.0073; PUPPI A, 1983, ACTA BIOL HUNG, V34, P323; ROWLAND V, 1987, ELECTROEN CLIN NEURO, V67, P591, DOI 10.1016/0013-4694(87)90063-0; SHVETS-TENETA-GURII T B, 1989, Byulleten' Eksperimental'noi Biologii i Meditsiny, V108, P259; SHVETSTENETAGUR.TB, 1986, BIOELEKTROKHIMICHESK; SHVETSTENETAGUR.TB, 1980, BIOELEKTROKHIMICHESK | AG27: 25 | AH27: 3 | AI27: 5 | AJ27: 0 | AK27: 0 | AL27: MEZHDUNARODNAYA KNIGA | AM27: MOSCOW | AN27: 39 DIMITROVA UL., 113095 MOSCOW, RUSSIA | AO27: 0044-4677 | AR27: ZH VYSSH NERV DEYAT+ | AS27: Zhurnal Vyss. Nervn. Deyatelnosti Im. I P Pavlov. | AT27: JAN-FEB | AU27: 1993 | AV27: 43 | AW27: 1 | BB27: 182 | BC27: 191 | BI27: 10 | BJ27: Neurosciences; Physiology | BK27: Neurosciences & Neurology; Physiology | BL27: KP845 | BM27: WOS:A1993KP84500022 | BN27: 8385393 | BR27: 43703
A28: 27 | B28: 10.1016/0022-0728(94)03651-I | C28: J | D28: TAKAYAMA, K; KUROSAKI, T; IKEDA, T; NAGASAWA, T | H28: TAKAYAMA, K; KUROSAKI, T; IKEDA, T; NAGASAWA, T | K28: BIOELECTROCATALYTIC HYDROXYLATION OF NICOTINIC-ACID AT AN ELECTRODE MODIFIED WITH IMMOBILIZED BACTERIAL-CELLS OF PSEUDOMONAS-FLUORESCENS IN THE PRESENCE OF ELECTRON-TRANSFER MEDIATORS | L28: JOURNAL OF ELECTROANALYTICAL CHEMISTRY | O28: English | P28: Article | V28: BIOELECTROCATALYSIS; HYDROXYLATION; NICOTINIC ACID; PSEUDOMONAS FLUORESCENS; ELECTRON TRANSFER MEDIATORS | W28: CARBON PASTE ELECTRODE; MICROBIAL FUEL-CELLS; BIOCATALYST ELECTRODE; GLUCOSE | X28: Bacterial cells of Pseudomonas fluorescens TN5 (Pf) were immobilized behind a dialysis membrane on the surface of a carbon paste electrode. The electrode produced an anodic current in a buffer solution containing nicotinic acid in the presence of phenazine methosulfate. The anodic current was attributable to the oxidative hydroxylation of nicotinic acid by the catalytic action of the bacterium, in which PMS functioned as an electron acceptor in the catalytic reaction and as an electron transfer mediator between the immobilized bacterial cells and the electrode. Such compounds as 1-methoxy-5-methylphenazinium methylsulfate, 2,6-dichlorophenolindophenol, p-benzoquinone (BQ), ferricyanide and ferrocene carboxylic acid were also effective as mediators in the reaction. When a Pf-modified electrode was constructed with a carbon paste electrode containing BQ, the electrode showed a current response to nicotinic acid in the absence of a mediator in solution. The current response of the Pf-modified BQ-containing electrode was highly selective to nicotinic acid. The bioelectrocatalysis behavior of the electrode is investigated in some detail, and the results are interpreted on the basis of a simple model of bioelectrocatalysis at a biocatalyst-modified electrode. | Y28: KYOTO UNIV,FAC AGR,DEPT AGR CHEM,SAKYO KU,KYOTO 606,JAPAN; NAGOYA UNIV,DEPT FOOD SCI & TECHNOL,CHIGUSA KU,NAGOYA,AICHI 464,JAPAN | AF28: AMEYAMA M, 1985, ENZYMES, V1, P71; BENNETTO HP, 1983, BIOTECHNOL BIOENG, V25, P559, DOI 10.1002/bit.260250219; BENNETTO HP, 1987, BIOSENSORS FUNDAMENT, P291; DISALVO EA, 1979, BIOELECTROCH BIOENER, V6, P185, DOI 10.1016/0302-4598(79)87007-5; HADJIPETROU LP, 1966, J GEN MICROBIOL, V45, P479, DOI 10.1099/00221287-45-3-479; HURH B, 1993, NIPPON NOGEIKAGAKU K, V67, P311; IKEDA T, 1985, AGR BIOL CHEM TOKYO, V49, P541, DOI 10.1080/00021369.1985.10866761; IKEDA T, 1988, ANAL SCI, V4, P133, DOI 10.2116/analsci.4.133; IKEDA T, 1986, AGR BIOL CHEM TOKYO, V50, P883, DOI 10.1080/00021369.1986.10867477; IKEDA T, 1992, BIOSCI BIOTECH BIOCH, V56, P1359, DOI 10.1271/bbb.56.1359; KULYS J, 1992, ELECTROANAL, V4, P527, DOI 10.1002/elan.1140040503; NAGASAWA T, 1994, BIOSCI BIOTECH BIOCH, V58, P665, DOI 10.1271/bbb.58.665; NISHIKAWA S, 1982, APPL ENVIRON MICROB, V43, P814; Potter MC, 1911, P R SOC LOND B-CONTA, V84, P260, DOI 10.1098/rspb.1911.0073; RICHARDSON NJ, 1991, J APPL BACTERIOL, V70, P422, DOI 10.1111/j.1365-2672.1991.tb02959.x; TAKAYAMA K, 1993, J ELECTROANAL CHEM, V356, P295, DOI 10.1016/0022-0728(93)80529-Q; TANAKA K, 1983, BIOELECTROCH BIOENER, V11, P135, DOI 10.1016/0302-4598(83)80088-9; Turner A.P.F., 1987, BIOSENSORS FUNDAMENT, P13; YAMADA H, 1983, SOC FERMENTATION BIO, P250; YOUNG TG, 1966, BIOTECHNOL BIOENG, V8, P581, DOI 10.1002/bit.260080410 | AG28: 20 | AH28: 33 | AI28: 34 | AJ28: 0 | AK28: 0 | AL28: ELSEVIER SCIENCE SA LAUSANNE | AM28: LAUSANNE 1 | AN28: PO BOX 564, 1001 LAUSANNE 1, SWITZERLAND | AO28: 0022-0728 | AR28: J ELECTROANAL CHEM | AS28: J. Electroanal. Chem. | AT28: JAN 24 | AU28: 1995 | AV28: 381 | AW28: 43497 | BB28: 47 | BC28: 53 | BE28: 10.1016/0022-0728(94)03651-I | BI28: 7 | BJ28: Chemistry, Analytical; Electrochemistry | BK28: Chemistry; Electrochemistry | BL28: QE042 | BM28: WOS:A1995QE04200008 | BR28: 43703
A29: 28 | B29: 10.1016/0956-5663(96)86783-2 | C29: J | D29: Hobson, NS; Tothill, I; Turner, APF | H29: Hobson, NS; Tothill, I; Turner, APF | K29: Microbial detection | L29: BIOSENSORS & BIOELECTRONICS | O29: English | P29: Review | W29: POLYMERASE CHAIN-REACTION; ESCHERICHIA-COLI; RAPID-DETERMINATION; BIOLOGICAL-SYSTEMS; ELECTRODE SYSTEM; CELL-POPULATIONS; BACTERIAL-GROWTH; BIOMASS; ENUMERATION; IMMUNOSENSOR | X29: There is a widespread need for commercial instrumentation for the rapid and inexpensive detection of microbial contamination of food, industrial waste water and clinical samples. A large number of detection methods have been developed utilizing the optical, electrochemical, biochemical and physical properties of microorganisms. The need for a device which can produce a rapid, accurate, sensitive, real-time analysis for clinical, industrial and environmental applications has led to considerable progress being achieved in recent years in the development of biosensors for microbial detection. This intense research has resulted in the commercialization of several instruments. Techniques used for the quantification of microorganisms are reviewed under the general categories of non-bioelectrochemical and bioelectrochemical methods. | Z29: Hobson, NS (reprint author), CRANFIELD UNIV, CTR BIOTECHNOL, CRANFIELD MK43 0AL, BEDS, ENGLAND. | AC29: Turner, Anthony/0000-0002-1815-9699 | AF29: ADAMS RLP, 1980, LABORATORY TECHNIQUE, V8, P103; ALLEN ME, 1990, THESIS CRANFIELD U B; ARMIGER NB, 1984, BIOTECH 1984; ASHLEY N, 1991, DAIRY IND INT, V56, P39; ASTON WJ, 1987, BIOSENSORS FUNDAMENT, P276; BACHRACH U, 1974, APPL MICROBIOL, V28, P169, DOI 10.1177/0193723504264772; BACHRACH U, 1976, P 2 INT S RAP METH A, P3; BADLEY RA, 1987, PHILOS T ROY SOC B, V316, P143, DOI 10.1098/rstb.1987.0024; BATTERSBY NS, 1985, J APPL BACTERIOL, V58, P425, DOI 10.1111/j.1365-2672.1985.tb01481.x; BATTLEY EH, 1960, PHYSIOL PLANTARUM, V13, P628, DOI 10.1111/j.1399-3054.1960.tb08085.x; BENJAMIN TG, 1979, P 14 INT EN CONS C, V1, P579; BENNETO HP, 1980, J BIOTECHNOL BIOENG, V25, P559; BENNETT EO, 1957, J APPL MICROBIOL, V5, P14; BEYELER W, 1981, J APPL MICROBIOL BIO, V13, P10; Bobowski S., 1987, Industrial microbiological testing, P171; BOE I, 1990, BIOTECHNOL BIOENG, V35, P1, DOI 10.1002/bit.260350102; BORSHEIM KY, 1990, APPL ENVIRON MICROB, V56, P352; BUDDEMEYER EU, 1976, P 2 INT S RAP METH A, P4; BULOW L, 1988, METHOD ENZYMOL, V137, P632; CARDOSI M, 1991, ELECTROANAL, V3, P169, DOI 10.1002/elan.1140030306; CARRINO DA, 1991, BIOCHEM INT, V24, P485; CAVINATO AG, 1990, 3 INT S AN METH BIOT; CHAN A, 1993, ANAL CHEM, V65, P158, DOI 10.1021/ac00050a012; CHATTOPADHYAY NC, 1977, J PHYTOPATHOL, V89, P256; CLARKE DJ, 1985, BIOSENSORS, V1, P213, DOI 10.1016/0265-928X(85)85001-X; CLARKE DJ, 1980, PRACTICAL MED MICROB; COCHET N, 1984, BIOTECHNOL LETT, V6, P155, DOI 10.1007/BF00127031; Cohen B., 1931, J BACTERIOL, V21, P18; COLLINGE TA, 1985, BIOSENSORS, V1, P213; Coons AH, 1942, J IMMUNOL, V45, P159; CULLEN DC, 1990, SENSOR ACTUAT B-CHEM, V1, P576, DOI 10.1016/0925-4005(90)80276-6; DAVIS JG, 1963, J ADV APPL MICROBIOL, V5, P51; DING T, 1990, ANAL CHIM ACTA, V234, P247, DOI 10.1016/S0003-2670(00)83564-3; DZIEZAK JD, 1987, FOOD TECHNOL JUL, P56; FINNEGAN RE, 1989, THESI CRANFIELD U BE; FIRSTENBERGEDEN R, 1986, FOODBORNE MICROORGAN, P129; FORD SR, 1985, SOIL BIOL BIOCHEM, V17, P811, DOI 10.1016/0038-0717(85)90138-5; GALANOS DS, 1966, ANAL CHIM ACTA, V34, P360, DOI 10.1016/S0003-2670(00)89052-2; GARG SK, 1982, BIOTECHNOL BIOENG, V24, P2407, DOI 10.1002/bit.260241108; GNAN S, 1982, J FOOD PROTECT, V45, P4, DOI 10.4315/0362-028X-45.1.4; HADLEY WK, 1976, P 2 INT S RAP METH A, P14; HARRIS CM, 1985, BIOSENSORS, V1, P17, DOI 10.1016/0265-928X(85)85005-7; HARRIS CM, 1983, BIOELECTROCH BIOENER, V11, P15, DOI 10.1016/0302-4598(83)85097-1; HELDAL M, 1985, APPL ENVIRON MICROB, V50, P1251; HOBSON PN, 1957, J GEN MICROBIOL, V16, P463, DOI 10.1099/00221287-16-2-463; HOLLAND RL, 1980, J CLIN MICROBIOL, V12, P180; HOPE CFA, 1985, J I BREWING, V91, P12, DOI 10.1002/j.2050-0416.1985.tb04298.x; HOSLER P, 1953, IND ENG CHEM, V45, P871, DOI 10.1021/ie50520a056; ISHIKAWA Y, 1983, BIOTECHNOL BIOENG, V25, P1817, DOI 10.1002/bit.260250711; ISHIMORI Y, 1981, APPL ENVIRON MICROB, V30, P483; JACKSON TM, 1986, J IMMUNOL METHODS, V87, P13, DOI 10.1016/0022-1759(86)90338-8; JONES JG, 1979, BIOL ASS; JUNTER GA, 1980, APPL ENVIRON MICROB, V39, P307; KAHN W, 1976, P 2 INT S RAP METH A, P14; KARL DM, 1980, MICROBIOL REV, V44, P739; KATES M, 1964, ADV LIPID RES, V2, P17; KEILMANN F, 1980, J APPL MICROBIOL, V40, P458; KISSINGER PT, 1984, LAB TECHNIQUES ELECT, P87; KNIGHT VA, 1981, BIOCHIM BIOPHYS ACTA, V637, P146, DOI 10.1016/0005-2728(81)90220-6; KOCH AL, 1961, BIOCHIM BIOPHYS ACTA, V51, P429, DOI 10.1016/0006-3002(61)90599-6; KORETOU O, 1988, ACTA HISTOCHEM CYTOC, V21, P25, DOI 10.1267/ahc.21.25; KOWALENKO C G, 1970, Soil Biology and Biochemistry, V2, P269, DOI 10.1016/0038-0717(70)90033-7; KRAKTY O, 1968, Patent No. 2704; KRAMBECK C, 1981, APPL ENVIRON MICROB, V42, P142; KRESSROGERS E, 1993, J FOOD CONTROL, V4, P149; Kubitschek HE, 1969, METHOD MICROBIOL, V1, P593; LAFIS S, 1992, THESIS CRANFIELD U B; LANG CA, 1958, ANAL CHEM, V30, P1692, DOI 10.1021/ac60142a038; LEVIN GV, 1963, J ADV APPL MICROBIOL, V5, P95; LIEDBERG B, 1983, SENSOR ACTUATOR, V4, P299, DOI 10.1016/0250-6874(83)85036-7; LILLEY MD, 1979, FERMENTATION ENZYME; LUONG JHT, 1982, CAN J CHEM ENG, V60, P163, DOI 10.1002/cjce.5450600129; MACDONALD AMG, 1963, J IND CHEM, V39, P265; MACFARLANE GT, 1984, J GEN MICROBIOL, V130, P2301; MALLETTE MF, 1969, METHOD MICROBIOL, P319; MANOHARAN R, 1990, J MICROBIOL METH, V11, P1, DOI 10.1016/0167-7012(90)90042-5; MATSUNAGA T, 1984, ANAL CHIM ACTA, V159, P87, DOI 10.1016/S0003-2670(00)84284-1; MATSUNAGA T, 1985, APPL ENVIRON MICROB, V50, P238; MATSUNAGA T, 1981, EUR J APPL MICROBIOL, V12, P97, DOI 10.1007/BF01970041; MATSUNAGA T, 1980, EUR J APPL MICROBIOL, V10, P125, DOI 10.1007/BF00504735; MATSUNAGA T, 1979, APPL ENVIRON MICROB, V37, P117; MATTIASSON B, 1977, BIOCHIM BIOPHYS ACTA, V483, P221, DOI 10.1016/0005-2744(77)90050-X; MEYENELL GG, 1970, THEORY PRACTICE EXPT; MILLER R, 1989, J I BREWING, V95, P317, DOI 10.1002/j.2050-0416.1989.tb04637.x; NAKAMURA N, 1993, ANAL CHEM, V65, P2036, DOI 10.1021/ac00063a018; NAKATA S, 1990, CHEM LETT, P1631, DOI 10.1246/cl.1990.1631; NEUFELD RJ, 1982, BIOTECHNOL LETT, V4, P701, DOI 10.1007/BF00134662; NISHIKAWA S, 1982, APPL ENVIRON MICROB, V43, P814; NORTH JR, 1985, TRENDS BIOTECHNOL, V3, P180, DOI 10.1016/0167-7799(85)90119-2; PATON AW, 1993, J CLIN MICROBIOL, V31, P3063; PETHIG R, 1987, PHYS MED BIOL, V32, P933, DOI 10.1088/0031-9155/32/8/001; PETTIFER GL, 1983, DIRECT EPIFLUORESCEN; PETTIFER GL, 1980, J APPL ENV MICROBIOL, V29, P29; Pirt S.J., 1975, PRINCIPLES MICROBE C; PLOMER M, 1992, ENZYME MICROB TECH, V14, P230, DOI 10.1016/0141-0229(92)90071-U; POSTGATE JR, 1969, METHOD MICROBIOL, V1, P611, DOI DOI 10.1016/S0580-9517(08)70149-1; Potter MC, 1911, P R SOC LOND B-CONTA, V84, P260, DOI 10.1098/rspb.1911.0073; POWELL EO, 1962, J GEN MICROBIOL, V27, P489, DOI 10.1099/00221287-27-3-489; POWELL S, 1991, LAB EQUIPMENT DIGEST, V29, P29; RICHARDS JCS, 1978, J PHYS E SCI INSTRUM, V11, P560, DOI 10.1088/0022-3735/11/6/017; ROWLEY DB, 1976, P 2 INT S RAP METH A, P3; SADDLER J N, 1980, Journal of Microbiology, V46, P27; Sambrook J, 1989, MOL CLONING LAB MANU; Sawyer DT, 1974, EXPT ELECTROCHEMISTR; Schmidt E., 1973, B ECOL RES COMM STOC, V17, P67; SCHMIDT EL, 1962, SCIENCE, V136, P776, DOI 10.1126/science.136.3518.776; SEYDEL JK, 1980, DRUG RES, V30, P298; SHARP AN, 1974, J APPL MICROBIOL, V28, P223; SHARPE AN, 1971, J APPL BACTERIOL, V34, P435, DOI 10.1111/j.1365-2672.1971.tb02303.x; Sheldon R.W., 1967, PRACTICAL MANUAL USE; SIEBURTH JM, 1979, SEA MICROBES; SILVERMAN MP, 1979, APPL ENVIRON MICROB, V37, P521; SIMS PJ, 1974, BIOCHEMISTRY-US, V13, P3315, DOI 10.1021/bi00713a022; SINGH A, 1994, ADV BIOCHEM ENG BIOT, V51, P48; SLATER JH, 1983, MICROBES THEIR NATUR, P37; STARKA J, 1962, J GEN MICROBIOL, V29, P83, DOI 10.1099/00221287-29-1-83; SUZUKI M, 1977, MICROBIOL IMMUNOL, V21, P419, DOI 10.1111/j.1348-0421.1977.tb00307.x; TAYLOR F, 1987, PERSONAL COMMUNICATI; THIERRY A, 1988, APPL MICROBIOL BIOT, V28, P199, DOI 10.1007/BF00694312; THOMAS DC, 1985, BIOTECHNOL BIOENG, V27, P729, DOI 10.1002/bit.260270523; TITUS JA, 1984, APPL ENVIRON MICROB, V47, P239; TURNER APF, 1983, BIOCHEM SOC T, V11, P445, DOI 10.1042/bst0110445; TURNER APF, 1987, BIOTECHNOLOGY FOOD I; TURNER APF, 1989, SAB TECHNICAL SERIES, V25, P213; WANG DIC, 1972, J APPL MICROBIOL, V23, P198; WARREN W, 1991, BIOTECHNIQUES, V11, P250; WATSON SW, 1977, APPL ENVIRON MICROB, V33, P940; WHITE DC, 1979, OECOLOGIA, V40, P51, DOI 10.1007/BF00388810; WILKINS JR, 1978, APPL ENVIRON MICROB, V35, P214; WILKINS JR, 1974, J APPL ENV MICROBIOL, V27, P949; WINGARD LB, 1982, ENZYME MICROB TECH, V4, P137, DOI 10.1016/0141-0229(82)90104-1; WOOLLEY GA, 1987, FEBS LETT, V224, P337, DOI 10.1016/0014-5793(87)80480-5; ZAFARI Y, 1977, J CLIN MICROBIOL, V5, P545 | AG29: 133 | AH29: 117 | AI29: 124 | AJ29: 1 | AK29: 17 | AL29: ELSEVIER ADVANCED TECHNOLOGY | AM29: OXFORD | AN29: OXFORD FULFILLMENT CENTRE THE BOULEVARD, LANGFORD LANE, KIDLINGTON, OXFORD OX5 1GB, OXON, ENGLAND | AO29: 0956-5663 | AP29: 1873-4235 | AR29: BIOSENS BIOELECTRON | AS29: Biosens. Bioelectron. | AU29: 1996 | AV29: 11 | AW29: 5 | BB29: 455 | BC29: 477 | BE29: 10.1016/0956-5663(96)86783-2 | BI29: 23 | BJ29: Biophysics; Biotechnology & Applied Microbiology; Chemistry, Analytical; Electrochemistry; Nanoscience & Nanotechnology | BK29: Biophysics; Biotechnology & Applied Microbiology; Chemistry; Electrochemistry; Science & Technology - Other Topics | BL29: UB805 | BM29: WOS:A1996UB80500001 | BN29: 8729237 | BR29: 43703
A30: 29 | B30: 10.1039/b009539g | C30: J | D30: Tsujimura, S; Fujita, M; Tatsumi, H; Kano, K; Ikeda, T | H30: Tsujimura, S; Fujita, M; Tatsumi, H; Kano, K; Ikeda, T | K30: Bioelectrocatalysis-based dihydrogen/dioxygen fuel cell operating at physiological pH | L30: PHYSICAL CHEMISTRY CHEMICAL PHYSICS | O30: English | P30: Article | W30: CYTOCHROME-C-OXIDASE; BILIRUBIN OXIDASE; ELECTROCHEMICAL PROPERTIES; ELECTRON-TRANSFER; BIOFUEL CELL; FUNCTIONAL-MODEL; HYDROGENASE; REDUCTION; DIOXYGEN; EXCHANGE | X30: A biochemical fuel cell was constructed using H-2 as fuel to produce H2O in the reaction with O-2 at neutral pH and ambient temperature. The cell uses carbon felt as an electrode material for both the anode and the cathode and an anion exchange membrane as a separator. The anodic oxidation of H-2 was accelerated by methyl viologen-mediated electrocatalysis with bacterial cells Desulfovibrio vulgaris (Hildenborough) as catalysts, and the cathodic reduction of O-2 was accelerated by 2,2'-azinobis(3-ethylbenzothiazoline-6-sulfonate)-mediated electrocatalysis with bilirubin oxidase as a catalyst. The bioelectrocatalytic systems allowed the cell to operate at 1.0 V with current 0.9 mA at an electrode of size 1.5x1.5x0.1 cm(3). The cell voltage attained 1.17 V at open circuit, which is close to the standard electromotive force 1.23 V. The cell voltage-current behavior is interpretable by linear sweep voltammetry using the same electrode system. On this basis, the electrochemistry behind the performance of the biochemical fuel cell is discussed. | Y30: Kyoto Univ, Grad Sch Agr, Div Appl Life Sci, Sakyo Ku, Kyoto 6068502, Japan | Z30: Ikeda, T (reprint author), Kyoto Univ, Grad Sch Agr, Div Appl Life Sci, Sakyo Ku, Kyoto 6068502, Japan. | AB30: Sokabe, Masahiro/I-1565-2012; Tsujimura, Seiya/O-4758-2018 | AC30: Tsujimura, Seiya/0000-0001-9603-2418 | AF30: BIANCO P, 1992, BIOCHEM BIOPH RES CO, V189, P633, DOI 10.1016/0006-291X(92)92247-U; BOCKRIS JO, 1993, SURFACE ELECTROCHEMI, P880; Butt JN, 1997, EUR J BIOCHEM, V245, P116, DOI 10.1111/j.1432-1033.1997.00116.x; *CHEM SOC JAP, 1984, HDB CHEM 2, P158; Cohen B., 1931, J BACTERIOL, V21, P18; Collman JP, 1997, SCIENCE, V275, P949, DOI 10.1126/science.275.5302.949; Collman JP, 1999, J AM CHEM SOC, V121, P1387, DOI 10.1021/ja983351a; Collman JP, 1998, ANGEW CHEM INT EDIT, V37, P3397, DOI 10.1002/(SICI)1521-3773(19981231)37:24<3397::AID-ANIE3397>3.0.CO;2-N; DAVIS G, 1983, ENZYME MICROB TECHNO, V5, P382; DAVIS JB, 1962, SCIENCE, V137, P615, DOI 10.1126/science.137.3530.615; GOTOH Y, 1989, J BIOCHEM-TOKYO, V106, P621, DOI 10.1093/oxfordjournals.jbchem.a122906; HALADJIAN J, 1987, BIOCHEM BIOPH RES CO, V147, P1289, DOI 10.1016/S0006-291X(87)80210-3; HILL HAO, 1981, FEBS LETT, V126, P282, DOI 10.1016/0014-5793(81)80261-X; HILL HAO, 1982, J AM CHEM SOC, V104, P6515, DOI 10.1021/ja00388a006; Kato K, 2000, J ELECTROCHEM SOC, V147, P1449, DOI 10.1149/1.1393376; Katz E, 1999, J ELECTROANAL CHEM, V479, P64, DOI 10.1016/S0022-0728(99)00425-8; LEE CW, 1984, J ELECTROANAL CHEM, V172, P289, DOI 10.1016/0022-0728(84)80193-X; MIZUGUCHI J, 1962, KOGYO KAGAKU ZASSHI, V65, P1606; MURAO S, 1982, AGR BIOL CHEM TOKYO, V46, P2031, DOI 10.1080/00021369.1982.10865379; NIVIERE V, 1988, BIOCHIM BIOPHYS ACTA, V935, P34, DOI 10.1016/0005-2728(88)90105-3; Palmore GTR, 1998, J ELECTROANAL CHEM, V443, P155, DOI 10.1016/S0022-0728(97)00393-8; Palmore GTR, 1999, J ELECTROANAL CHEM, V464, P110, DOI 10.1016/S0022-0728(99)00008-X; PALMORE GTR, 1994, ACS SYM SER, V566, P271; Potter MC, 1911, P R SOC LOND B-CONTA, V84, P260, DOI 10.1098/rspb.1911.0073; Shimizu A, 1999, BIOCHEMISTRY-US, V38, P3034, DOI 10.1021/bi9819531; Shimizu A, 1999, J BIOCHEM-TOKYO, V125, P662, DOI 10.1093/oxfordjournals.jbchem.a022334; SRINIVASAN S, 1991, J POWER SOURCES, V36, P299, DOI 10.1016/0378-7753(91)87009-Z; TANAKA N, 1982, AGR BIOL CHEM TOKYO, V46, P2499, DOI 10.1080/00021369.1982.10865459; TARASEVICH MR, 1979, BIOELECTROCH BIOENER, V6, P393, DOI 10.1016/0302-4598(79)80006-9; Tatsumi H, 2000, J PHYS CHEM B, V104, P12079, DOI 10.1021/jp002475i; Tatsumi H, 1999, ANAL CHEM, V71, P1753, DOI 10.1021/ac981003l; Tsujimura S, 2001, J ELECTROANAL CHEM, V496, P69, DOI 10.1016/S0022-0728(00)00239-4; VARFOLOMEYEV SD, 1993, J BIOTECHNOL, V27, P331, DOI 10.1016/0168-1656(93)90095-5; VERHAGEN MFJM, 1994, EUR J BIOCHEM, V221, P821, DOI 10.1111/j.1432-1033.1994.tb18796.x; WINGARD LB, 1982, ENZYME MICROB TECH, V4, P137, DOI 10.1016/0141-0229(82)90104-1; Xu F, 1996, BBA-PROTEIN STRUCT M, V1292, P303, DOI 10.1016/0167-4838(95)00210-3; Yaropolov AI, 1996, BIOELECTROCH BIOENER, V40, P49, DOI 10.1016/0302-4598(96)01919-8; YOUNG TG, 1966, BIOTECHNOL BIOENG, V8, P581, DOI 10.1002/bit.260080410 | AG30: 38 | AH30: 125 | AI30: 125 | AJ30: 1 | AK30: 42 | AL30: ROYAL SOC CHEMISTRY | AM30: CAMBRIDGE | AN30: THOMAS GRAHAM HOUSE, SCIENCE PARK, MILTON RD,, CAMBRIDGE CB4 0WF, CAMBS, ENGLAND | AO30: 1463-9076 | AR30: PHYS CHEM CHEM PHYS | AS30: Phys. Chem. Chem. Phys. | AU30: 2001 | AV30: 3 | AW30: 7 | BB30: 1331 | BC30: 1335 | BE30: 10.1039/b009539g | BI30: 5 | BJ30: Chemistry, Physical; Physics, Atomic, Molecular & Chemical | BK30: Chemistry; Physics | BL30: 412XH | BM30: WOS:000167579300029 | BR30: 43703
A31: 30 | B31: 10.1038/441277a | C31: J | D31: Schubert, C | H31: Schubert, C | K31: Circuits of slime | L31: NATURE | O31: English | P31: News Item | AF31: Cheng S, 2006, ENVIRON SCI TECHNOL, V40, P2426, DOI 10.1021/es051652w; Kim BH, 1999, J MICROBIOL BIOTECHN, V9, P127; Potter MC, 1911, P R SOC LOND B-CONTA, V84, P260, DOI 10.1098/rspb.1911.0073; Reguera G, 2005, NATURE, V435, P1098, DOI 10.1038/nature03661; Reimers CE, 2001, ENVIRON SCI TECHNOL, V35, P192, DOI 10.1021/es001223s | AG31: 5 | AH31: 2 | AI31: 2 | AJ31: 1 | AK31: 9 | AL31: NATURE PUBLISHING GROUP | AM31: LONDON | AN31: MACMILLAN BUILDING, 4 CRINAN ST, LONDON N1 9XW, ENGLAND | AO31: 0028-0836 | AR31: NATURE | AS31: Nature | AT31: 43221 | AU31: 2006 | AV31: 441 | AW31: 7091 | BB31: 277 | BC31: 279 | BE31: 10.1038/441277a | BI31: 3 | BJ31: Multidisciplinary Sciences | BK31: Science & Technology - Other Topics | BL31: 043IB | BM31: WOS:000237593200014 | BN31: 16710388 | BR31: 43703
A32: 31 | B32: 10.1038/nrmicro1442 | C32: J | D32: Lovley, DR | H32: Lovley, Derek R. | K32: Bug juice: harvesting electricity with microorganisms | L32: NATURE REVIEWS MICROBIOLOGY | O32: English | P32: Review | W32: MICROBIAL FUEL-CELLS; INSOLUBLE FE(III) OXIDE; EXTRACELLULAR ELECTRON-TRANSFER; FE(III)-REDUCING BACTERIUM; GEOBACTER-SULFURREDUCENS; ANAEROBIC RESPIRATION; BIOFUEL CELLS; DISSIMILATORY REDUCTION; SHEWANELLA-PUTREFACIENS; SUBSURFACE ENVIRONMENTS | X32: It is well established that some reduced fermentation products or microbially reduced artificial mediators can abiotically react with electrodes to yield a small electrical current. This type of metabolism does not typically result in an efficient conversion of organic compounds to electricity because only some metabolic end products will react with electrodes, and the microorganisms only incompletely oxidize their organic fuels. A new form of microbial respiration has recently been discovered in which microorganisms conserve energy to support growth by oxidizing organic compounds to carbon dioxide with direct quantitative electron transfer to electrodes. These organisms, termed electricigens, offer the possibility of efficiently converting organic compounds into electricity in self-sustaining systems with long-term stability. | Y32: Univ Massachusetts, Dept Microbiol, Amherst, MA 01003 USA | Z32: Lovley, DR (reprint author), Univ Massachusetts, Dept Microbiol, Amherst, MA 01003 USA. | AA32: dlovley@microbio.umass.edu | AF32: Anderson RT, 2003, APPL ENVIRON MICROB, V69, P5884, DOI 10.1128/AEM.69.10.5884-5891.2003; Anderson RT, 1997, ADV MICROB ECOL, V15, P289; Angenent LT, 2004, TRENDS BIOTECHNOL, V22, P477, DOI 10.1016/j.tibtech.2004.07.001; ASTON WJ, 1984, BIOTECHNOL GENET ENG, V1, P89, DOI 10.1080/02648725.1984.10647782; BENNETTO HP, 1985, BIOTECHNOL LETT, V7, P699, DOI 10.1007/BF01032279; BENNETTO HP, 1990, FRONTIERS SCI, P66; Bond DR, 2002, SCIENCE, V295, P483, DOI 10.1126/science.1066771; Bond DR, 2005, APPL ENVIRON MICROB, V71, P2186, DOI 10.1128/AEM.71.4.2186-2189.2005; Bond DR, 2003, APPL ENVIRON MICROB, V69, P1548, DOI 10.1128/AEM.69.3.1548-1555.2003; Caccavo F, 1996, ARCH MICROBIOL, V165, P370, DOI 10.1007/s002030050340; Chaudhuri SK, 2003, NAT BIOTECHNOL, V21, P1229, DOI 10.1038/nbt867; CHENG S, 2006, ENV SCI TECHNOL; Childers SE, 2002, NATURE, V416, P767, DOI 10.1038/416767a; Cohen B., 1931, J BACTERIOL, V21, P18; Coppi MV, 2001, APPL ENVIRON MICROB, V67, P3180, DOI 10.1128/AEM.67.7.3180-3187.2001; DAIVS JB, 1963, ADV APPL MICROBIOL, P51; DeLong EF, 2002, NAT BIOTECHNOL, V20, P788, DOI 10.1038/nbt0802-788; Finneran KT, 2002, ENVIRON MICROBIOL, V4, P510, DOI 10.1046/j.1462-2920.2002.00317.x; Finneran KT, 2003, INT J SYST EVOL MICR, V53, P669, DOI 10.1099/ijs.0.02298-0; Gregory KB, 2005, ENVIRON SCI TECHNOL, V39, P8943, DOI 10.1021/es050457e; Gregory KB, 2004, ENVIRON MICROBIOL, V6, P596, DOI 10.1111/j.1462-2920.2004.00593.x; GREGORY KB, 2005, ABSTR GEN M AM SOC M, V114; Hernandez ME, 2004, APPL ENVIRON MICROB, V70, P921, DOI 10.1128/AEM.70.2.921-928.2004; Holmes DE, 2004, APPL ENVIRON MICROB, V70, P1234, DOI 10.1128/AEM.70.2.1234-1237.2004; Holmes DE, 2005, APPL ENVIRON MICROB, V71, P6870, DOI 10.1128/AEM.71.11.6870-6877.2005; Holmes DE, 2004, MICROB ECOL, V48, P178, DOI 10.1007/s00248-003-0004-4; Holmes DE, 2004, APPL ENVIRON MICROB, V70, P6023, DOI 10.1128/AEM.70.10.6023-6030.2004; HOLMES DE, 2006, IN PRESS ENV MICROBI; HOLMES DE, IN PRESS ENV MICROBI; KARUBE I, 1977, BIOTECHNOL BIOENG, V19, P1727, DOI 10.1002/bit.260191112; Kashefi K, 2004, GEOPH MONOG SERIES, V144, P199, DOI 10.1029/144GM13; Katz E., 2003, HDB FUEL CELLS FUNDA, V1, P355; Kim BH, 1999, J MICROBIOL BIOTECHN, V9, P127; Kim HJ, 2002, ENZYME MICROB TECH, V30, P145, DOI 10.1016/S0141-0229(01)00478-1; KONIKOFF JJ, 1963, AEROSPACE MED, V34, P1129; Krumholz LR, 1997, INT J SYST BACTERIOL, V47, P1262, DOI 10.1099/00207713-47-4-1262; LARMINIE J, 2003, FUEL CELL SYSTEMS EP; Lee JY, 2003, FEMS MICROBIOL LETT, V223, P185, DOI 10.1016/S0378-1097(03)00356-2; LEWIS K, 1966, BACTERIOL REV, V30, P101; Lies DP, 2005, APPL ENVIRON MICROB, V71, P4414, DOI 10.1128/AEM.71.8.4414-4426.2005; Liu H, 2004, ENVIRON SCI TECHNOL, V38, P4040, DOI 10.1021/es0499344; Logan BE, 2005, WATER SCI TECHNOL, V52, P31; LOVLEY DR, 1989, APPL ENVIRON MICROB, V55, P3234; Lovley DR, 1997, J IND MICROBIOL BIOT, V18, P75, DOI 10.1038/sj.jim.2900246; Lovley DR, 1999, ENVIRON MICROBIOL, V1, P89, DOI 10.1046/j.1462-2920.1999.00009.x; LOVLEY DR, 1989, APPL ENVIRON MICROB, V55, P700; LOVLEY DR, 1988, APPL ENVIRON MICROB, V54, P1472; Lovley DR, 1996, NATURE, V382, P445, DOI 10.1038/382445a0; Lovley DR, 2004, ADV MICROB PHYSIOL, V49, P219, DOI 10.1016/S0065-2911(04)49005-5; LOVLEY DR, PROKARYOTES; Mahadevan R, 2006, APPL ENVIRON MICROB, V72, P1558, DOI 10.1128/AEM.72.2.1558-1568.2006; Methe BA, 2003, SCIENCE, V302, P1967, DOI 10.1126/science.1088727; Myers CR, 2004, APPL ENVIRON MICROB, V70, P5415, DOI 10.1128/AEM.70.9.5415-5425.2004; Nevin KP, 2000, APPL ENVIRON MICROB, V66, P2248, DOI 10.1128/AEM.66.5.2248-2251.2000; Nevin KP, 2002, APPL ENVIRON MICROB, V68, P2294, DOI 10.1128/AEM.68.5.2294-2299.2002; Nevin KP, 2002, GEOMICROBIOL J, V19, P141, DOI 10.1080/01490450252864253; Newman DK, 2000, NATURE, V405, P94, DOI 10.1038/35011098; Park DH, 2003, BIOTECHNOL BIOENG, V81, P348, DOI 10.1002/bit.10501; Park DH, 2002, APPL MICROBIOL BIOT, V59, P58, DOI 10.1007/s00253-002-0972-1; Park HI, 2005, PROCESS BIOCHEM, V40, P3383, DOI 10.1016/j.procbio.2005.03.017; Park HS, 2001, ANAEROBE, V7, P297, DOI 10.1006/anae.2001.0399; Pham CA, 2003, FEMS MICROBIOL LETT, V223, P129, DOI 10.1016/S0378-1097(03)00354-9; Potter MC, 1911, P R SOC LOND B-CONTA, V84, P260, DOI 10.1098/rspb.1911.0073; Potter MC, 1910, P U DURHAM PHIL SOC, V3, P245; Rabaey K, 2005, TRENDS BIOTECHNOL, V23, P291, DOI 10.1016/j.tibtech.2005.04.008; Rabaey K, 2005, ENVIRON SCI TECHNOL, V39, P3401, DOI 10.1021/es048563o; Rabaey K, 2004, APPL ENVIRON MICROB, V70, P5373, DOI 10.1128/AEM.70.9.5373-5382.2004; Rabaey K, 2005, WATER SCI TECHNOL, V52, P515; Reguera G, 2005, NATURE, V435, P1098, DOI 10.1038/nature03661; REGUERA G, 2006, ABSTR GEN M AM SOC Q, V143; Reimers CE, 2001, ENVIRON SCI TECHNOL, V35, P192, DOI 10.1021/es001223s; Rhoads A, 2005, ENVIRON SCI TECHNOL, V39, P4666, DOI 10.1021/es048386r; Rosso KM, 2003, GEOCHIM COSMOCHIM AC, V67, P1081, DOI 10.1016/S0016-7037(02)00904-3; Schroder U, 2003, ANGEW CHEM INT EDIT, V42, P2880, DOI 10.1002/anie.200350918; Shantaram A, 2005, ENVIRON SCI TECHNOL, V39, P5037, DOI 10.1021/es0480668; Shukla AK, 2004, CURR SCI INDIA, V87, P455; Sisler FD, 1962, J WASH ACAD SCI, V52, P182; Sung Y, 2003, APPL ENVIRON MICROB, V69, P2964, DOI 10.1128/AEM.69.5.2964-2974; Tender LM, 2002, NAT BIOTECHNOL, V20, P821, DOI 10.1038/nbt716; Wilkinson S, 2000, AUTON ROBOT, V9, P99, DOI 10.1023/A:1008984516499 | AG32: 80 | AH32: 762 | AI32: 807 | AJ32: 20 | AK32: 346 | AL32: NATURE PUBLISHING GROUP | AM32: LONDON | AN32: MACMILLAN BUILDING, 4 CRINAN ST, LONDON N1 9XW, ENGLAND | AO32: 1740-1526 | AR32: NAT REV MICROBIOL | AS32: Nat. Rev. Microbiol. | AT32: JUL | AU32: 2006 | AV32: 4 | AW32: 7 | BB32: 497 | BC32: 508 | BE32: 10.1038/nrmicro1442 | BI32: 12 | BJ32: Microbiology | BK32: Microbiology | BL32: 063NF | BM32: WOS:000239024700010 | BN32: 16778836 | BR32: 43703
A33: 32 | B33: 10.1021/es0605016 | C33: J | D33: Logan, BE; Hamelers, B; Rozendal, RA; Schrorder, U; Keller, J; Freguia, S; Aelterman, P; Verstraete, W; Rabaey, K | H33: Logan, Bruce E.; Hamelers, Bert; Rozendal, Rene A.; Schrorder, Uwe; Keller, Jurg; Freguia, Stefano; Aelterman, Peter; Verstraete, Willy; Rabaey, Korneel | K33: Microbial fuel cells: Methodology and technology | L33: ENVIRONMENTAL SCIENCE & TECHNOLOGY | O33: English | P33: Review | W33: CONTINUOUS ELECTRICITY-GENERATION; SEDIMENT-WATER INTERFACE; PROTON-EXCHANGE MEMBRANE; REDUCED NEUTRAL RED; BIOFUEL CELLS; ELECTRON-TRANSFER; POWER-GENERATION; WASTE-WATER; ENERGY-CONSERVATION; HARVESTING ENERGY | X33: Microbial fuel cell (MFC) research is a rapidly evolving field that lacks established terminology and methods for the analysis of system performance. This makes it difficult for researchers to compare devices on an equivalent basis. The construction and analysis of MFCs requires knowledge of different scientific and engineering fields, ranging from microbiology and electrochemistry to materials and environmental engineering. Describing MFC systems therefore involves an understanding of these different scientific and engineering principles. In this paper, we provide a review of the different materials and methods used to construct MFCs, techniques used to analyze system performance, and recommendations on what information to include in MFC studies and the most useful ways to present results. | Y33: Penn State Univ, Hydrogen Energy Ctr, University Pk, PA 16802 USA; Wageningen Univ, Sub Dept Environm Technol, NL-6700 EV Wageningen, Netherlands; Wetsus, Ctr Sustainable Water Technol, NL-8900 CC Leeuwarden, Netherlands; Ernst Moritz Arndt Univ Greifswald, Inst Chem & Biochem, D-17489 Greifswald, Germany; Univ Queensland, AWMC, St Lucia, Qld 4072, Australia; Univ Ghent, Lab Microbial Ecol & Technol, B-9000 Ghent, Belgium | Z33: Logan, BE (reprint author), Penn State Univ, Hydrogen Energy Ctr, 212 Sackett Bldg, University Pk, PA 16802 USA. | AA33: blogan@psu.edu | AB33: Logan, Bruce/E-7063-2012; Keller, Jurg/C-3649-2013 | AC33: Logan, Bruce/0000-0001-7478-8070; Keller, Jurg/0000-0001-6796-0936; Hamelers, Hubertus/0000-0002-0990-4773; Rabaey, Korneel/0000-0001-8738-7778; Schroder, Uwe/0000-0002-8144-0328; Freguia, Stefano/0000-0002-2294-9036 | AF33: Aelterman P, 2006, ENVIRON SCI TECHNOL, V40, P3388, DOI 10.1021/es0525511; Alberty R.A., 2003, THERMODYNAMICS BIOCH; Amend JP, 2001, FEMS MICROBIOL REV, V25, P175, DOI 10.1016/S0168-6445(00)00062-0; Bard A. J, 1985, STANDARD POTENTIALS; Bard A. J., 2001, ELECTROCHEMICAL METH; Barton SC, 2004, CHEM REV, V104, P4867, DOI 10.1021/cr020719k; Bergel A, 2005, ELECTROCHEM COMMUN, V7, P900, DOI 10.1016/j.elecom.2005.06.006; BERK RS, 1964, APPL MICROBIOL, V12, P10; Bond DR, 2002, SCIENCE, V295, P483, DOI 10.1126/science.1066771; Bond DR, 2003, APPL ENVIRON MICROB, V69, P1548, DOI 10.1128/AEM.69.3.1548-1555.2003; Buisman CJN, 2005, International Patent., Patent No. [WO-2005-005981, 2005005981, WO2005005981]; Bullen RA, 2006, BIOSENS BIOELECTRON, V21, P2015, DOI 10.1016/j.bios.2006.01.030; Chaudhuri SK, 2003, NAT BIOTECHNOL, V21, P1229, DOI 10.1038/nbt867; Cheng S, 2006, ENVIRON SCI TECHNOL, V40, P364, DOI 10.1021/es0512071; Cheng S, 2006, ENVIRON SCI TECHNOL, V40, P2426, DOI 10.1021/es051652w; Cheng S, 2006, ELECTROCHEM COMMUN, V8, P489, DOI 10.1016/j.elecom.2006.01.010; Cohen B., 1931, J BACTERIOL, V21, P18; DAVIS JB, 1962, SCIENCE, V137, P615, DOI 10.1126/science.137.3530.615; Gil GC, 2003, BIOSENS BIOELECTRON, V18, P327, DOI 10.1016/S0956-5663(02)00110-0; Gorby Y. A., 2005, DOE NABIR M APR 20 W; GORBY YA, 2006, IN PRESS PNAS; HABERMANN W, 1991, APPL MICROBIOL BIOT, V35, P128; Hasvold O, 1997, J POWER SOURCES, V65, P253, DOI 10.1016/S0378-7753(97)02477-4; He Z, 2005, ENVIRON SCI TECHNOL, V39, P5262, DOI 10.1021/es0502876; He Z, 2006, ENVIRON SCI TECHNOL, V40, P5212, DOI 10.1021/es060394f; HEILMANN J, MICROBIAL FUEL CELLS; Heilmann J, 2006, WATER ENVIRON RES, V78, P531, DOI 10.2175/106143005X73046; Hoogers G., 2003, FUEL CELL TECHNOLOGY; Kim B.H., 1999, U.S. Patent, Patent No. [5976719, 5,976,719]; Kim HJ, 2002, ENZYME MICROB TECH, V30, P145, DOI 10.1016/S0141-0229(01)00478-1; Kim N, 2000, B KOR CHEM SOC, V21, P44; Larminie J, 2000, FUEL CELL SYSTEMS EX; Liu H, 2004, ENVIRON SCI TECHNOL, V38, P2281, DOI 10.1021/es034923g; Liu H, 2005, ENVIRON SCI TECHNOL, V39, P4317, DOI 10.1021/es050244p; Liu H, 2005, ENVIRON SCI TECHNOL, V39, P658, DOI 10.1021/es048927c; Liu H, 2004, ENVIRON SCI TECHNOL, V38, P4040, DOI 10.1021/es0499344; Liu H, 2005, ENVIRON SCI TECHNOL, V39, P5488, DOI 10.1021/es050316c; Logan BE, 2005, WATER RES, V39, P942, DOI 10.1016/j.watres.2004.11.019; Logan BE, 2004, ENVIRON SCI TECHNOL, V38, p160A, DOI 10.1021/es040468s; LOGAN BE, Patent No. 60588022; Logan BE, 2006, ENVIRON SCI TECHNOL, V40, P5172, DOI 10.1021/es0627592; Lowy DA, 2006, BIOSENS BIOELECTRON, V21, P2058, DOI 10.1016/j.bios.2006.01.033; Min B, 2004, ENVIRON SCI TECHNOL, V38, P5809, DOI 10.1021/es0491026; Min BK, 2005, WATER RES, V39, P1675, DOI 10.1016/j.watres.2005.02.002; NEWMAN J, 1973, ELECTROCHEMICAL SYST; Niessen J, 2004, ELECTROCHEM COMMUN, V6, P955, DOI 10.1016/j.elecom.2004.07.010; Niessen J, 2004, ELECTROCHEM COMMUN, V6, P571, DOI 10.1016/j.elecom.2004.04.006; Oh S, 2004, ENVIRON SCI TECHNOL, V38, P4900, DOI 10.1021/es049422p; Oh SE, 2006, APPL MICROBIOL BIOT, V70, P162, DOI 10.1007/s00253-005-0066-y; Park DH, 2003, BIOTECHNOL BIOENG, V81, P348, DOI 10.1002/bit.10501; Park DH, 1999, J BACTERIOL, V181, P2403; Park DH, 1999, APPL ENVIRON MICROB, V65, P2912; Park HS, 2001, ANAEROBE, V7, P297, DOI 10.1006/anae.2001.0399; Phung NT, 2004, FEMS MICROBIOL LETT, V233, P77, DOI 10.1016/j.femsle.2004.01.041; Potter MC, 1911, P R SOC LOND B-CONTA, V84, P260, DOI 10.1098/rspb.1911.0073; Rabaey K, 2005, TRENDS BIOTECHNOL, V23, P291, DOI 10.1016/j.tibtech.2005.04.008; Rabaey K, 2005, ENVIRON SCI TECHNOL, V39, P3401, DOI 10.1021/es048563o; Rabaey K, 2003, BIOTECHNOL LETT, V25, P1531, DOI 10.1023/A:1025484009367; Rabaey K, 2004, APPL ENVIRON MICROB, V70, P5373, DOI 10.1128/AEM.70.9.5373-5382.2004; Rabaey K, 2005, ENVIRON SCI TECHNOL, V39, P8077, DOI 10.1021/es050986i; Rabaey K, 2005, WATER SCI TECHNOL, V52, P515; RAO JR, 1976, BIOELECTROCH BIOENER, V3, P139, DOI 10.1016/0302-4598(76)85014-3; Reguera G, 2005, NATURE, V435, P1098, DOI 10.1038/nature03661; Reimers CE, 2001, ENVIRON SCI TECHNOL, V35, P192, DOI 10.1021/es001223s; Rhoads A, 2005, ENVIRON SCI TECHNOL, V39, P4666, DOI 10.1021/es048386r; Ringeisen BR, 2006, ENVIRON SCI TECHNOL, V40, P2629, DOI 10.1021/es052254w; Rosenbaum M, 2005, ENVIRON SCI TECHNOL, V39, P6328, DOI 10.1021/es0505447; ROZENDAL RA, ENV SCI TECHNOL; Rozendal RA, 2006, INT J HYDROGEN ENERG, V31, P1632, DOI 10.1016/j.ijhydene.2005.12.006; Schroder U, 2003, ANGEW CHEM INT EDIT, V42, P2880, DOI 10.1002/anie.200350918; SELL D, 1989, APPL MICROBIOL BIOT, V31, P211, DOI 10.1007/BF00262465; Shantaram A, 2005, ENVIRON SCI TECHNOL, V39, P5037, DOI 10.1021/es0480668; TANISHO S, 1989, BIOELECTROCH BIOENER, V21, P25, DOI 10.1016/0302-4598(89)87003-5; Tchobanoglous G., 1991, WASTEWATER ENG TREAT; Tender LM, 2002, NAT BIOTECHNOL, V20, P821, DOI 10.1038/nbt716; THAUER RK, 1977, BACTERIOL REV, V41, P100; Zhao F, 2005, ELECTROCHEM COMMUN, V7, P1405, DOI 10.1016/j.elecom.2005.09.032 | AG33: 77 | AH33: 2967 | AI33: 3229 | AJ33: 181 | AK33: 2734 | AL33: AMER CHEMICAL SOC | AM33: WASHINGTON | AN33: 1155 16TH ST, NW, WASHINGTON, DC 20036 USA | AO33: 0013-936X | AR33: ENVIRON SCI TECHNOL | AS33: Environ. Sci. Technol. | AT33: 37135 | AU33: 2006 | AV33: 40 | AW33: 17 | BB33: 5181 | BC33: 5192 | BE33: 10.1021/es0605016 | BI33: 12 | BJ33: Engineering, Environmental; Environmental Sciences | BK33: Engineering; Environmental Sciences & Ecology | BL33: 078UP | BM33: WOS:000240130200010 | BN33: 16999087 | BR33: 43703
A34: 33 | B34: 10.1111/j.1462-2920.2006.01065.x | C34: J | D34: Holmes, DE; Chaudhuri, SK; Nevin, KP; Mehta, T; Methe, BA; Liu, A; Ward, JE; Woodard, TL; Webster, J; Lovley, DR | H34: Holmes, Dawn E.; Chaudhuri, Swades K.; Nevin, Kelly P.; Mehta, Teena; Methe, Barbara A.; Liu, Anna; Ward, Joy E.; Woodard, Trevor L.; Webster, Jennifer; Lovley, Derek R. | K34: Microarray and genetic analysis of electron transfer to electrodes in Geobacter sulfurreducens | L34: ENVIRONMENTAL MICROBIOLOGY | O34: English | P34: Article | W34: QUANTITATIVE RT-PCR; FE(III) REDUCTION; ELECTRICITY-GENERATION; HOUSEKEEPING GENES; AQUATIC SEDIMENTS; FUEL-CELL; EXPRESSION; SUBSURFACE; QUANTIFICATION; NORMALIZATION | X34: Whole-genome analysis of gene expression in Geobacter sulfurreducens revealed 474 genes with transcript levels that were significantly different during growth with an electrode as the sole electron acceptor versus growth on Fe(III) citrate. The greatest response was a more than 19-fold increase in transcript levels for omcS, which encodes an outer-membrane cytochrome previously shown to be required for Fe(III) oxide reduction. Quantitative reverse transcription polymerase chain reaction and Northern analyses confirmed the higher levels of omcS transcripts, which increased as power production increased. Deletion of omcS inhibited current production that was restored when omcS was expressed in trans. Transcript expression and genetic analysis suggested that OmcE, another outer-membrane cytochrome, is also involved in electron transfer to electrodes. Surprisingly, genes for other proteins known to be important in Fe(III) reduction such as the outer-membrane c-type cytochrome, OmcB, and the electrically conductive pilin 'nanowires' did not have higher transcript levels on electrodes, and deletion of the relevant genes did not inhibit power production. Changes in the transcriptome suggested that cells growing on electrodes were subjected to less oxidative stress than cells growing on Fe(III) citrate and that a number of genes annotated as encoding metal efflux proteins or proteins of unknown function may be important for growth on electrodes. These results demonstrate for the first time that it is possible to evaluate gene expression, and hence the metabolic state, of microorganisms growing on electrodes on a genome-wide basis and suggest that OmcS, and to a lesser extent OmcE, are important in electron transfer to electrodes. This has important implications for the design of electrode materials and the genetic engineering of microorganisms to improve the function of microbial fuel cells. | Y34: Univ Massachusetts, Dept Microbiol, Amherst, MA 01003 USA; Inst Genom Res, Rockville, MD 20850 USA | Z34: Holmes, DE (reprint author), Univ Massachusetts, Dept Microbiol, Amherst, MA 01003 USA. | AA34: dholmes@microbio.umass.edu | AF34: Afkar E, 2005, BMC MICROBIOL, V5, DOI 10.1186/1471-2180-5-41; Ausubel FA, 1997, CURRENT PROTOCOLS MO; Bond DR, 2002, SCIENCE, V295, P483, DOI 10.1126/science.1066771; Bond DR, 2005, APPL ENVIRON MICROB, V71, P2186, DOI 10.1128/AEM.71.4.2186-2189.2005; Bond DR, 2003, APPL ENVIRON MICROB, V69, P1548, DOI 10.1128/AEM.69.3.1548-1555.2003; BRADY RA, 1988, J BACTERIOL, V170, P2379, DOI 10.1128/jb.170.5.2379-2382.1988; Cabiscol Elisa, 2000, International Microbiology, V3, P3; Chaudhuri SK, 2003, NAT BIOTECHNOL, V21, P1229, DOI 10.1038/nbt867; Coppi MV, 2001, APPL ENVIRON MICROB, V67, P3180, DOI 10.1128/AEM.67.7.3180-3187.2001; Gregory K. B., 2005, 105 AM SOC MICR GEN; Holmes DE, 2004, APPL ENVIRON MICROB, V70, P7251, DOI 10.1128/AEM.70.12.7251-7259.2004; Holmes DE, 2005, APPL ENVIRON MICROB, V71, P6870, DOI 10.1128/AEM.71.11.6870-6877.2005; Holmes DE, 2004, MICROB ECOL, V48, P178, DOI 10.1007/s00248-003-0004-4; Holmes DE, 2004, APPL ENVIRON MICROB, V70, P6023, DOI 10.1128/AEM.70.10.6023-6030.2004; Jara M, 2003, J BACTERIOL, V185, P2493, DOI 10.1128/JB.185.8.2493-2502.2003; JUNNEMAN S, 1997, BIOCHIM BIOPHYS ACTA, V1321, P107; Kim HJ, 2002, ENZYME MICROB TECH, V30, P145, DOI 10.1016/S0141-0229(01)00478-1; Leang C, 2003, J BACTERIOL, V185, P2096, DOI 10.1128/JB.185.7.2096-2103.2003; Leang C, 2005, J BACTERIOL, V187, P5918, DOI 10.1128/JB.187.17.5918-5926.2005; Lin WC, 2004, APPL ENVIRON MICROB, V70, P2525, DOI 10.1128/AEM.70.4.2525-2528.2004; LOVLEY DR, 1987, APPL ENVIRON MICROB, V53, P1536; LOVLEY DR, 1988, APPL ENVIRON MICROB, V54, P1472; Lovley DR, 2004, ADV MICROB PHYSIOL, V49, P219, DOI 10.1016/S0065-2911(04)49005-5; LOVLEY DR, 2006, IN PRESS NAT REV MIC; Marlowe EM, 2002, BIODEGRADATION, V13, P251, DOI 10.1023/A:1021221104425; Mehta T, 2005, APPL ENVIRON MICROB, V71, P8634, DOI 10.1128/AEM.71.12.8634-8641.2005; MEHTA T, 2006, IN PRESS MICROBIOLOG; Methe BA, 2005, APPL ENVIRON MICROB, V71, P2530, DOI 10.1128/AEM.71.5.2530-2538.2005; Methe BA, 2003, SCIENCE, V302, P1967, DOI 10.1126/science.1088727; Nies DH, 1999, APPL MICROBIOL BIOT, V51, P730, DOI 10.1007/s002530051457; NIES DH, 1995, J BACTERIOL, V177, P2707, DOI 10.1128/jb.177.10.2707-2712.1995; Potter MC, 1911, P R SOC LOND B-CONTA, V84, P260, DOI 10.1098/rspb.1911.0073; Reguera G, 2005, NATURE, V435, P1098, DOI 10.1038/nature03661; Rodionov DA, 2004, GENOME BIOL, V5, DOI 10.1186/gb-2004-5-11-r90; Rodriguez Madeleine W., 2004, BMC Immunology, V5, DOI 10.1186/1471-2172-5-13; Savli H, 2003, J MED MICROBIOL, V52, P403, DOI 10.1099/jmm.0.05132-0; Smyth G.K., 2004, STAT APPL GENET MOL, V3; Smyth GK, 2005, STAT BIOL HEALTH, P397, DOI 10.1007/0-387-29362-0_23; Smyth GK, 2005, BIOINFORMATICS, V21, P2067, DOI 10.1093/bioinformatics/bti270; Smyth GK, 2003, METHODS, V31, P265, DOI 10.1016/S1046-2023(03)00155-5; Storey JD, 2003, P NATL ACAD SCI USA, V100, P9440, DOI 10.1073/pnas.1530509100; Tender LM, 2002, NAT BIOTECHNOL, V20, P821, DOI 10.1038/nbt716; Tusher VG, 2001, P NATL ACAD SCI USA, V98, P5116, DOI 10.1073/pnas.091062498; Vandecasteele SJ, 2001, J BACTERIOL, V183, P7094, DOI 10.1128/JB.183.24.7094-7101.2001; Vandesompele J, 2002, GENOME BIOL, V3, DOI 10.1186/gb-2002-3-7-research0034 | AG34: 45 | AH34: 200 | AI34: 215 | AJ34: 7 | AK34: 86 | AL34: WILEY | AM34: HOBOKEN | AN34: 111 RIVER ST, HOBOKEN 07030-5774, NJ USA | AO34: 1462-2912 | AP34: 1462-2920 | AR34: ENVIRON MICROBIOL | AS34: Environ. Microbiol. | AT34: OCT | AU34: 2006 | AV34: 8 | AW34: 10 | BB34: 1805 | BC34: 1815 | BE34: 10.1111/j.1462-2920.2006.01065.x | BI34: 11 | BJ34: Microbiology | BK34: Microbiology | BL34: 079VE | BM34: WOS:000240205200013 | BN34: 16958761 | BR34: 43703
A35: 34 | B35: 10.1016/j.tim.2006.10.003 | C35: J | D35: Logan, BE; Regan, JM | H35: Logan, Bruce E.; Regan, John M. | K35: Electricity-producing bacterial communities in microbial fuel cells | L35: TRENDS IN MICROBIOLOGY | O35: English | P35: Review | W35: SEDIMENT-WATER INTERFACE; WASTE-WATER; ELECTRON-TRANSFER; HARVESTING ELECTRICITY; POWER-GENERATION; BIOFUEL CELLS; MICROORGANISMS; HYDROGEN; MEMBRANE; ACETATE | X35: Microbial fuel cells (MFCs) are not yet commercialized but they show great promise as a method of water treatment and as power sources for environmental sensors. The power produced by these systems is currently limited, primarily by high internal (ohmic) resistance. However, improvements in the system architecture will soon result in power generation that is dependent on the capabilities of the microorganisms. The bacterial communities that develop in these systems show great diversity, ranging from primarily delta-Proteobacteria that predominate in sediment MFCs to communities composed of alpha-, beta-, gamma- or delta-Proteobacteria, Firmicutes and uncharacterized clones in other types of MFCs. Much remains to be discovered about the physiology of these bacteria capable of exocellular electron transfer, collectively defined as a community of 'exoelectrogens'. Here, we review the microbial communities found in MFCs and the prospects for this emerging bioenergy technology. | Y35: Penn State Univ, Dept Civil & Environm Engn, University Pk, PA 16802 USA | Z35: Logan, BE (reprint author), Penn State Univ, Dept Civil & Environm Engn, University Pk, PA 16802 USA. | AA35: blogan@psu.edu | AB35: Logan, Bruce/E-7063-2012 | AC35: Logan, Bruce/0000-0001-7478-8070 | AF35: Aelterman P, 2006, ENVIRON SCI TECHNOL, V40, P3388, DOI 10.1021/es0525511; Bond DR, 2002, SCIENCE, V295, P483, DOI 10.1126/science.1066771; Bond DR, 2003, APPL ENVIRON MICROB, V69, P1548, DOI 10.1128/AEM.69.3.1548-1555.2003; Cheng S, 2006, ENVIRON SCI TECHNOL, V40, P364, DOI 10.1021/es0512071; Cheng S, 2006, ENVIRON SCI TECHNOL, V40, P2426, DOI 10.1021/es051652w; Cheng S, 2006, ELECTROCHEM COMMUN, V8, P489, DOI 10.1016/j.elecom.2006.01.010; Gorby YA, 2006, P NATL ACAD SCI USA, V103, P11358, DOI 10.1073/pnas.0604517103; He Z, 2005, ENVIRON SCI TECHNOL, V39, P5262, DOI 10.1021/es0502876; Heilmann J, 2006, WATER ENVIRON RES, V78, P531, DOI 10.2175/106143005X73046; HERNANDEZ ME, 2004, APPL ENVIRON MICROB, V79, P921; Holmes DE, 2004, MICROB ECOL, V48, P178, DOI 10.1007/s00248-003-0004-4; Ishii S, 2005, APPL ENVIRON MICROB, V71, P7838, DOI 10.1128/AEM.71.12.7838-7845.2005; Kim B.H., 1999, U.S. Patent, Patent No. [5976719, 5,976,719]; Kim BH, 2004, APPL MICROBIOL BIOT, V63, P672, DOI 10.1007/s00253-003-1412-6; Kim BH, 2003, BIOTECHNOL LETT, V25, P541, DOI 10.1023/A:1022891231369; KIM JR, IN PRESS BIORES TECH; Lee JY, 2003, FEMS MICROBIOL LETT, V223, P185, DOI 10.1016/S0378-1097(03)00356-2; Lies DP, 2005, APPL ENVIRON MICROB, V71, P4414, DOI 10.1128/AEM.71.8.4414-4426.2005; Liu H, 2004, ENVIRON SCI TECHNOL, V38, P2281, DOI 10.1021/es034923g; Liu H, 2005, ENVIRON SCI TECHNOL, V39, P4317, DOI 10.1021/es050244p; Liu H, 2005, ENVIRON SCI TECHNOL, V39, P658, DOI 10.1021/es048927c; Liu H, 2004, ENVIRON SCI TECHNOL, V38, P4040, DOI 10.1021/es0499344; Liu H, 2005, ENVIRON SCI TECHNOL, V39, P5488, DOI 10.1021/es050316c; Logan BE, 2005, WATER RES, V39, P942, DOI 10.1016/j.watres.2004.11.019; LOGAN BE, 2005, Patent No. 60588022; Logan BE, 2006, ENVIRON SCI TECHNOL, V40, P5172, DOI 10.1021/es0627592; Lovley DR, 2006, NAT REV MICROBIOL, V4, P497, DOI 10.1038/nrmicro1442; Lowy DA, 2006, BIOSENS BIOELECTRON, V21, P2058, DOI 10.1016/j.bios.2006.01.033; Min B, 2005, WATER RES, V39, P4961, DOI 10.1016/j.watres.2005.09.039; Min B, 2004, ENVIRON SCI TECHNOL, V38, P5809, DOI 10.1021/es0491026; Min BK, 2005, WATER RES, V39, P1675, DOI 10.1016/j.watres.2005.02.002; Morrow WR, 2006, ENVIRON SCI TECHNOL, V40, P2877, DOI 10.1021/es048296m; MYERS CR, 1992, J BACTERIOL, V174, P3429; Nielsen JL, 2002, APPL ENVIRON MICROB, V68, P4629, DOI 10.1128/AEM.68.9.4629-4636.2002; Niessen J, 2004, ELECTROCHEM COMMUN, V6, P955, DOI 10.1016/j.elecom.2004.07.010; Oh SE, 2005, WATER RES, V39, P4673, DOI 10.1016/j.watres.2005.09.019; Pham CA, 2003, FEMS MICROBIOL LETT, V223, P129, DOI 10.1016/S0378-1097(03)00354-9; Phung NT, 2004, FEMS MICROBIOL LETT, V233, P77, DOI 10.1016/j.femsle.2004.01.041; Potter MC, 1911, P R SOC LOND B-CONTA, V84, P260, DOI 10.1098/rspb.1911.0073; Rabaey K, 2005, ENVIRON SCI TECHNOL, V39, P3401, DOI 10.1021/es048563o; Rabaey K, 2003, BIOTECHNOL LETT, V25, P1531, DOI 10.1023/A:1025484009367; Rabaey K, 2004, APPL ENVIRON MICROB, V70, P5373, DOI 10.1128/AEM.70.9.5373-5382.2004; Rabaey K, 2005, ENVIRON SCI TECHNOL, V39, P8077, DOI 10.1021/es050986i; Rabaey K, 2005, WATER SCI TECHNOL, V52, P515; Ragauskas AJ, 2006, SCIENCE, V311, P484, DOI 10.1126/science.1114736; Reguera G, 2005, NATURE, V435, P1098, DOI 10.1038/nature03661; Reimers CE, 2001, ENVIRON SCI TECHNOL, V35, P192, DOI 10.1021/es001223s; Rosenbaum M, 2005, ENVIRON SCI TECHNOL, V39, P6328, DOI 10.1021/es0505447; ROZENDAL RA, IN PRESS INT J HYDRO; Schroder U, 2003, ANGEW CHEM INT EDIT, V42, P2880, DOI 10.1002/anie.200350918; Stams AJM, 2006, ENVIRON MICROBIOL, V8, P371, DOI 10.1111/j.1462-2920.2006.00989.x; Tender LM, 2002, NAT BIOTECHNOL, V20, P821, DOI 10.1038/nbt716; Zhao F, 2005, ELECTROCHEM COMMUN, V7, P1405, DOI 10.1016/j.elecom.2005.09.032; ZUO Y, 2005, ENERG FUEL, V20, P1716 | AG35: 54 | AH35: 648 | AI35: 701 | AJ35: 24 | AK35: 387 | AL35: ELSEVIER SCIENCE LONDON | AM35: LONDON | AN35: 84 THEOBALDS RD, LONDON WC1X 8RR, ENGLAND | AO35: 0966-842X | AR35: TRENDS MICROBIOL | AS35: Trends Microbiol. | AT35: DEC | AU35: 2006 | AV35: 14 | AW35: 12 | BB35: 512 | BC35: 518 | BE35: 10.1016/j.tim.2006.10.003 | BI35: 7 | BJ35: Biochemistry & Molecular Biology; Microbiology | BK35: Biochemistry & Molecular Biology; Microbiology | BL35: 116HZ | BM35: WOS:000242794500002 | BN35: 17049240 | BR35: 43703
A36: 35 | B36: 10.1016/j.bios.2006.04.029 | C36: J | D36: Davis, F; Higson, SPJ | H36: Davis, Frank; Higson, Seamus P. J. | K36: Biofuel cells - Recent advances and applications | L36: BIOSENSORS & BIOELECTRONICS | O36: English | P36: Article | V36: bioelectronics; biofuel cells; glucose oxidase; microbial fuel cells | W36: MICROBIAL FUEL-CELLS; NICOTINAMIDE ADENINE-DINUCLEOTIDE; ELECTRICITY-GENERATION; ELECTRON-TRANSFER; DEHYDROGENASE ENZYMES; OXYGEN REDUCTION; POWER OUTPUT; THIN-FILMS; PERFORMANCE; WATER | X36: In 2006, the journal Biosensors and Bioelectronics published a special issue devoted exclusively to biofuel cells, including several research papers and an extensive review of the field [Bullen, R.A,, Arnot, T.C., Lakeman, J.B., Walsh, F.C., 2006. Biosens. Bioelectron.]. Within this review a brief description will firstly be given of the history of biofuel cells together with coverage of some of the major historical advances. The review is intended, however, to largely concentrate on and give an overview of the advances made in recent years in this area together with a discussion surrounding the practical application of biofuel cells. There are several classes of biofuel cells: we shall firstly discuss the recent advances in biofuel cells that convert chemical fuels to produce electrical power by use of catalytic enzymes. This will be followed by a section on similar cells where micro-organisms rather than enzymes are used to convert the fuel to energy. Thirdly we shall consider hybrid biofuel cells that combine the utilisation of photochemical chemistries and biological systems for the generation of electricity. Finally we will discuss some of the proposed uses of biofuel cells together with a short consideration of future research possibilities and applications of these systems. (c) 2006 Elsevier B.V. All rights reserved. | Y36: Cranfield Univ, Cranfield Hlth, Silsoe MK45 4DT, Beds, England | Z36: Higson, SPJ (reprint author), Cranfield Univ, Cranfield Hlth, Silsoe MK45 4DT, Beds, England. | AA36: s.p.j.higson@cranfield.ac.uk | AC36: , Frank/0000-0002-2669-9169 | AF36: Akers NL, 2005, ELECTROCHIM ACTA, V50, P2521, DOI 10.1016/j.electacta.2004.10.080; ALLEN RM, 1993, APPL BIOCHEM BIOTECH, V39, P27, DOI 10.1007/BF02918975; ASTON WJ, 1984, BIOTECHNOL GENET ENG, V1, P89, DOI 10.1080/02648725.1984.10647782; Bagotzky VS, 2003, RUSS J ELECTROCHEM+, V39, P919, DOI 10.1023/A:1025719619261; Barriere F, 2004, ELECTROCHEM COMMUN, V6, P237, DOI 10.1016/j.elecom.2003.12.006; Barton SC, 2004, CHEM REV, V104, P4867, DOI 10.1021/cr020719k; BENNETTO HP, 1985, BIOTECHNOL LETT, V7, P699, DOI 10.1007/BF01032279; Bennetto HP, 1987, NEW SCI, V114, P36; Bond DR, 2002, SCIENCE, V295, P483, DOI 10.1126/science.1066771; Bond DR, 2003, APPL ENVIRON MICROB, V69, P1548, DOI 10.1128/AEM.69.3.1548-1555.2003; Brune A, 2004, LANGMUIR, V20, P8366, DOI 10.1021/la048974i; Bullen RA, 2006, BIOSENS BIOELECTRON, V21, P2015, DOI 10.1016/j.bios.2006.01.030; Chaudhuri SK, 2003, NAT BIOTECHNOL, V21, P1229, DOI 10.1038/nbt867; Cohen B., 1931, J BACTERIOL, V21, P18; Davis F, 2005, BIOSENS BIOELECTRON, V21, P1, DOI 10.1016/j.bios.2004.10.001; DAVIS JB, 1962, SCIENCE, V137, P615, DOI 10.1126/science.137.3530.615; de Bruijn F, 2005, GREEN CHEM, V7, P132, DOI 10.1039/b415317k; de la Garza L, 2003, J PHYS CHEM B, V107, P10252, DOI 10.1021/jp030360j; Farneth WE, 2005, J ELECTROANAL CHEM, V581, P197, DOI 10.1016/j.jelechem.2005.03.018; Farneth WE, 2005, J ELECTROANAL CHEM, V581, P190, DOI 10.1016/j.jelechem.2005.03.025; Gil GC, 2003, BIOSENS BIOELECTRON, V18, P327, DOI 10.1016/S0956-5663(02)00110-0; Granot E, 2005, CHEM MATER, V17, P4600, DOI 10.1021/cm050193v; Halliwell CM, 2002, BIOELECTROCHEMISTRY, V55, P21, DOI 10.1016/S1567-5394(01)00172-4; Heller A, 2004, PHYS CHEM CHEM PHYS, V6, P209, DOI 10.1039/b313149a; Ieropoulos L, 2005, J POWER SOURCES, V145, P253, DOI 10.1016/j.jpowsour.2004.11.070; JONES AK, 2002, J CHEM SOC CHEM COMM, P866; KARYAKIN AA, 2002, ELECTROCHEM COMMUN, V41, P417; Katz E, 1999, NEW J CHEM, V23, P481, DOI 10.1039/a808561g; Katz E, 1999, J ELECTROANAL CHEM, V479, P64, DOI 10.1016/S0022-0728(99)00425-8; Katz E, 2005, J AM CHEM SOC, V127, P3979, DOI 10.1021/ja044157t; Katz E, 2003, J AM CHEM SOC, V125, P6803, DOI 10.1021/ja034008v; Katz E, 2001, J AM CHEM SOC, V123, P10752, DOI 10.1021/ja0167102; Katz E., 2003, HDB FUEL CELLS FUNDA, V1, P355; Kelley SC, 2000, ELECTROCHEM SOLID ST, V3, P407; Kelly I, 2003, ROBOTICA, V21, P399, DOI 10.1017/S0263574703004934; KIM HH, 2003, J ELECTROCHEM SOC, V150, P209; Kim JR, 2005, APPL MICROBIOL BIOT, V68, P23, DOI 10.1007/s00253-004-1845-6; Kim N, 2000, BIOTECHNOL BIOENG, V70, P109, DOI 10.1002/1097-0290(20001005)70:1<109::AID-BIT11>3.0.CO;2-M; Liu H, 2004, ENVIRON SCI TECHNOL, V38, P4040, DOI 10.1021/es0499344; Liu Y, 2005, CHEM-EUR J, V11, P4970, DOI 10.1002/chem.200500308; Liu Y, 2005, J ELECTROANAL CHEM, V581, P1, DOI 10.1016/j.jelechem.2005.01.022; Logan BE, 2005, WATER SCI TECHNOL, V52, P31; Logan BE, 2005, WATER RES, V39, P942, DOI 10.1016/j.watres.2004.11.019; Lowy DA, 2006, BIOSENS BIOELECTRON, V21, P2058, DOI 10.1016/j.bios.2006.01.033; Mano N, 2003, J AM CHEM SOC, V125, P15290, DOI 10.1021/ja038285d; Mano N, 2003, J AM CHEM SOC, V125, P6588, DOI 10.1021/ja0346328; MANO N, 2004, CHEM BIOCH, V51, P1703; Mano N., 2003, J CHEM SOC CHEM COMM, P518; MANO N, 2002, J PHYS CHEM B, V106, P884; Min BK, 2005, WATER RES, V39, P1675, DOI 10.1016/j.watres.2005.02.002; Moore CM, 2005, LAB CHIP, V5, P218, DOI 10.1039/b412719f; Niessen J, 2004, ELECTROCHEM COMMUN, V6, P955, DOI 10.1016/j.elecom.2004.07.010; Palmore GTR, 1998, J ELECTROANAL CHEM, V443, P155, DOI 10.1016/S0022-0728(97)00393-8; Palmore GTR, 1999, J ELECTROANAL CHEM, V464, P110, DOI 10.1016/S0022-0728(99)00008-X; Park DH, 2003, BIOTECHNOL BIOENG, V81, P348, DOI 10.1002/bit.10501; Park DH, 2000, BIOTECHNOL LETT, V22, P1301, DOI 10.1023/A:1005674107841; PERSSON B, 1986, BIOELECTROCH BIOENER, V16, P479, DOI 10.1016/0302-4598(86)80069-1; Pizzariello A, 2002, BIOELECTROCHEMISTRY, V56, P99, DOI 10.1016/S1567-5394(02)00026-9; Potter MC, 1911, P R SOC LOND B-CONTA, V84, P260, DOI 10.1098/rspb.1911.0073; Rabaey K, 2005, ENVIRON SCI TECHNOL, V39, P3401, DOI 10.1021/es048563o; Rabaey K, 2003, BIOTECHNOL LETT, V25, P1531, DOI 10.1023/A:1025484009367; Rabaey K, 2004, APPL ENVIRON MICROB, V70, P5373, DOI 10.1128/AEM.70.9.5373-5382.2004; Rabaey K, 2005, ENVIRON SCI TECHNOL, V39, P8077, DOI 10.1021/es050986i; Rabaey K, 2005, WATER SCI TECHNOL, V52, P515; RABAEY K, 2005, TRENDS BIOTECHNOL, V23, P691; Ramanavicius A, 2005, BIOSENS BIOELECTRON, V20, P1962, DOI 10.1016/j.bios.2004.08.032; RAO JR, 1976, BIOELECTROCH BIOENER, V3, P139, DOI 10.1016/0302-4598(76)85014-3; Rhoads A, 2005, ENVIRON SCI TECHNOL, V39, P4666, DOI 10.1021/es048386r; ROLLER SD, 1983, P INT C COMM APPL BI, P655; SATO F, 2005, ELECTROCHEM COMMUN, V71, P643; SCOUTEN WH, 1995, TRENDS BIOTECHNOL, V13, P178, DOI 10.1016/S0167-7799(00)88935-0; Shukla AK, 2004, CURR SCI INDIA, V87, P455; Shukla AK, 1999, CURR SCI INDIA, V77, P1141; Simon E, 2002, BIOELECTROCHEMISTRY, V55, P13, DOI 10.1016/S1567-5394(01)00160-8; SOOKEUN J, 2005, J MICROBIOL BIOTECHN, V15, P234; Soukharev V, 2004, J AM CHEM SOC, V126, P8368, DOI 10.1021/ja0475510; TARASEVICH MR, 2003, ELECTROCHEM COMMUN, V6, P491; Tsujimura S, 2002, ELECTROCHEMISTRY, V70, P940; Tsujimura S, 2001, ENZYME MICROB TECH, V29, P225, DOI 10.1016/S0141-0229(01)00374-X; Tsujimura S, 2001, PHYS CHEM CHEM PHYS, V3, P1331, DOI 10.1039/b009539g; Tsujimura S, 2005, J ELECTROANAL CHEM, V576, P113, DOI 10.1016/j.jelechem.2004.09.031; TURNER APF, 1982, BIOL FUEL CELL FUEL, P107; VOSTIAR I, 2004, ELECTROCHEM COMMUN, V61, P626; Wang MK, 2005, BIOSENS BIOELECTRON, V21, P159, DOI 10.1016/j.bios.2004.08.012; WIEBEL MK, 1975, ARCH BIOCHEM BIOPHYS, V169, P146; Wilkinson S, 2000, AUTON ROBOT, V9, P99, DOI 10.1023/A:1008984516499; WILLNER I, 1998, J CHEM SOC P2, V8, P1822; WILLNER I, 1998, BIOELECTROCH BIOENER, V44, P214; Yagishita T, 1997, SOL ENERGY, V61, P347, DOI 10.1016/S0038-092X(97)00069-8; Yagishita T, 1998, J FERMENT BIOENG, V85, P546, DOI 10.1016/S0922-338X(98)80106-2; Yuhashi N, 2005, BIOSENS BIOELECTRON, V20, P2145, DOI 10.1016/j.bios.2004.08.017 | AG36: 91 | AH36: 361 | AI36: 373 | AJ36: 4 | AK36: 158 | AL36: ELSEVIER ADVANCED TECHNOLOGY | AM36: OXFORD | AN36: OXFORD FULFILLMENT CENTRE THE BOULEVARD, LANGFORD LANE, KIDLINGTON, OXFORD OX5 1GB, OXON, ENGLAND | AO36: 0956-5663 | AR36: BIOSENS BIOELECTRON | AS36: Biosens. Bioelectron. | AT36: 42036 | AU36: 2007 | AV36: 22 | AW36: 7 | BB36: 1224 | BC36: 1235 | BE36: 10.1016/j.bios.2006.04.029 | BI36: 12 | BJ36: Biophysics; Biotechnology & Applied Microbiology; Chemistry, Analytical; Electrochemistry; Nanoscience & Nanotechnology | BK36: Biophysics; Biotechnology & Applied Microbiology; Chemistry; Electrochemistry; Science & Technology - Other Topics | BL36: 138TM | BM36: WOS:000244385400006 | BN36: 16781864 | BR36: 43703
A37: 36 | B37: 10.1039/b703627m | C37: J | D37: Schroder, U | H37: Schroeder, Uwe | K37: Anodic electron transfer mechanisms in microbial fuel cells and their energy efficiency | L37: PHYSICAL CHEMISTRY CHEMICAL PHYSICS | O37: English | P37: Article | W37: ELECTRICITY-GENERATION; FE(III)-REDUCING BACTERIUM; BIOFUEL CELLS; NEUTRAL RED; PERFORMANCE; REDUCTION; OXIDATION; HYDROGEN; MR-1 | X37: The performance of a microbial fuel cell (MFC) depends on a complex system of parameters. Apart from technical variables like the anode or fuel cell design, it is mainly the paths and mechanisms of the bioelectrochemical energy conversion that decisively determine the MFC power and energy output. Here, the electron transfer from the microbial cell to the fuel cell anode, as a process that links microbiology and electrochemistry, represents a key factor that defines the theoretical limits of the energy conversion. The determination of the energy efficiency of the electron transfer reactions, based on the biological standard potentials of the involved redox species in combination with the known paths (and stoichiometry) of the underlying microbial metabolism, is an important instrument for this discussion. Against the sometimes confusing classifications of MFCs in literature it is demonstrated that the anodic electron transfer is always based on one and the same background: the exploitation of the necessity of every living cell to dispose the electrons liberated during oxidative substrate degradation. | Y37: Ernst Moritz Arndt Univ Greifswald, Inst Biochem, D-17487 Greifswald, Germany | Z37: Schroder, U (reprint author), Ernst Moritz Arndt Univ Greifswald, Inst Biochem, Felix Hausdorff Str 4, D-17487 Greifswald, Germany. | AA37: uiveschr@uni-greifswald.de | AC37: Schroder, Uwe/0000-0002-8144-0328 | AF37: ASTON WJ, 1984, BIOTECHNOL GENET ENG, V1, P89, DOI 10.1080/02648725.1984.10647782; Barton SC, 2004, CHEM REV, V104, P4867, DOI 10.1021/cr020719k; BENNETTO H P, 1984, Life Chemistry Reports, V2, P363; BENNETTO HP, 1983, BIOTECHNOL BIOENG, V25, P559, DOI 10.1002/bit.260250219; Bennetto HP, 1990, BIOTECHNOL ED, V1, P163, DOI DOI 10.2166/WST2011.822; BOCKRIS JO, 1993, SURFACE ELECTROCHEMI, P319; Bond DR, 2003, APPL ENVIRON MICROB, V69, P1548, DOI 10.1128/AEM.69.3.1548-1555.2003; Bullen RA, 2006, BIOSENS BIOELECTRON, V21, P2015, DOI 10.1016/j.bios.2006.01.030; Canfield J. H., 1963, NASA TECHNICAL REPOR, P63; Chan HM, 2001, INT J MOD PHYS A, V16, P163, DOI 10.1142/S0217751X0100298X; Chaudhuri SK, 2003, NAT BIOTECHNOL, V21, P1229, DOI 10.1038/nbt867; Cheng S, 2006, ENVIRON SCI TECHNOL, V40, P364, DOI 10.1021/es0512071; Cohen B., 1931, J BACTERIOL, V21, P18; Cohn E. M., 1963, DEV IND MICROBIOL, V4, P53; DELANEY GM, 1984, J CHEM TECH BIOT B, V34, P13; Finkelstein DA, 2006, ENVIRON SCI TECHNOL, V40, P6990, DOI 10.1021/es061146m; Friedheim E, 1931, J BIOL CHEM, V91, P355; Gil GC, 2003, BIOSENS BIOELECTRON, V18, P327, DOI 10.1016/S0956-5663(02)00110-0; Gorby YA, 2006, P NATL ACAD SCI USA, V103, P11358, DOI 10.1073/pnas.0604517103; HABERMANN W, 1991, APPL MICROBIOL BIOT, V35, P128; HADDOCK BA, 1977, BACTERIOL REV, V41, P47; He Z, 2006, ELECTROANAL, V18, P2009, DOI 10.1002/elan.200603628; Heller A, 2004, PHYS CHEM CHEM PHYS, V6, P209, DOI 10.1039/b313149a; Hernandez ME, 2001, CELL MOL LIFE SCI, V58, P1562, DOI 10.1007/PL00000796; Holmes DE, 2004, APPL ENVIRON MICROB, V70, P6023, DOI 10.1128/AEM.70.10.6023-6030.2004; IEROPOULUS I, 2005, P AUT ROB SYS C; KARUBE I, 1977, BIOTECHNOL BIOENG, V19, P1727, DOI 10.1002/bit.260191112; KATZ E, 2003, HDB FUEL CELL FUNDAM, V1; Kim B, 2001, International Patent, Patent No. [WO 01/04626, 0104626]; Kim B.H., 1999, U.S. Patent, Patent No. [5976719, 5,976,719]; Kim BH, 2004, APPL MICROBIOL BIOT, V63, P672, DOI 10.1007/s00253-003-1412-6; Kim BH, 1999, J MICROBIOL BIOTECHN, V9, P127; Kim HJ, 2002, ENZYME MICROB TECH, V30, P145, DOI 10.1016/S0141-0229(01)00478-1; LEWIS K, 1966, BACTERIOL REV, V30, P101; Lies DP, 2005, APPL ENVIRON MICROB, V71, P4414, DOI 10.1128/AEM.71.8.4414-4426.2005; Liu H, 2005, ENVIRON SCI TECHNOL, V39, P658, DOI 10.1021/es048927c; Logan B, 2005, WATER ENVIRON RES, V77, P211, DOI 10.1002/j.1554-7531.2005.tb00288.x; Logan BE, 2005, WATER SCI TECHNOL, V52, P31; Logan BE, 2006, ENVIRON SCI TECHNOL, V40, P5181, DOI 10.1021/es0605016; Lovley D. R., 2006, CURR OPIN BIOTECH, V17, P1; Lovley DR, 2006, NAT REV MICROBIOL, V4, P497, DOI 10.1038/nrmicro1442; LUCKNER M, 1990, SECONDARY METABOLISM; MADIGAN M, 1999, BROCK BIOL MICROORGA; Newman DK, 2000, NATURE, V405, P94, DOI 10.1038/35011098; Newman DK, 2001, SCIENCE, V292, P1312, DOI 10.1126/science.1060572; Niessen J, 2004, ELECTROCHEM COMMUN, V6, P955, DOI 10.1016/j.elecom.2004.07.010; Niessen J, 2005, LETT APPL MICROBIOL, V41, P286, DOI 10.1111/j.1472-765X.2005.01742.x; Niessen J, 2004, ELECTROCHEM COMMUN, V6, P571, DOI 10.1016/j.elecom.2004.04.006; Park DH, 1999, J BACTERIOL, V181, P2403; Park DH, 2000, APPL ENVIRON MICROB, V66, P1292, DOI 10.1128/AEM.66.4.1292-1297.2000; Park HS, 2001, ANAEROBE, V7, P297, DOI 10.1006/anae.2001.0399; Pham CA, 2003, FEMS MICROBIOL LETT, V223, P129, DOI 10.1016/S0378-1097(03)00354-9; Potter MC, 1911, P R SOC LOND B-CONTA, V84, P260, DOI 10.1098/rspb.1911.0073; Rabaey K, 2005, TRENDS BIOTECHNOL, V23, P291, DOI 10.1016/j.tibtech.2005.04.008; Rabaey K, 2005, ENVIRON SCI TECHNOL, V39, P3401, DOI 10.1021/es048563o; Rabaey K, 2004, APPL ENVIRON MICROB, V70, P5373, DOI 10.1128/AEM.70.9.5373-5382.2004; RABAEY K, 2006, BIOFUELS FUEL CELLS; Rabaey K, 2007, ISME J, V1, P9, DOI 10.1038/ismej.2007.4; Rabaey K, 2006, ENVIRON SCI TECHNOL, V40, P5218, DOI 10.1021/es060382u; Reguera G, 2005, NATURE, V435, P1098, DOI 10.1038/nature03661; Reguera G, 2006, APPL ENVIRON MICROB, V72, P7345, DOI 10.1128/AEM.01444-06; Reimers CE, 2001, ENVIRON SCI TECHNOL, V35, P192, DOI 10.1021/es001223s; ROLLER SD, 1984, J CHEM TECH BIOT B, V34, P3; Rosenbaum M, 2005, ENVIRON SCI TECHNOL, V39, P6328, DOI 10.1021/es0505447; Rosenbaum M, 2005, APPL MICROBIOL BIOT, V68, P753, DOI 10.1007/s00253-005-1915-4; Rosenbaum M, 2007, APPL CATAL B-ENVIRON, V74, P261, DOI 10.1016/j.apcatb.2007.02.013; Rosenbaum M, 2006, ANGEW CHEM INT EDIT, V45, P6658, DOI 10.1002/anie.200602021; Rosenbaum M, 2006, J SOLID STATE ELECTR, V10, P872, DOI 10.1007/s10008-006-0167-2; Schroder U., 2003, ANGEW CHEM, V115, P2986; SELL D, 1999, BIOTECHNOLOGY, V10, P11; STIRLING JL, 1983, BIOCHEM SOC T, V11, P451, DOI 10.1042/bst0110451; SUZUKI S, 1983, ANN NY ACAD SCI, V413, P133, DOI 10.1111/j.1749-6632.1983.tb47884.x; THAUER RK, 1977, BACTERIOL REV, V41, P100; Wilkinson S, 2000, AUTON ROBOT, V9, P99, DOI 10.1023/A:1008984516499; WINGARD LB, 1982, ENZYME MICROB TECH, V4, P137, DOI 10.1016/0141-0229(82)90104-1; Zhao F, 2006, ENVIRON SCI TECHNOL, V40, P5193, DOI 10.1021/es060332p | AG37: 76 | AH37: 475 | AI37: 490 | AJ37: 15 | AK37: 264 | AL37: ROYAL SOC CHEMISTRY | AM37: CAMBRIDGE | AN37: THOMAS GRAHAM HOUSE, SCIENCE PARK, MILTON RD, CAMBRIDGE CB4 0WF, CAMBS, ENGLAND | AO37: 1463-9076 | AP37: 1463-9084 | AR37: PHYS CHEM CHEM PHYS | AS37: Phys. Chem. Chem. Phys. | AT37: 39234 | AU37: 2007 | AV37: 9 | AW37: 21 | BB37: 2619 | BC37: 2629 | BE37: 10.1039/b703627m | BI37: 11 | BJ37: Chemistry, Physical; Physics, Atomic, Molecular & Chemical | BK37: Chemistry; Physics | BL37: 179TW | BM37: WOS:000247314000010 | BN37: 17627307 | BR37: 43703
A38: 37 | B38: 10.1016/j.biotechadv.2007.05.004 | C38: J | D38: Du, ZW; Li, HR; Gu, TY | H38: Du, Zhuwei; Li, Haoran; Gu, Tingyue | K38: A state of the art review on microbial fuel cells: A promising technology for wastewater treatment and bioenergy | L38: BIOTECHNOLOGY ADVANCES | O38: English | P38: Review | V38: microbial fuel cells; wastewater treatment; electricity generation; biohydrogen; biosensor | W38: CONTINUOUS ELECTRICITY-GENERATION; METAL-REDUCING BACTERIUM; PROTON-EXCHANGE MEMBRANE; OXYGEN-DEMAND SENSOR; MEDIATOR-LESS; ELECTRON-TRANSFER; BIOFUEL CELLS; FE(III)-REDUCING BACTERIUM; SHEWANELLA-PUTREFACIENS; POWER-GENERATION | X38: A microbial fuel cell (MFC) is a bioreactor that converts chemical energy in the chemical bonds in organic compounds to electrical energy through catalytic reactions of microorganisms under anaerobic conditions. It has been known for many years that it is possible to generate electricity directly by using bacteria to break down organic substrates. The recent energy crisis has reinvigorated interests in MFCs among academic researchers as a way to generate electric power or hydrogen from biomass without a net carbon emission into the ecosystem. MFCs can also be used in wastewater treatment facilities to break down organic matters. They have also been studied for applications as biosensors such as sensors for biological oxygen demand monitoring. Power output and Coulombic efficiency are significantly affected by the types of microbe in the anodic chamber of an MFC, configuration of the MFC and operating conditions. Currently, real-world applications of MFCs are limited because of their low power density level of several thousand mW/m(2). Efforts are being made to improve the performance and reduce the construction and operating costs of MFCs. This article presents a critical review on the recent advances in MFC research with emphases on MFC configurations and performances. (C) 2007 Elsevier Inc. All rights reserved. | Z38: Gu, TY (reprint author), Ohio Univ, Dept Chem & Biomol Engn, Athens, OH 45701 USA. | AA38: gu@ohio.edu | AB38: Kalia, Yogeshvar/M-4745-2019 | AC38: Kalia, Yogeshvar/0000-0001-9049-5489 | AF38: Aelterman P, 2006, ENVIRON SCI TECHNOL, V40, P3388, DOI 10.1021/es0525511; ALLEN RM, 1993, APPL BIOCHEM BIOTECH, V39, P27, DOI 10.1007/BF02918975; Angenent LT, 2004, TRENDS BIOTECHNOL, V22, P477, DOI 10.1016/j.tibtech.2004.07.001; Appleby AJ, 1989, FUEL CELL HDB; Back JH, 2004, FEMS MICROBIOL LETT, V238, P65, DOI 10.1111/j.1574-6968.2004.tb09738.x; BENNETTO H P, 1984, Life Chemistry Reports, V2, P363; Bergel A, 2005, ELECTROCHEM COMMUN, V7, P900, DOI 10.1016/j.elecom.2005.06.006; Bond DR, 2002, SCIENCE, V295, P483, DOI 10.1126/science.1066771; Bond DR, 2003, APPL ENVIRON MICROB, V69, P1548, DOI 10.1128/AEM.69.3.1548-1555.2003; Bullen RA, 2006, BIOSENS BIOELECTRON, V21, P2015, DOI 10.1016/j.bios.2006.01.030; Chan HM, 2001, INT J MOD PHYS A, V16, P163, DOI 10.1142/S0217751X0100298X; Chang IS, 2005, BIOSENS BIOELECTRON, V20, P1856, DOI 10.1016/j.bios.2004.06.003; Chang IS, 2004, BIOSENS BIOELECTRON, V19, P607, DOI 10.1016/S0956-5663(03)00272-0; Chaudhuri SK, 2003, NAT BIOTECHNOL, V21, P1229, DOI 10.1038/nbt867; Cheng S, 2006, ENVIRON SCI TECHNOL, V40, P364, DOI 10.1021/es0512071; Cheng S, 2006, ENVIRON SCI TECHNOL, V40, P2426, DOI 10.1021/es051652w; Cheng S, 2006, ELECTROCHEM COMMUN, V8, P489, DOI 10.1016/j.elecom.2006.01.010; CHIA M, 2002, MINIATURIZED MICROBI, P59; Choi Y, 2003, BIOELECTROCHEMISTRY, V59, P121, DOI 10.1016/S1567-5394(03)00018-5; Davis F, 2007, BIOSENS BIOELECTRON, V22, P1224, DOI 10.1016/j.bios.2006.04.029; DELANEY GM, 1984, J CHEM TECH BIOT B, V34, P13; DeLong EF, 2002, NAT BIOTECHNOL, V20, P788, DOI 10.1038/nbt0802-788; Gil GC, 2003, BIOSENS BIOELECTRON, V18, P327, DOI 10.1016/S0956-5663(02)00110-0; Gregory KB, 2004, ENVIRON MICROBIOL, V6, P596, DOI 10.1111/j.1462-2920.2004.00593.x; Grzebyk M, 2005, SEP PURIF TECHNOL, V41, P321, DOI 10.1016/j.seppur.2004.04.009; HABERMANN W, 1991, APPL MICROBIOL BIOT, V35, P128; He Z, 2005, ENVIRON SCI TECHNOL, V39, P5262, DOI 10.1021/es0502876; He Z, 2006, ENVIRON SCI TECHNOL, V40, P5212, DOI 10.1021/es060394f; Hernandez ME, 2001, CELL MOL LIFE SCI, V58, P1562, DOI 10.1007/PL00000796; Holmes DE, 2004, MICROB ECOL, V48, P178, DOI 10.1007/s00248-003-0004-4; Holzman DC, 2005, ENVIRON HEALTH PERSP, V113, pA754, DOI 10.1289/ehp.113-a754; Ieropoulos I, 2003, LECT NOTES ARTIF INT, V2801, P792; Ieropoulos I., 2003, P I INT S IM AN ART, P191; Jang JK, 2004, PROCESS BIOCHEM, V39, P1007, DOI 10.1016/S0032-9592(03)00203-6; Kang KH, 2003, BIOTECHNOL LETT, V25, P1357, DOI 10.1023/A:1024984521699; Kim BH, 2004, APPL MICROBIOL BIOT, V63, P672, DOI 10.1007/s00253-003-1412-6; Kim BH, 2003, BIOTECHNOL LETT, V25, P541, DOI 10.1023/A:1022891231369; Kim BH, 1999, J MICROBIOL BIOTECHN, V9, P127; Kim HJ, 1999, J MICROBIOL BIOTECHN, V9, P365; Kim HJ, 2002, ENZYME MICROB TECH, V30, P145, DOI 10.1016/S0141-0229(01)00478-1; Kim JR, 2005, APPL MICROBIOL BIOT, V68, P23, DOI 10.1007/s00253-004-1845-6; Lee SA, 2002, BIOELECTROCHEMISTRY, V57, P173, DOI 10.1016/S1567-5394(02)00115-9; LEROPOULOS I, 2005, ADV ROBOT SYST, V2, P295; LEROPOULOS I, 2005, J POWER SOURCES, V145, P253; LEROPOULOS I, 2004, INTELLIGENT AUTONOMO, V8, P128; Leropoulos IA, 2005, ENZYME MICROB TECH, V37, P238; Liu H, 2005, ENVIRON SCI TECHNOL, V39, P4317, DOI 10.1021/es050244p; Liu H, 2005, ENVIRON SCI TECHNOL, V39, P658, DOI 10.1021/es048927c; Liu H, 2004, ENVIRON SCI TECHNOL, V38, P4040, DOI 10.1021/es0499344; Liu H, 2005, ENVIRON SCI TECHNOL, V39, P5488, DOI 10.1021/es050316c; LIU H, 2004, ENV CELL TECHNOL, V28, P2281; LIU ZD, 2006, CHIN J BIOTECH, V21, P131; Logan BE, 2005, WATER RES, V39, P942, DOI 10.1016/j.watres.2004.11.019; Logan BE, 2006, ENVIRON SCI TECHNOL, V40, P5181, DOI 10.1021/es0605016; LOVELY DR, 2006, CURR OPIN BIOTECH, V17, P327; LOVLEY DR, 1993, ANNU REV MICROBIOL, V47, P263, DOI 10.1146/annurev.mi.47.100193.001403; Lovley DR, 1996, NATURE, V382, P445, DOI 10.1038/382445a0; Lovley DR, 2004, ADV MICROB PHYSIOL, V49, P219, DOI 10.1016/S0065-2911(04)49005-5; Lowy DA, 2006, BIOSENS BIOELECTRON, V21, P2058, DOI 10.1016/j.bios.2006.01.033; Lusk P., 1998, NRELSR58025145; Madigan MT, 2000, BROCK BIOL MICROORGA; Melhuish C, 2006, AUTON ROBOT, V21, P187, DOI 10.1007/s10514-006-6574-5; Menicucci J, 2006, ENVIRON SCI TECHNOL, V40, P1062, DOI 10.1021/es051180l; Min B, 2005, WATER RES, V39, P4961, DOI 10.1016/j.watres.2005.09.039; Min B, 2004, ENVIRON SCI TECHNOL, V38, P5809, DOI 10.1021/es0491026; Min BK, 2005, WATER RES, V39, P1675, DOI 10.1016/j.watres.2005.02.002; Moon H, 2006, BIORESOURCE TECHNOL, V97, P621, DOI 10.1016/j.biortech.2005.03.027; Moon H, 2005, BIOCHEM ENG J, V27, P59, DOI 10.1016/j.bej.2005.02.010; Moon H, 2004, BIOTECHNOL LETT, V26, P1717, DOI 10.1007/s10529-004-3743-5; Nevin KP, 2000, APPL ENVIRON MICROB, V66, P2248, DOI 10.1128/AEM.66.5.2248-2251.2000; Niessen J, 2004, ELECTROCHEM COMMUN, V6, P955, DOI 10.1016/j.elecom.2004.07.010; Niessen J, 2004, ELECTROCHEM COMMUN, V6, P571, DOI 10.1016/j.elecom.2004.04.006; Niessen J, 2006, ELECTROCHEM COMMUN, V8, P869, DOI 10.1016/j.elecom.2006.03.025; Oh S, 2004, ENVIRON SCI TECHNOL, V38, P4900, DOI 10.1021/es049422p; Oh SE, 2006, APPL MICROBIOL BIOT, V70, P162, DOI 10.1007/s00253-005-0066-y; Oh SE, 2005, WATER RES, V39, P4673, DOI 10.1016/j.watres.2005.09.019; Park DH, 2003, BIOTECHNOL BIOENG, V81, P348, DOI 10.1002/bit.10501; Park DH, 1997, BIOTECHNOL TECH, V11, P145, DOI 10.1023/A:1018441127733; Park DH, 1999, J BACTERIOL, V181, P2403; Park DH, 1999, APPL ENVIRON MICROB, V65, P2912; Park DH, 2000, APPL ENVIRON MICROB, V66, P1292, DOI 10.1128/AEM.66.4.1292-1297.2000; Park DH, 2002, APPL MICROBIOL BIOT, V59, P58, DOI 10.1007/s00253-002-0972-1; Park HS, 2001, ANAEROBE, V7, P297, DOI 10.1006/anae.2001.0399; Pham CA, 2003, FEMS MICROBIOL LETT, V223, P129, DOI 10.1016/S0378-1097(03)00354-9; Pham TH, 2006, ENG LIFE SCI, V6, P285, DOI 10.1002/elsc.200620121; Pham TH, 2004, J MICROBIOL BIOTECHN, V14, P324; Potter MC, 1911, P R SOC LOND B-CONTA, V84, P260, DOI 10.1098/rspb.1911.0073; Prasad D, 2006, J POWER SOURCES, V160, P991, DOI 10.1016/j.jpowsour.2006.02.051; Rabaey K, 2005, TRENDS BIOTECHNOL, V23, P291, DOI 10.1016/j.tibtech.2005.04.008; Rabaey K, 2005, ENVIRON SCI TECHNOL, V39, P3401, DOI 10.1021/es048563o; Rabaey K, 2003, BIOTECHNOL LETT, V25, P1531, DOI 10.1023/A:1025484009367; Rabaey K, 2004, APPL ENVIRON MICROB, V70, P5373, DOI 10.1128/AEM.70.9.5373-5382.2004; Rabaey K, 2005, ENVIRON SCI TECHNOL, V39, P8077, DOI 10.1021/es050986i; Rabaey K, 2006, ENVIRON SCI TECHNOL, V40, P5218, DOI 10.1021/es060382u; Rhoads A, 2005, ENVIRON SCI TECHNOL, V39, P4666, DOI 10.1021/es048386r; Ringeisen BR, 2006, ENVIRON SCI TECHNOL, V40, P2629, DOI 10.1021/es052254w; Rosenbaum M, 2006, J SOLID STATE ELECTR, V10, P872, DOI 10.1007/s10008-006-0167-2; Rozendal RA, 2006, ENVIRON SCI TECHNOL, V40, P5206, DOI 10.1021/es060387r; Scholz F, 2003, NAT BIOTECHNOL, V21, P1151, DOI 10.1038/nbt1003-1151; Schroder U, 2003, ANGEW CHEM INT EDIT, V42, P2880, DOI 10.1002/anie.200350918; Shantaram A, 2005, ENVIRON SCI TECHNOL, V39, P5037, DOI 10.1021/es0480668; STIRLING JL, 1983, BIOCHEM SOC T, V11, P451, DOI 10.1042/bst0110451; Straub KL, 2001, FEMS MICROBIOL ECOL, V34, P181, DOI 10.1111/j.1574-6941.2001.tb00768.x; Suzuki S., 1978, BIOTECHNOL BIOENG S, V8, P501; Tartakovsky B, 2006, BIOTECHNOL PROGR, V22, P241, DOI 10.1021/bp050225j; Tender LM, 2002, NAT BIOTECHNOL, V20, P821, DOI 10.1038/nbt716; THURSTON CF, 1985, J GEN MICROBIOL, V131, P1393; Tokuji I., 2003, BIOCHIM BIOPHYS ACTA, V1647, P121; Vargas M, 1998, NATURE, V395, P65; VEGA CA, 1987, BIOELECTROCH BIOENER, V17, P217, DOI 10.1016/0302-4598(87)80026-0; Wilkinson S, 2000, AUTON ROBOT, V9, P99, DOI 10.1023/A:1008984516499; Zhang ER, 2006, J POWER SOURCES, V161, P820, DOI 10.1016/j.jpowsour.2006.05.004; Zhao F, 2005, ELECTROCHEM COMMUN, V7, P1405, DOI 10.1016/j.elecom.2005.09.032; ZHAO F, 2006, ENVIRON SCI TECHNOL, P5193; Zuo Y, 2006, ENERG FUEL, V20, P1716, DOI 10.1021/ef060033l | AG38: 115 | AH38: 755 | AI38: 799 | AJ38: 46 | AK38: 788 | AL38: PERGAMON-ELSEVIER SCIENCE LTD | AM38: OXFORD | AN38: THE BOULEVARD, LANGFORD LANE, KIDLINGTON, OXFORD OX5 1GB, ENGLAND | AO38: 0734-9750 | AR38: BIOTECHNOL ADV | AS38: Biotechnol. Adv. | AT38: SEP-OCT | AU38: 2007 | AV38: 25 | AW38: 5 | BB38: 464 | BC38: 482 | BE38: 10.1016/j.biotechadv.2007.05.004 | BI38: 19 | BJ38: Biotechnology & Applied Microbiology | BK38: Biotechnology & Applied Microbiology | BL38: 198WR | BM38: WOS:000248658700004 | BN38: 17582720 | BR38: 43703
A39: 38 | B39: 10.1016/j.jpowsour.2007.07.010 | C39: J | D39: HaoYu, E; Cheng, S; Scott, K; Logan, B | H39: HaoYu, Eileen; Cheng, Shaoan; Scott, Keith; Logan, Bruce | K39: Microbial fuel cell performance with non-Pt cathode catalysts | L39: JOURNAL OF POWER SOURCES | O39: English | P39: Article | V39: microbial fuel cells; oxygen reduction; transition metal macrocycles; iron phthalocyanine; power output | W39: WASTE-WATER TREATMENT; OXYGEN REDUCTION; ELECTRICITY-GENERATION; POWER-GENERATION; MEDIATOR-LESS; METHANOL; ELECTROCATALYST; MEMBRANE; ANODE; PHTHALOCYANINE | X39: Various cathode catalysts prepared from metal porphyrines and phthalocyanines were examined for their oxygen reduction activity in neutral pH media. Electrochemical studies were carried out with metal tetramethoxyphenylporphyrin (TMPP), CoTMPP and FeCoTMPP, and metal phthalocyanine (Pc), FePc, CoPc and FeCuPc, supported on Ketjenblack (KJB) carbon. Iron phthalocyanine supported on KJB (FePc-KJB) carbon demonstrated higher activity towards oxygen reduction than Pt in neutral media. The effect of carbon substrate was investigated by evaluating FePc on Vulcan XC carbon (FcPcVC) versus Ketjenblack carbon. FePc-KJB showed higher activity than FePcVC suggesting the catalyst activity could be improved by using carbon substrate with a higher surface area. With FePc-KJB as the MFC cathode catalyst, a power density of 634 mW m(-2) was achieved in 50 mM phosphate buffer medium at pH 7, which was higher than that obtained using the precious-metal Pt cathode (593 mW m(-2)). Under optimum operating conditions (i.e. using a high surface area carbon brush anode and 200 mM PBM as the supporting electrolyte with 1 g L-1 acetate as the substrate), the power density was increased to 2011 mW m(-2). This high power output indicates that MFCs with low cost metal macrocycles catalysts is promising in further practical applications. (C) 2007 Elsevier B.V. All rights reserved. | Y39: Univ Newcastle Upon Tyne, Sch Chem Engn & Adv Mat, Newcastle Upon Tyne NE1 7RU, Tyne & Wear, England; Penn State Univ, Penn State Hydrogen Energy H2E Ctr, Dept Civil & Environm Engn, University Pk, PA 16802 USA | Z39: HaoYu, E (reprint author), Univ Newcastle Upon Tyne, Sch Chem Engn & Adv Mat, Newcastle Upon Tyne NE1 7RU, Tyne & Wear, England. | AA39: eileen.yu@ncl.ac.uk | AB39: Yu, Eileen H/E-6567-2011 | AC39: Yu, Eileen H/0000-0002-6872-975X | AD39: Engineering and Physical Sciences Research Council [EP/C535456/1] | AF39: Alferov SV, 2006, RUSS J ELECTROCHEM+, V42, P403, DOI 10.1134/S1023193506040185; ALLEN RM, 1993, APPL BIOCHEM BIOTECH, V39, P27, DOI 10.1007/BF02918975; Bouwkamp-Wijnoltz AL, 1999, ELECTROCHIM ACTA, V45, P379, DOI 10.1016/S0013-4686(99)00281-9; Chaudhuri SK, 2003, NAT BIOTECHNOL, V21, P1229, DOI 10.1038/nbt867; Cheng S, 2006, ENVIRON SCI TECHNOL, V40, P364, DOI 10.1021/es0512071; Cheng S, 2006, ENVIRON SCI TECHNOL, V40, P2426, DOI 10.1021/es051652w; Cheng S, 2006, ELECTROCHEM COMMUN, V8, P489, DOI 10.1016/j.elecom.2006.01.010; Cheng SA, 2007, ELECTROCHEM COMMUN, V9, P492, DOI 10.1016/j.elecom.2006.10.023; Cohen B., 1931, J BACTERIOL, V21, P18; Finkelstein DA, 2006, ENVIRON SCI TECHNOL, V40, P6990, DOI 10.1021/es061146m; Furukawa K, 2005, INT J ENERG RES, V29, P1073, DOI 10.1002/er.1140; Gil GC, 2003, BIOSENS BIOELECTRON, V18, P327, DOI 10.1016/S0956-5663(02)00110-0; Gojkovic SL, 1998, J ELECTROCHEM SOC, V145, P3493, DOI 10.1149/1.1838833; GUPTA S, 1991, J ELECTROANAL CHEM, V306, P239, DOI 10.1016/0022-0728(91)85233-F; Jang JK, 2004, PROCESS BIOCHEM, V39, P1007, DOI 10.1016/S0032-9592(03)00203-6; Jiang RZ, 2000, J ELECTROCHEM SOC, V147, P4605, DOI 10.1149/1.1394109; LADOUCEUR M, 1993, J ELECTROCHEM SOC, V140, P1974, DOI 10.1149/1.2220748; Lefevre M, 2000, J PHYS CHEM B, V104, P11238, DOI 10.1021/jp002444n; Lefevre M, 2002, J PHYS CHEM B, V106, P8705, DOI 10.1021/jp020267f; Liu H, 2004, ABSTR PAP AM CHEM S, V228, pU622; Liu H, 2004, ENVIRON SCI TECHNOL, V38, P2281, DOI 10.1021/es034923g; Liu JL, 2007, J APPL MICROBIOL, V102, P177, DOI 10.1111/j.1365-2672.2006.03051.x; Logan B, 2005, WATER ENVIRON RES, V77, P211, DOI 10.1002/j.1554-7531.2005.tb00288.x; Logan BE, 2005, WATER SCI TECHNOL, V52, P31; Logan BE, 2004, ENVIRON SCI TECHNOL, V38, p160A, DOI 10.1021/es040468s; Logan B, 2007, ENVIRON SCI TECHNOL, V41, P3341, DOI 10.1021/es062644y; MOUAHID OE, 1997, J ELECTROANAL CHEM, V426, P117; Pham TH, 2004, J MICROBIOL BIOTECHN, V14, P324; Potter MC, 1911, P R SOC LOND B-CONTA, V84, P260, DOI 10.1098/rspb.1911.0073; Rabaey K, 2005, ENVIRON SCI TECHNOL, V39, P8077, DOI 10.1021/es050986i; Rabaey K, 2005, WATER SCI TECHNOL, V52, P515; Scott K, 2004, J POWER SOURCES, V126, P67, DOI 10.1016/j.jpowsour.2003.09.041; Sun GQ, 1998, J APPL ELECTROCHEM, V28, P1087, DOI 10.1023/A:1003413226041; TANAKA AA, 1989, MATER CHEM PHYS, V22, P431, DOI 10.1016/0254-0584(89)90009-6; WIESENER K, 1989, MATER CHEM PHYS, V22, P457, DOI 10.1016/0254-0584(89)90010-2; Zhao F, 2005, ELECTROCHEM COMMUN, V7, P1405, DOI 10.1016/j.elecom.2005.09.032; Zhao F, 2006, ENVIRON SCI TECHNOL, V40, P5193, DOI 10.1021/es060332p | AG39: 37 | AH39: 197 | AI39: 210 | AJ39: 5 | AK39: 92 | AL39: ELSEVIER SCIENCE BV | AM39: AMSTERDAM | AN39: PO BOX 211, 1000 AE AMSTERDAM, NETHERLANDS | AO39: 0378-7753 | AR39: J POWER SOURCES | AS39: J. Power Sources | AT39: 46631 | AU39: 2007 | AV39: 171 | AW39: 2 | BB39: 275 | BC39: 281 | BE39: 10.1016/j.jpowsour.2007.07.010 | BI39: 7 | BJ39: Chemistry, Physical; Electrochemistry; Energy & Fuels; Materials Science, Multidisciplinary | BK39: Chemistry; Electrochemistry; Energy & Fuels; Materials Science | BL39: 219EG | BM39: WOS:000250066900004 | BR39: 43703
A40: 39 | B40: 10.1007/s00253-007-1162-y | C40: J | D40: Jung, S; Regan, JM | H40: Jung, Sokhee; Regan, John M. | K40: Comparison of anode bacterial communities and performance in microbial fuel cells with different electron donors | L40: APPLIED MICROBIOLOGY AND BIOTECHNOLOGY | O40: English | P40: Article | W40: ANAEROBIC SLUDGE DIGESTER; ELECTRICITY-GENERATION; GEOBACTER-SULFURREDUCENS; FE(III)-REDUCING BACTERIUM; FE(III) REDUCTION; SP-NOV; ORGANIC-COMPOUNDS; MICROORGANISMS; ENRICHMENT; DIVERSITY | X40: Microbial fuel cells (MFCs) harness the electrochemical activity of certain microbes for the production of electricity from reduced compounds. Characterizations of MFC anode biofilms have collectively shown very diverse microbial communities, raising ecological questions about competition and community succession within these anode-reducing communities. Three sets of triplicate, two-chamber MFCs inoculated with anaerobic sludge and differing in energy sources (acetate, lactate, and glucose) were operated to explore these questions. Based on 16S rDNA-targeted denaturing gradient gel electrophoresis (DGGE), all anode communities contained sequences closely affiliated with Geobacter sulfurreducens (> 99% similarity) and an uncultured bacterium clone in the Bacteroidetes class (99% similarity). Various other Geobacter-like sequences were also enriched in most of the anode biofilms. While the anode communities in replicate reactors for each substrate generally converged to a reproducible community, there were some variations in the relative distribution of these putative anode-reducing Geobacter-like strains. Firmicutes were found only in glucose-fed MFCs, presumably serving the roles of converting complex carbon into simple molecules and scavenging oxygen. The maximum current density in these systems was negatively correlated with internal resistance variations among replicate reactors and, likely, was only minimally affected by anode community differences in these two-chamber MFCs with high internal resistance. | Y40: Penn State Univ, Dept Civil & Environm Engn, University Pk, PA 16802 USA | Z40: Regan, JM (reprint author), Penn State Univ, Dept Civil & Environm Engn, University Pk, PA 16802 USA. | AA40: jregan@engr.psu.edu | AB40: Jung, Sokhee P/A-5109-2012 | AC40: Jung, Sokhee P/0000-0002-3566-5649 | AF40: Aelterman P, 2006, WATER SCI TECHNOL, V54, P9, DOI 10.2166/wst.2006.702; Aelterman P, 2006, ENVIRON SCI TECHNOL, V40, P3388, DOI 10.1021/es0525511; Ariesyady HD, 2007, WATER RES, V41, P1554, DOI 10.1016/j.watres.2006.12.036; Bond DR, 2002, SCIENCE, V295, P483, DOI 10.1126/science.1066771; Bond DR, 2003, APPL ENVIRON MICROB, V69, P1548, DOI 10.1128/AEM.69.3.1548-1555.2003; Butler JE, 2004, J BACTERIOL, V186, P4042, DOI 10.1128/JB.186.12.4042-4045.2004; CACCAVO F, 1994, APPL ENVIRON MICROB, V60, P3752; Chaudhuri SK, 2003, NAT BIOTECHNOL, V21, P1229, DOI 10.1038/nbt867; Cheng S, 2006, ENVIRON SCI TECHNOL, V40, P2426, DOI 10.1021/es051652w; Choo YF, 2006, J MICROBIOL BIOTECHN, V16, P1481; Chouari R, 2005, APPL ENVIRON MICROB, V71, P2145, DOI 10.1128/AEM.71.4.2145-2153.2005; Crocetti GR, 2000, APPL ENVIRON MICROB, V66, P1175, DOI 10.1128/AEM.66.3.1175-1182.2000; DON RH, 1991, NUCLEIC ACIDS RES, V19, P14; Gorby YA, 2006, P NATL ACAD SCI USA, V103, P11358, DOI 10.1073/pnas.0604517103; Gottschalk G., 1986, BACTERIAL METABOLISM; Holmes DE, 2004, MICROB ECOL, V48, P178, DOI 10.1007/s00248-003-0004-4; Jong BC, 2006, ENVIRON SCI TECHNOL, V40, P6449, DOI 10.1021/es0613512; Kim BH, 2004, APPL MICROBIOL BIOT, V63, P672, DOI 10.1007/s00253-003-1412-6; Kim BH, 1999, J MICROBIOL BIOTECHN, V9, P127; Kim GT, 2006, J APPL MICROBIOL, V101, P698, DOI 10.1111/j.1365-2672.2006.02923.x; Kim GT, 2005, J APPL MICROBIOL, V99, P978, DOI 10.1111/j.1365-2672.2004.02514.x; Kim HJ, 2002, ENZYME MICROB TECH, V30, P145, DOI 10.1016/S0141-0229(01)00478-1; Kim JR, 2005, APPL MICROBIOL BIOT, V68, P23, DOI 10.1007/s00253-004-1845-6; Kim JR, 2007, BIORESOURCE TECHNOL, V98, P2568, DOI 10.1016/j.biortech.2006.09.036; Leang C, 2003, J BACTERIOL, V185, P2096, DOI 10.1128/JB.185.7.2096-2103.2003; Lee JY, 2003, FEMS MICROBIOL LETT, V223, P185, DOI 10.1016/S0378-1097(03)00356-2; Liu H, 2005, ENVIRON SCI TECHNOL, V39, P658, DOI 10.1021/es048927c; Liu H, 2004, ENVIRON SCI TECHNOL, V38, P4040, DOI 10.1021/es0499344; Liu JL, 2007, J APPL MICROBIOL, V102, P177, DOI 10.1111/j.1365-2672.2006.03051.x; Logan BE, 2005, WATER RES, V39, P942, DOI 10.1016/j.watres.2004.11.019; Logan BE, 2006, TRENDS MICROBIOL, V14, P512, DOI 10.1016/j.tim.2006.10.003; LOVLEY DR, 1988, APPL ENVIRON MICROB, V54, P1472; LOVLEY DR, 1993, ARCH MICROBIOL, V159, P336, DOI 10.1007/BF00290916; Martin-Laurent F, 2001, APPL ENVIRON MICROB, V67, P2354, DOI 10.1128/AEM.67.5.2354-2359.2001; Milliken CE, 2007, APPL MICROBIOL BIOT, V73, P1180, DOI 10.1007/s00253-006-0564-6; Min BK, 2005, WATER RES, V39, P1675, DOI 10.1016/j.watres.2005.02.002; Muyzer G., 2004, Molecular microbial ecology manual. Volumes 1 and 2, P743; Muyzer G, 1999, CURR OPIN MICROBIOL, V2, P317, DOI 10.1016/S1369-5274(99)80055-1; Nevin KP, 2005, INT J SYST EVOL MICR, V55, P1667, DOI 10.1099/ijs.0.63417-0; Oh S, 2004, ENVIRON SCI TECHNOL, V38, P4900, DOI 10.1021/es049422p; OH SE, 2005, APPL MICROBIOL BIOT, V70, P1; Park HS, 2001, ANAEROBE, V7, P297, DOI 10.1006/anae.2001.0399; Pham CA, 2003, FEMS MICROBIOL LETT, V223, P129, DOI 10.1016/S0378-1097(03)00354-9; Phung NT, 2004, FEMS MICROBIOL LETT, V233, P77, DOI 10.1016/j.femsle.2004.01.041; Potter MC, 1911, P R SOC LOND B-CONTA, V84, P260, DOI 10.1098/rspb.1911.0073; Rabaey K, 2004, APPL ENVIRON MICROB, V70, P5373, DOI 10.1128/AEM.70.9.5373-5382.2004; Rabaey K, 2007, ISME J, V1, P9, DOI 10.1038/ismej.2007.4; Reguera G, 2005, NATURE, V435, P1098, DOI 10.1038/nature03661; Reimers CE, 2001, ENVIRON SCI TECHNOL, V35, P192, DOI 10.1021/es001223s; Ringeisen BR, 2006, ENVIRON SCI TECHNOL, V40, P2629, DOI 10.1021/es052254w; Schaum M, 2000, SOUTHERN LIT J, V33, P1, DOI 10.1353/slj.2000.0013; Tender LM, 2002, NAT BIOTECHNOL, V20, P821, DOI 10.1038/nbt716 | AG40: 52 | AH40: 228 | AI40: 237 | AJ40: 10 | AK40: 103 | AL40: SPRINGER | AM40: NEW YORK | AN40: 233 SPRING STREET, NEW YORK, NY 10013 USA | AO40: 0175-7598 | AR40: APPL MICROBIOL BIOT | AS40: Appl. Microbiol. Biotechnol. | AT40: NOV | AU40: 2007 | AV40: 77 | AW40: 2 | BB40: 393 | BC40: 402 | BE40: 10.1007/s00253-007-1162-y | BI40: 10 | BJ40: Biotechnology & Applied Microbiology | BK40: Biotechnology & Applied Microbiology | BL40: 224YI | BM40: WOS:000250483900017 | BN40: 17786426 | BR40: 43703
A41: 40 | C41: B | D41: Lovley, DR; Nevin, KP | F41: Wall, JD; Harwood, CS; Demain, A | H41: Lovley, Derek R.; Nevin, Kelly P. | K41: Electricity Production with Electricigens | L41: BIOENERGY | O41: English | P41: Article; Book Chapter | W41: INSOLUBLE FE(III) OXIDE; MICROBIAL FUEL-CELLS; ANAEROBIC BENZENE OXIDATION; SEDIMENT-WATER INTERFACE; METAL-REDUCING BACTERIUM; GEOBACTER-SULFURREDUCENS; ELECTRON-TRANSFER; DISSIMILATORY FE(III); SUBSURFACE ENVIRONMENTS; HARVESTING ELECTRICITY | Y41: [Lovley, Derek R.; Nevin, Kelly P.] Univ Massachusetts, Dept Microbiol, Amherst, MA 01003 USA | Z41: Lovley, DR (reprint author), Univ Massachusetts, Dept Microbiol, Amherst, MA 01003 USA. | AF41: Anderson RT, 1998, ENVIRON SCI TECHNOL, V32, P1222, DOI 10.1021/es9704949; BENNETTO HP, 1990, FRONTIERS SCI, P66; Bond DR, 2002, SCIENCE, V295, P483, DOI 10.1126/science.1066771; Bond DR, 2005, APPL ENVIRON MICROB, V71, P2186, DOI 10.1128/AEM.71.4.2186-2189.2005; Bond DR, 2003, APPL ENVIRON MICROB, V69, P1548, DOI 10.1128/AEM.69.3.1548-1555.2003; Butler JE, 2006, J BACTERIOL, V188, P450, DOI 10.1128/JB.188.2.450-455.2006; CACCAVO F, 1992, APPL ENVIRON MICROB, V58, P3211; Chaudhuri SK, 2003, NAT BIOTECHNOL, V21, P1229, DOI 10.1038/nbt867; Cheng S, 2006, ENVIRON SCI TECHNOL, V40, P2426, DOI 10.1021/es051652w; Childers SE, 2002, NATURE, V416, P767, DOI 10.1038/416767a; Coppi MV, 2001, APPL ENVIRON MICROB, V67, P3180, DOI 10.1128/AEM.67.7.3180-3187.2001; Ding YHR, 2006, BBA-PROTEINS PROTEOM, V1764, P1198, DOI 10.1016/j.bbapap.2006.04.017; Finneran KT, 2003, INT J SYST EVOL MICR, V53, P669, DOI 10.1099/ijs.0.02298-0; Gorby YA, 2006, P NATL ACAD SCI USA, V103, P11358, DOI 10.1073/pnas.0604517103; Gregory KB, 2005, ENVIRON SCI TECHNOL, V39, P8943, DOI 10.1021/es050457e; Gregory KB, 2004, ENVIRON MICROBIOL, V6, P596, DOI 10.1111/j.1462-2920.2004.00593.x; Holmes DE, 2006, ENVIRON MICROBIOL, V8, P1805, DOI 10.1111/j.1462-2920.2006.01065.x; Holmes DE, 2004, APPL ENVIRON MICROB, V70, P1234, DOI 10.1128/AEM.70.2.1234-1237.2004; Holmes DE, 2004, MICROB ECOL, V48, P178, DOI 10.1007/s00248-003-0004-4; Holmes DE, 2004, APPL ENVIRON MICROB, V70, P6023, DOI 10.1128/AEM.70.10.6023-6030.2004; Katz E., 2003, HDB FUEL CELLS FUNDA, V1, P355; Khare T, 2006, PROTEOMICS, V6, P632, DOI 10.1002/pmic.200500137; Kim HJ, 2002, ENZYME MICROB TECH, V30, P145, DOI 10.1016/S0141-0229(01)00478-1; Lanthier M, 2008, FEMS MICROBIOL LETT, V278, P29, DOI 10.1111/j.1574-6968.2007.00964.x; Leang C, 2003, J BACTERIOL, V185, P2096, DOI 10.1128/JB.185.7.2096-2103.2003; Lies DP, 2005, APPL ENVIRON MICROB, V71, P4414, DOI 10.1128/AEM.71.8.4414-4426.2005; Lin B, 2005, APPL ENVIRON MICROB, V71, P5983, DOI 10.1128/AEM.71.10.5983-5991.2005; Logan BE, 2005, WATER SCI TECHNOL, V52, P31; Logan B, 2007, ENVIRON SCI TECHNOL, V41, P3341, DOI 10.1021/es062644y; Lovley D, 2006, SCIENTIST, V20, P46; Lovley DR, 2006, NAT REV MICROBIOL, V4, P497, DOI 10.1038/nrmicro1442; LOVLEY DR, 1987, NATURE, V330, P252, DOI 10.1038/330252a0; LOVLEY DR, 1994, NATURE, V370, P128, DOI 10.1038/370128a0; LOVLEY DR, 1989, APPL ENVIRON MICROB, V55, P3234; LOVLEY DR, 1989, NATURE, V339, P297, DOI 10.1038/339297a0; Lovley DR, 1996, APPL ENVIRON MICROB, V62, P288; LOVLEY DR, 1991, MICROBIOL REV, V55, P259; LOVLEY DR, 1988, APPL ENVIRON MICROB, V54, P1472; Lovley DR, 1996, NATURE, V382, P445, DOI 10.1038/382445a0; Lovley DR, 2004, ADV MICROB PHYSIOL, V49, P219, DOI 10.1016/S0065-2911(04)49005-5; Lowy DA, 2006, BIOSENS BIOELECTRON, V21, P2058, DOI 10.1016/j.bios.2006.01.033; Mahadevan R, 2006, APPL ENVIRON MICROB, V72, P1558, DOI 10.1128/AEM.72.2.1558-1568.2006; Mehta T, 2005, APPL ENVIRON MICROB, V71, P8634, DOI 10.1128/AEM.71.12.8634-8641.2005; Mehta T, 2006, MICROBIOL-SGM, V152, P2257, DOI 10.1099/mic.0.28864-0; Methe BA, 2005, APPL ENVIRON MICROB, V71, P2530, DOI 10.1128/AEM.71.5.2530-2538.2005; Methe BA, 2003, SCIENCE, V302, P1967, DOI 10.1126/science.1088727; Nevin KP, 2000, APPL ENVIRON MICROB, V66, P2248, DOI 10.1128/AEM.66.5.2248-2251.2000; Nevin KP, 2002, APPL ENVIRON MICROB, V68, P2294, DOI 10.1128/AEM.68.5.2294-2299.2002; Nevin KP, 2002, GEOMICROBIOL J, V19, P141, DOI 10.1080/01490450252864253; Newman D. K., 2000, NATURE, V405, P93; Park DH, 1999, APPL ENVIRON MICROB, V65, P2912; POSTIER BL, 2007, J MICROBIOL METHODS; Potter MC, 1911, P R SOC LOND B-CONTA, V84, P260, DOI 10.1098/rspb.1911.0073; Potter MC, 1910, P U DURHAM PHIL SOC, V3, P245; Rabaey K, 2005, TRENDS BIOTECHNOL, V23, P291, DOI 10.1016/j.tibtech.2005.04.008; Reguera G, 2005, NATURE, V435, P1098, DOI 10.1038/nature03661; Reguera G, 2007, J BACTERIOL, V189, P2125, DOI 10.1128/JB.01284-06; Reguera G, 2006, APPL ENVIRON MICROB, V72, P7345, DOI 10.1128/AEM.01444-06; Reimers CE, 2001, ENVIRON SCI TECHNOL, V35, P192, DOI 10.1021/es001223s; Richter H, 2007, APPL ENVIRON MICROB, V73, P5347, DOI 10.1128/AEM.00804-07; Roling WFM, 2001, APPL ENVIRON MICROB, V67, P4619, DOI 10.1128/AEM.67.10.4619-4629.2001; Rooney-Varga JN, 1999, APPL ENVIRON MICROB, V65, P3056; Rosso KM, 2003, GEOCHIM COSMOCHIM AC, V67, P1081, DOI 10.1016/S0016-7037(02)00904-3; Rotello V. M., 2008, LANGMUIR; Shukla AK, 2004, CURR SCI INDIA, V87, P455; Tender LM, 2002, NAT BIOTECHNOL, V20, P821, DOI 10.1038/nbt716 | AG41: 66 | AH41: 22 | AI41: 24 | AJ41: 0 | AK41: 13 | AL41: AMER SOC MICROBIOLOGY | AM41: WASHINGTON | AN41: 1752 N STREET NW, WASHINGTON, DC 20036-2904 USA | AQ41: 978-1-55581-478-6 | AU41: 2008 | BB41: 295 | BC41: 306 | BI41: 12 | BJ41: Biotechnology & Applied Microbiology; Energy & Fuels; Microbiology | BK41: Biotechnology & Applied Microbiology; Energy & Fuels; Microbiology | BL41: BPH82 | BM41: WOS:000278888100024 | BR41: 43703
A42: 41 | B42: 10.1039/b708013c | C42: J | D42: Moehlenbrock, MJ; Minteer, SD | H42: Moehlenbrock, Michael J.; Minteer, Shelley D. | K42: Extended lifetime biofuel cells | L42: CHEMICAL SOCIETY REVIEWS | O42: English | P42: Review | W42: NICOTINAMIDE ADENINE-DINUCLEOTIDE; DIRECT ELECTRON-TRANSFER; SOL-GEL ELECTRODES; DEHYDROGENASE ENZYMES; FUEL-CELL; IMMOBILIZATION; BIOSENSORS; OPERATION; OXIDATION; MEMBRANES | X42: Over the last 40 years, researchers have been studying and improving enzymatic biofuel cells, but until the last five years, the technology was plagued by short active lifetimes (typically 8 hours to 7 days) that prohibited the commercial use of this technology. This tutorial review introduces the topic of enzymatic biofuel cells and discusses the recent work done to stabilize and immobilize enzymes at bioanodes and biocathodes of biofuel cells. This review covers a wide variety of fuel systems from sugar to alcohols and covers both direct electron transfer (DET) systems and mediated electron transfer (MET) systems. | Y42: [Moehlenbrock, Michael J.; Minteer, Shelley D.] St Louis Univ, Dept Chem, St Louis, MO 63103 USA | Z42: Minteer, SD (reprint author), St Louis Univ, Dept Chem, 3501 Laclede Ave, St Louis, MO 63103 USA. | AA42: minteers@slu.edu | AB42: Minteer, Shelley/A-7711-2009; Minteer, Shelley/C-4751-2014 | AC42: Minteer, Shelley/0000-0002-5788-2249 | AF42: Akers NL, 2005, ELECTROCHIM ACTA, V50, P2521, DOI 10.1016/j.electacta.2004.10.080; Arechederra R.L., 2007, PREPR S AM CHEM SOC, V52, P175; ARECHEDERRA RL, 2007, THESIS SAINT LOUIS U, P115; Arechederra RL, 2007, J POWER SOURCES, V173, P156, DOI 10.1016/j.jpowsour.2007.08.012; ASTON WJ, 1984, BIOTECHNOL GENET ENG, V1, P89, DOI 10.1080/02648725.1984.10647782; Barton SC, 2004, CHEM REV, V104, P4867, DOI 10.1021/cr020719k; BLAEDEL WJ, 1975, ANAL CHEM, V47, P1337, DOI 10.1021/ac60358a034; Bullen RA, 2006, BIOSENS BIOELECTRON, V21, P2015, DOI 10.1016/j.bios.2006.01.030; Calabrese-Barton S., 2004, CHEM REV, V104, P4867; Chaubey A, 2002, BIOSENS BIOELECTRON, V17, P441, DOI 10.1016/S0956-5663(01)00313-X; Chen T, 2001, J AM CHEM SOC, V123, P8630, DOI 10.1021/ja0163164; Davis F, 2007, BIOSENS BIOELECTRON, V22, P1224, DOI 10.1016/j.bios.2006.04.029; Fischback MB, 2006, ELECTROANAL, V18, P2016, DOI 10.1002/elan.200603626; Ghindilis AL, 1997, ELECTROANAL, V9, P661, DOI 10.1002/elan.1140090902; Heller A, 2004, PHYS CHEM CHEM PHYS, V6, P209, DOI 10.1039/b313149a; Katz E., 2003, HDB FUEL CELLS FUNDA, P1; Kerr J, 2006, POLYM MAT SCI ENG, V94, P594; Kerr J., 2005, POLYM PREPR, V46, P623; Kim J, 2003, NANO LETT, V3, P1219, DOI 10.1021/nl034404b; Kim J, 2006, BIOTECHNOL ADV, V24, P296, DOI 10.1016/j.biotechadv.2005.11.006; Kim J, 2006, CHEM ENG SCI, V61, P1017, DOI 10.1016/j.ces.2005.05.067; Kjeang E, 2006, J POWER SOURCES, V158, P1, DOI 10.1016/j.jpowsour.2005.07.092; Klotzbach T.L., 2007, POLYM PREPR, V48, P1008; Klotzbach T.L., 2006, POLYM MAT SCI ENG, V94, P599; Klotzbach T, 2006, J MEMBRANE SCI, V282, P276, DOI 10.1016/j.memsci.2006.05.029; Lim J, 2007, PHYS CHEM CHEM PHYS, V9, P1809, DOI 10.1039/b618422g; Lim J, 2007, J ELECTROCHEM SOC, V154, pA140, DOI 10.1149/1.2404904; Lim KG, 2007, BIOSENS BIOELECTRON, V22, P941, DOI 10.1016/j.bios.2006.04.019; Mano N, 2003, J AM CHEM SOC, V125, P15290, DOI 10.1021/ja038285d; Mano N, 2003, J ELECTROCHEM SOC, V150, pA1136, DOI 10.1149/1.1592519; Mano N, 2002, J AM CHEM SOC, V124, P6480, DOI 10.1021/ja025874v; Mano N, 2003, J AM CHEM SOC, V125, P6588, DOI 10.1021/ja0346328; Mano N, 2002, J AM CHEM SOC, V124, P12962, DOI 10.1021/ja028514g; Moore CM, 2005, LAB CHIP, V5, P218, DOI 10.1039/b412719f; Moore CM, 2004, BIOMACROMOLECULES, V5, P1241, DOI 10.1021/bm0345256; Palmore GTR, 1998, J ELECTROANAL CHEM, V443, P155, DOI 10.1016/S0022-0728(97)00393-8; Potter MC, 1911, P R SOC LOND B-CONTA, V84, P260, DOI 10.1098/rspb.1911.0073; Sahney R, 2006, ANAL CHIM ACTA, V578, P156, DOI 10.1016/j.aca.2006.06.063; Silverman R. B., 2000, ORGANIC CHEM ENZYME; Soukharev V, 2004, J AM CHEM SOC, V126, P8368, DOI 10.1021/ja0475510; TEODORESCU SG, 2006, 209 ECS M DENV CO 20; Thomas TJ, 2003, J MEMBRANE SCI, V213, P55, DOI 10.1016/S0376-7388(02)00512-4; Togo M, 2007, ELECTROCHIM ACTA, V52, P4669, DOI 10.1016/j.electacta.2007.01.067; Topcagic S, 2006, ELECTROCHIM ACTA, V51, P2168, DOI 10.1016/j.electacta.2005.03.090; Topcagic S, 2006, CHEM IND-SER, V112, P215; Treu B.L., 2005, POLYM MAT SCI ENG, V92, P192; TSONG TY, 1998, AM PHYS SOC; YAHIRO AT, 1964, BIOCHIM BIOPHYS ACTA, V88, P375, DOI 10.1016/0926-6577(64)90192-5; Yuhashi N, 2005, BIOSENS BIOELECTRON, V20, P2145, DOI 10.1016/j.bios.2004.08.017; Zeng K, 2000, ANAL CHEM, V72, P2211, DOI 10.1021/ac9911138 | AG42: 50 | AH42: 241 | AI42: 242 | AJ42: 1 | AK42: 74 | AL42: ROYAL SOC CHEMISTRY | AM42: CAMBRIDGE | AN42: THOMAS GRAHAM HOUSE, SCIENCE PARK, MILTON RD, CAMBRIDGE CB4 0WF, CAMBS, ENGLAND | AO42: 0306-0012 | AP42: 1460-4744 | AR42: CHEM SOC REV | AS42: Chem. Soc. Rev. | AU42: 2008 | AV42: 37 | AW42: 6 | BB42: 1188 | BC42: 1196 | BE42: 10.1039/b708013c | BI42: 9 | BJ42: Chemistry, Multidisciplinary | BK42: Chemistry | BL42: 304NA | BM42: WOS:000256115000010 | BN42: 18497931 | BR42: 43703
A43: 42 | B43: 10.1039/b809009b | C43: J | D43: Cooney, MJ; Svoboda, V; Lau, C; Martin, G; Minteer, SD | H43: Cooney, M. J.; Svoboda, V.; Lau, C.; Martin, G.; Minteer, S. D. | K43: Enzyme catalysed biofuel cells | L43: ENERGY & ENVIRONMENTAL SCIENCE | O43: English | P43: Review | W43: DIRECT ELECTRON-TRANSFER; REDUCED NICOTINAMIDE COENZYMES; DIHYDRONICOTINAMIDE ADENINE-DINUCLEOTIDE; LASER-SCANNING MICROSCOPE; GLUCOSE-OXIDASE; CARBON-NANOTUBES; CONDUCTING-POLYMER; METHYLENE GREEN; CYTOCHROME-C; DIRECT BIOELECTROCATALYSIS | X43: Biofuel cells are energy conversion devices that use biocatalysts to convert chemical energy to electrical energy. Over the last decade, research in this area has intensified, especially in the area of direct electron transfer between enzymes and electrodes. This review details the fundamentals of enzymatic biofuel cells and reviews characterization techniques that can be used to evaluate and optimize biofuel cells. The review details the advantages and disadvantages of mediated and direct bioelectrocatalysis at electrodes for biofuel cells. It also compares and contrasts different enzyme immobilization techniques and different electrode structures. | Y43: [Cooney, M. J.; Svoboda, V.; Lau, C.; Martin, G.] Univ Hawaii, Hawaii Nat Energy Inst, Honolulu, HI 96822 USA; [Minteer, S. D.] St Louis Univ, Dept Chem, St Louis, MO 63103 USA | Z43: Cooney, MJ (reprint author), Univ Hawaii, Hawaii Nat Energy Inst, Honolulu, HI 96822 USA. | AA43: mcooney@hawaii.edu; minteers@slu.edu | AB43: Minteer, Shelley/C-4751-2014; Minteer, Shelley/A-7711-2009 | AC43: Minteer, Shelley/0000-0002-5788-2249; | AF43: ALBAUGH S, 1989, BIOPHYS CHEM, V33, P71, DOI 10.1016/0301-4622(89)80009-2; ALBERY WJ, 1980, J ELECTROCHEM SOC, V127, P654, DOI 10.1149/1.2129727; ALLEN PM, 1984, J ELECTROANAL CHEM, V178, P69, DOI 10.1016/S0022-0728(84)80024-8; ANDERSON RB, 1964, J CATAL, V3, P50, DOI 10.1016/0021-9517(64)90092-2; Arechederra RL, 2007, J POWER SOURCES, V173, P156, DOI 10.1016/j.jpowsour.2007.08.012; ARMSTRONG FA, 1988, ACCOUNTS CHEM RES, V21, P407, DOI 10.1021/ar00155a004; Armstrong FA, 2000, ELECTROCHIM ACTA, V45, P2623, DOI 10.1016/S0013-4686(00)00342-X; ATANASSOV P, 2004, P COLL CHEM DIV AM C, P207; Badea M G, 1979, Methods Enzymol, V61, P378; Bardea A, 1997, J AM CHEM SOC, V119, P9114, DOI 10.1021/ja971192+; Barriere F, 2004, ELECTROCHEM COMMUN, V6, P237, DOI 10.1016/j.elecom.2003.12.006; BARTELL FE, 1952, J COLL SCI IMP U TOK, V7, P80, DOI 10.1016/0095-8522(52)90022-6; BARTLETT PN, 1993, SYNTHETIC MET, V61, P15, DOI 10.1016/0379-6779(93)91194-7; Barton SC, 2004, CHEM REV, V104, P4867, DOI 10.1021/cr020719k; BEREZIN IV, 1978, DOKL AKAD NAUK SSSR+, V240, P615; BILITEWSKI U, 1991, BIOSENS BIOELECTRON, V6, P369, DOI 10.1016/0956-5663(91)85024-Q; BRU R, 1995, BIOCHEM J, V310, P721, DOI 10.1042/bj3100721; Brunauer S, 1938, J AM CHEM SOC, V60, P309, DOI 10.1021/ja01269a023; BRUNAUER S, 1967, J COLLOID INTERF SCI, V25, P353, DOI 10.1016/0021-9797(67)90041-0; Calabrese-Barton S., 2004, CHEM REV, V104, P4867; CALABRESEBARTON S, 2001, J PHYS CHEM B, V105, P11917; CALVO EJ, 1994, J ELECTROANAL CHEM, V369, P279, DOI 10.1016/0022-0728(94)87112-4; Cao LQ, 2005, CURR OPIN CHEM BIOL, V9, P217, DOI 10.1016/j.cbpa.2005.02.014; CHI QJ, 1994, ANAL CHIM ACTA, V285, P125, DOI 10.1016/0003-2670(94)85016-X; Chi QJ, 1996, J MOL CATAL A-CHEM, V105, P193; Choo YF, 2006, J MICROBIOL BIOTECHN, V16, P1481; Christenson A, 2004, ELECTROANAL, V16, P1074, DOI 10.1002/elan.200403004; CLEGG JS, 1984, J CELL BIOL, V99, P167; CocheGuerente L, 1997, CHEM MATER, V9, P1348, DOI 10.1021/cm960498x; COLLINSON M, 1992, LANGMUIR, V8, P1247, DOI 10.1021/la00041a004; Cooney MJ, 2008, J MATER CHEM, V18, P667, DOI 10.1039/b710082e; COONEY MJ, 2006, BIOMOLECULAR CATALYS, P289; COONEY MJ, 2008, CARBOHYDR POLYM; D'Auria S, 2001, CURR OPIN BIOTECH, V12, P99, DOI 10.1016/S0958-1669(00)00164-6; DANLIKER WB, 1970, IMMUNOCHEMISTRY, V7, P799; Darby R., 1965, Advanced Energy Conversion, V5, P43, DOI 10.1016/0365-1789(65)90012-3; DEBNATH S, 2006, LANGMUIR, P8732; DEGANI Y, 1989, J AM CHEM SOC, V111, P2357, DOI 10.1021/ja00188a091; DEGANI Y, 1988, J AM CHEM SOC, V110, P2615, DOI 10.1021/ja00216a040; DEGRAND C, 1980, J AM CHEM SOC, V102, P5728, DOI 10.1021/ja00538a005; Digman MA, 2005, BIOPHYS J, V88, pL33, DOI 10.1529/biophysj.105.061788; Digman MA, 2005, BIOPHYS J, V89, P1317, DOI 10.1529/biophysj.105.062836; Digman MA, 2008, BIOPHYS J, V94, P2819, DOI 10.1529/biophysj.107.104984; DROST-HANSEN W, 1979, P440; DUBININ MM, 1968, ADV COLLOID INTERFAC, V2, P217; Duma R, 2007, ECS T, V5, P117; Duma R., 2006, POLYM MAT SCI ENG, V94, P592; EDDOWES MJ, 1977, J CHEM SOC CHEM COMM, P771; ENRIQUEZGRANADOS M, 1983, ELECTROCHIM ACTA, V28, P1407, DOI 10.1016/0013-4686(83)85196-2; Farber L, 2003, POWDER TECHNOL, V132, P57, DOI 10.1016/S0032-5910(03)00043-3; FEI J, 2005, P ORG CHEM DIV AM CH; FERNANDEZLAFUENTE R, 1995, ENZYME MICROB TECH, V17, P517, DOI 10.1016/0141-0229(94)00090-E; FORSTER T, 1948, ANN PHYS-BERLIN, V2, P55, DOI 10.1002/andp.19484370105; FREW JE, 1988, EUR J BIOCHEM, V172, P261, DOI 10.1111/j.1432-1033.1988.tb13882.x; Gerard M, 2002, BIOSENS BIOELECTRON, V17, P345, DOI 10.1016/S0956-5663(01)00312-8; Ghindilis A, 2000, BIOCHEM SOC T, V28, P84, DOI 10.1042/bst0280084; Ghindilis AL, 1997, ELECTROANAL, V9, P661, DOI 10.1002/elan.1140090902; Gooding JJ, 2003, J AM CHEM SOC, V125, P9006, DOI 10.1021/ja035722f; GORTON L, 1995, ELECTROANAL, V7, P23, DOI 10.1002/elan.1140070104; GORTON L, 1992, ANALYST, V117, P1235, DOI 10.1039/an9921701235; Gorton L, 1999, ANAL CHIM ACTA, V400, P91, DOI 10.1016/S0003-2670(99)00610-8; GORTON L, 1984, J ELECTROANAL CHEM, V161, P103, DOI 10.1016/S0022-0728(84)80253-3; GORTON L, 1985, J ELECTROANAL CHEM, V196, P81, DOI 10.1016/0022-0728(85)85082-8; GREGG BA, 1990, ANAL CHEM, V62, P258, DOI 10.1021/ac00202a007; Gros P, 2004, BIOSENS BIOELECTRON, V20, P204, DOI 10.1016/j.bios.2004.02.023; Guiseppi-Elie A, 2002, NANOTECHNOLOGY, V13, P559, DOI 10.1088/0957-4484/13/5/303; HABERMULLER K, 2000, FRESEN J ANAL CHEM, V366, P560; HELLER A, 1990, ACCOUNTS CHEM RES, V23, P128, DOI 10.1021/ar00173a002; Heller A, 2006, CURR OPIN CHEM BIOL, V10, P664, DOI 10.1016/j.cbpa.2006.09.018; HILL HAO, 1993, METHOD ENZYMOL, V227, P501; HILL HAO, 1981, PHILOS T R SOC A, V302, P267, DOI 10.1098/rsta.1981.0166; HUBER K, 1948, J COLL SCI IMP U TOK, V3, P197, DOI 10.1016/0095-8522(48)90028-2; Hussain F, 2005, ANAL BIOCHEM, V339, P137, DOI 10.1016/j.ab.2004.01.016; IKEDA T, 1991, BIOSENS BIOELECTRON, V6, P299, DOI 10.1016/0956-5663(91)85015-O; Ikeda T., 1997, FRONTIERS BIOSENSORI, P243; Islam MK, 2004, CHEM SENSES, V20, P744; Ivnitski D, 2007, ELECTROANAL, V19, P2307, DOI 10.1002/elan.200703983; Ivnitski D, 2007, ELECTROANAL, V19, P1562, DOI 10.1002/elan.200703899; Ivnitski D, 2006, ELECTROCHEM COMMUN, V8, P1204, DOI 10.1016/j.elecom.2006.05.024; JAMESON DM, 1995, METHOD ENZYMOL, V246, P283; Jameson DM, 2003, METHOD ENZYMOL, V360, P1; Jameson DM, 2003, COMB CHEM HIGH T SCR, V6, P167, DOI 10.2174/138620703106298347; JAMESON DM, 1991, TIME RESOLVED FLUORE; JENA A, 2001, J POWER SOURCES, P96; Johnston W, 2005, ENZYME MICROB TECH, V36, P540, DOI 10.1016/j.enzmictec.2004.11.016; Johnston W, 2006, ENZYME MICROB TECH, V39, P131, DOI 10.1016/j.enzmictec.2005.10.008; Kamitaka Y, 2007, PHYS CHEM CHEM PHYS, V9, P1793, DOI 10.1039/b617650j; Kane MA, 2000, J PHYS CHEM B, V104, P8585, DOI 10.1021/jp001301y; Karyakin AA, 1999, ELECTROANAL, V11, P553, DOI 10.1002/(SICI)1521-4109(199906)11:8<553::AID-ELAN553>3.0.CO;2-6; Karyakin AA, 1999, ELECTROANAL, V11, P149, DOI 10.1002/(SICI)1521-4109(199903)11:3<149::AID-ELAN149>3.0.CO;2-G; Katz E, 2003, J AM CHEM SOC, V125, P6803, DOI 10.1021/ja034008v; Kim J, 2006, BIOTECHNOL ADV, V24, P296, DOI 10.1016/j.biotechadv.2005.11.006; Klotzbach T, 2006, J MEMBRANE SCI, V282, P276, DOI 10.1016/j.memsci.2006.05.029; Konash A, 2006, J MATER CHEM, V16, P4107, DOI 10.1039/b611686h; KOOPAL CGJ, 1991, J CHEM SOC CHEM COMM, P1691, DOI 10.1039/c39910001691; KOOPAL CGJ, 1994, SENSOR ACTUAT B-CHEM, V18, P166, DOI 10.1016/0925-4005(94)87077-2; KULYS J, 1993, ELECTROANAL, V5, P201, DOI 10.1002/elan.1140050304; Lakowicz J. R., 1999, PRINCIPLES FLUORESCE, P38; LANGE KR, 1963, J COLL SCI IMP U TOK, V18, P65, DOI 10.1016/0095-8522(63)90104-1; LAU MJ, 2008, LANGMUIR IN PRESS, V24, P7004; LAURENCE DJR, 1952, BIOCHEM J, V51, P168, DOI 10.1042/bj0510168; Leger C, 2002, J PHYS CHEM B, V106, P13058, DOI 10.1021/jp0265687; Lei CH, 1996, ANAL CHEM, V68, P3344, DOI 10.1021/ac960291n; Lim J, 2007, J ELECTROCHEM SOC, V154, pA140, DOI 10.1149/1.2404904; Lin Y, 2004, J MATER CHEM, V14, P527, DOI 10.1039/b314481j; Liu SN, 2007, CHINESE J CHEM, V25, P439, DOI 10.1002/cjoc.200790084; Liu Y, 2007, BIOSENS BIOELECTRON, V23, P593, DOI 10.1016/j.bios.2007.06.002; LOGAN B, 2005, 78 TECHN EXH C WAT E, P93; Lovely D. R., 2006, MICROBE, V1, P323; LYONS MEG, 1986, ANAL CHEM S SER, V25, P285; MAGDE D, 1974, BIOPOLYMERS, V13, P29, DOI 10.1002/bip.1974.360130103; Mano N, 2002, J PHYS CHEM B, V106, P8842, DOI 10.1021/jp025955d; Mano N, 2006, J PHYS CHEM B, V110, P11180, DOI 10.1021/jp055654e; Mao LQ, 2000, TALANTA, V51, P187, DOI 10.1016/S0039-9140(99)00275-1; MARCUS RA, 1985, BIOCHIM BIOPHYS ACTA, V811, P265, DOI 10.1016/0304-4173(85)90014-X; MARCUS RA, 1993, REV MOD PHYS, V65, P599, DOI 10.1103/RevModPhys.65.599; MARSHALL RJ, 1985, SURF TECHNOL, V24, P45, DOI 10.1016/0376-4583(85)90015-9; MARTINEK K, 1989, BIOCHIM BIOPHYS ACTA, V981, P161, DOI 10.1016/0005-2736(89)90024-2; MARTINEK K, 1983, DOKL AKAD NAUK SSSR, V263, P491; Martinek K., 1988, BIOKHIMIYA, V53, P1013; Mathieu LM, 2006, BIOMATERIALS, V27, P905, DOI 10.1016/j.biomaterials.2005.07.015; Minteer SD, 2007, CURR OPIN BIOTECH, V18, P228, DOI 10.1016/j.copbio.2007.03.007; MOIROUX J, 1978, ANAL CHEM, V50, P1056, DOI 10.1021/ac50030a015; Moore CM, 2005, J MEMBRANE SCI, V255, P233, DOI 10.1016/j.memsci.2005.01.043; Moore CM, 2004, BIOMACROMOLECULES, V5, P1241, DOI 10.1021/bm0345256; Nazaruk E, 2007, BIOELECTROCHEMISTRY, V71, P8, DOI 10.1016/j.bioelechem.2006.12.007; Nguyen DT, 2002, CHEM MATER, V14, P4300, DOI 10.1021/cm020398t; NI F, 1990, LANGMUIR, V6, P66, DOI 10.1021/la00091a010; NIKI K, 1979, J AM CHEM SOC, V101, P3335, DOI 10.1021/ja00506a033; Okuda J, 2007, ANAL LETT, V40, P431, DOI 10.1080/00032710600964692; Palmore GTR, 1998, J ELECTROANAL CHEM, V443, P155, DOI 10.1016/S0022-0728(97)00393-8; Palmore GTR, 1999, J ELECTROANAL CHEM, V464, P110, DOI 10.1016/S0022-0728(99)00008-X; Pharoah JG, 2006, J POWER SOURCES, V161, P214, DOI 10.1016/j.jpowsour.2006.03.093; PIEKARCZYK J, 1976, CERAMURGIA INT, V2, P177; Potter MC, 1911, P R SOC LOND B-CONTA, V84, P260, DOI 10.1098/rspb.1911.0073; Rabinovich-Guilatt L, 2004, CHEM PHYS LIPIDS, V131, P1, DOI 10.1016/j.chemphyslip.2004.04.003; Ramanavicius A, 2005, BIOSENS BIOELECTRON, V20, P1962, DOI 10.1016/j.bios.2004.08.032; Ramanavicius A, 1999, ANAL CHEM, V71, P3581, DOI 10.1021/ac981201c; RAZOUK RI, 1967, J COLLOID INTERF SCI, V24, P470, DOI 10.1016/0021-9797(67)90245-7; SAVETT SC, 2002, J ELECTROCHEM SOC, V149, P1527; SCHMIDT HL, 1993, SENSOR ACTUAT B-CHEM, V13, P366, DOI 10.1016/0925-4005(93)85403-W; SCHUHMANN W, 1991, J AM CHEM SOC, V113, P1394, DOI 10.1021/ja00004a048; Schuhmann W, 1995, MIKROCHIM ACTA, V121, P1, DOI 10.1007/BF01248237; SCHUHMANN W, 1995, BIOSENS BIOELECTRON, V10, P181, DOI 10.1016/0956-5663(95)96805-9; Shleev S, 2005, BIOSENS BIOELECTRON, V20, P2517, DOI 10.1016/j.bios.2004.10.003; Shleev S, 2004, ELECTROCHEM COMMUN, V6, P934, DOI 10.1016/j.elecom.2004.07.008; Soutar I, 1996, J PHOTOCH PHOTOBIO A, V102, P87, DOI 10.1016/S1010-6030(96)04389-4; Stoica L, 2006, ANAL CHEM, V78, P393, DOI 10.1021/ac050327o; STORCK A, 1982, ELECTROCHIM ACTA, V27, P293, DOI 10.1016/0013-4686(82)80018-2; Sun DM, 2008, ELECTROCHEM SOLID ST, V11, pB101, DOI 10.1149/1.2900014; SVOBODA V, 2008, J PURE APPL IN PRESS; Svoboda V, 2008, ELECTROANAL, V20, P1099, DOI 10.1002/elan.200704158; Svoboda V, 2007, J ELECTROCHEM SOC, V154, pD113, DOI 10.1149/1.2409858; Tasca F, 2008, J PHYS CHEM C, V112, P9956, DOI 10.1021/jp802099p; TORSTENSSON A, 1981, J ELECTROANAL CHEM, V130, P199, DOI 10.1016/0368-1874(81)87436-9; TROJANOWICZ M, 1995, SENSOR ACTUAT B-CHEM, V28, P191, DOI 10.1016/0925-4005(95)01724-0; Tsujimura S, 2002, CHEM LETT, P1022, DOI 10.1246/cl.2002.1022; VANLENTHE GH, BIOMATERIALS, V28, P2479; Varfolomeev SD, 1996, BIOSENS BIOELECTRON, V11, P863, DOI 10.1016/0956-5663(96)89435-8; Vijayakumar AR, 1996, ANAL CHIM ACTA, V327, P223, DOI 10.1016/0003-2670(96)00093-1; Wang G, 2006, ELECTROCHEM COMMUN, V8, P987, DOI 10.1016/j.elecom.2006.03.046; Wang J, 2005, ANAL CHIM ACTA, V539, P209, DOI 10.1016/j.aca.2005.02.059; Wheeldon IR, 2007, BIOMACROMOLECULES, V8, P2990, DOI 10.1021/bm700858p; Willner I, 1996, J AM CHEM SOC, V118, P10321, DOI 10.1021/ja9608611; Willner I, 2002, SCIENCE, V298, P2407, DOI 10.1126/science.298.5602.2407; WINGARD LB, 1984, TRAC-TREND ANAL CHEM, V3, P235, DOI 10.1016/0165-9936(84)87038-7; WINNIK MA, 1985, ACCOUNTS CHEM RES, V18, P73, DOI 10.1021/ar00111a002; WOJCIESZYN JW, 1981, P NATL ACAD SCI-BIOL, V78, P4407, DOI 10.1073/pnas.78.7.4407; WOLFBEIS OS, 2000, ANAL CHEM, V72, P81; Xiao Y, 2003, SCIENCE, V299, P1877, DOI 10.1126/science.1080664; YAHIRO AT, 1964, BIOCHIM BIOPHYS ACTA, V88, P375, DOI 10.1016/0926-6577(64)90192-5; Yan YM, 2006, ADV MATER, V18, P2639, DOI 10.1002/adma.200600028; YEH P, 1977, CHEM LETT, P1145, DOI 10.1246/cl.1977.1145; Zheng W, 2006, ELECTROANAL, V18, P587, DOI 10.1002/elan.200503444; Zhu Ziwei, 2007, Biotechnology Journal, V2, P241, DOI 10.1002/biot.200600185 | AG43: 175 | AH43: 275 | AI43: 276 | AJ43: 8 | AK43: 163 | AL43: ROYAL SOC CHEMISTRY | AM43: CAMBRIDGE | AN43: THOMAS GRAHAM HOUSE, SCIENCE PARK, MILTON RD, CAMBRIDGE CB4 0WF, CAMBS, ENGLAND | AO43: 1754-5692 | AR43: ENERG ENVIRON SCI | AS43: Energy Environ. Sci. | AU43: 2008 | AV43: 1 | AW43: 3 | BB43: 320 | BC43: 337 | BE43: 10.1039/b809009b | BI43: 18 | BJ43: Chemistry, Multidisciplinary; Energy & Fuels; Engineering, Chemical; Environmental Sciences | BK43: Chemistry; Energy & Fuels; Engineering; Environmental Sciences & Ecology | BL43: 414TK | BM43: WOS:000263887900010 | BR43: 43703
A44: 43 | B44: 10.1039/b810642h | C44: J | D44: Schaetzle, O; Barriere, F; Baronian, K | H44: Schaetzle, Olivier; Barriere, Frederic; Baronian, Keith | K44: Bacteria and yeasts as catalysts in microbial fuel cells: electron transfer from micro-organisms to electrodes for green electricity | L44: ENERGY & ENVIRONMENTAL SCIENCE | O44: English | P44: Review | W44: SHEWANELLA-PUTREFACIENS MR-1; GLASSY-CARBON ELECTRODES; REDUCED NEUTRAL RED; LESS BIOFUEL CELL; SACCHAROMYCES-CEREVISIAE; FE(III)-REDUCING BACTERIUM; PHYSIOLOGICAL CONDITIONS; ANAEROBIC RESPIRATION; COVALENT MODIFICATION; GRAPHITE-ELECTRODES | X44: This article reviews the use of micro-organisms as catalysts at the electrodes of microbial fuel cells (MFCs). The principle of MFCs and their intended use for water treatment and clean electricity production is discussed. We address the different microbial structure and metabolic pathways found in prokaryote (bacteria) and eukaryote (yeasts) that allow the understanding of why electron transfer is possible between a microbe and an electrode. The different mechanisms of microbe-electrode electron transfer are discussed: direct electron transfer or through natural nanowires (pili), mediated electron transfer by natural or artificial redox mediator and finally direct redox transformation of excreted metabolites at the electrodes. This is followed by a review of the different bacteria that have been found and studied in MFCs mainly in the anodic compartment but also more recently in the cathodic side of the fuel cells. A perspective on the possible advantages and challenges of the use of yeasts in MFCs is provided, as this aspect has not been thoroughly studied so far. The fourth section of the review focuses on how to improve the performance and sustainability of MFCs through the functionalisation of the electrode surface, for instance with the covalent grafting of redox mediators and/or enzymes. | Y44: [Schaetzle, Olivier; Barriere, Frederic] Univ Rennes 1, CNRS, UMR Sci Chim Rennes 6226, Equipe MaCSE, F-35014 Rennes, France; [Baronian, Keith] Christchurch Polytech Inst Technol, Sch Appl Sci, Christchurch, New Zealand | Z44: Schaetzle, O (reprint author), Univ Rennes 1, CNRS, UMR Sci Chim Rennes 6226, Equipe MaCSE, F-35014 Rennes, France. | AA44: frederic.barriere@univ-rennes1.fr | AC44: Barriere, Frederic/0000-0001-5515-4080 | AD44: The France-New Zealand Dumont d'Urville | AE44: O. S. thanks ADEME and Region Bretagne for a studentship. The France-New Zealand Dumont d'Urville exchange program is gratefully acknowledged. | AF44: Adachi M, 2008, CHEM COMMUN, P2055, DOI 10.1039/b717773a; Bard A. J., 2006, ENCY ELECTROCHEMIS A, V7a, P119; Baronian KHR, 2002, APPL MICROBIOL BIOT, V60, P108, DOI 10.1007/s00253-002-1108-3; Barriere F, 2004, ELECTROCHEM COMMUN, V6, P237, DOI 10.1016/j.elecom.2003.12.006; Barriere F, 2008, J SOLID STATE ELECTR, V12, P1231, DOI 10.1007/s10008-008-0526-2; Barriere F, 2006, ELECTROCHIM ACTA, V51, P5187, DOI 10.1016/j.electacta.2006.03.050; Beliaev AS, 1998, J BACTERIOL, V180, P6292; Bennetto HP, 1990, BIOTECHNOL ED, V1, P163, DOI DOI 10.2166/WST2011.822; Berg J.M.T., 2001, BIOCHEMISTRY; Blanford CF, 2007, CHEM COMMUN, P1710, DOI 10.1039/b703114a; Boland S, 2008, LANGMUIR, V24, P6351, DOI 10.1021/la7031972; Bond DR, 2002, SCIENCE, V295, P483, DOI 10.1126/science.1066771; Bond DR, 2005, APPL ENVIRON MICROB, V71, P2186, DOI 10.1128/AEM.71.4.2186-2189.2005; Bond DR, 2003, APPL ENVIRON MICROB, V69, P1548, DOI 10.1128/AEM.69.3.1548-1555.2003; BOOGERD FC, 1987, J BACTERIOL, V169, P489, DOI 10.1128/jb.169.2.489-494.1987; Bron M, 2002, J ELECTROANAL CHEM, V535, P113, DOI 10.1016/S0022-0728(02)01189-0; Busalmen JP, 2008, ANGEW CHEM INT EDIT, V47, P4874, DOI 10.1002/anie.200801310; Chaudhuri SK, 2003, NAT BIOTECHNOL, V21, P1229, DOI 10.1038/nbt867; Cheng RHW, 2008, J PERIODONTOL, V79, P379, DOI [10.1902/jop.2008.070247, 10.1902/jop.2008.070247 ]; Chiao M, 2003, PROC IEEE MICR ELECT, P383; Clauwaert P, 2007, ENVIRON SCI TECHNOL, V41, P7564, DOI 10.1021/es0709831; Clauwaert P, 2007, ENVIRON SCI TECHNOL, V41, P3354, DOI 10.1021/es062580r; DAMORE T, 1989, ENZYME MICROB TECH, V11, P411, DOI 10.1016/0141-0229(89)90135-X; de Schamphelaire L, 2008, ENVIRON SCI TECHNOL, V42, P3053, DOI 10.1021/es071938w; Downard AJ, 2000, ELECTROANAL, V12, P1085, DOI 10.1002/1521-4109(200010)12:14<1085::AID-ELAN1085>3.0.CO;2-A; Du ZW, 2007, BIOTECHNOL ADV, V25, P464, DOI 10.1016/j.biotechadv.2007.05.004; Dumas C, 2008, ELECTROCHIM ACTA, V53, P2494, DOI 10.1016/j.electacta.2007.10.018; Fricke K, 2008, ENERG ENVIRON SCI, V1, P144, DOI 10.1039/b802363h; Gorby YA, 2006, P NATL ACAD SCI USA, V103, P11358, DOI 10.1073/pnas.0604517103; Gregory KB, 2004, ENVIRON MICROBIOL, V6, P596, DOI 10.1111/j.1462-2920.2004.00593.x; Habrioux A, 2008, J ELECTROANAL CHEM, V622, P97, DOI 10.1016/j.jelechem.2008.05.011; He Z, 2006, ELECTROANAL, V18, P2009, DOI 10.1002/elan.200603628; Heller A, 2004, PHYS CHEM CHEM PHYS, V6, P209, DOI 10.1039/b313149a; Holmes DE, 2004, APPL ENVIRON MICROB, V70, P1234, DOI 10.1128/AEM.70.2.1234-1237.2004; Holmes DE, 2004, APPL ENVIRON MICROB, V70, P6023, DOI 10.1128/AEM.70.10.6023-6030.2004; Jia YH, 2008, BIOPROC BIOSYST ENG, V31, P315, DOI 10.1007/s00449-007-0164-6; Kaku N, 2008, APPL MICROBIOL BIOT, V79, P43, DOI 10.1007/s00253-008-1410-9; Kim BH, 1999, J MICROBIOL BIOTECHN, V9, P127; Kim N, 2000, BIOTECHNOL BIOENG, V70, P109, DOI 10.1002/1097-0290(20001005)70:1<109::AID-BIT11>3.0.CO;2-M; Klis FM, 2006, YEAST, V23, P185, DOI 10.1002/yea.1349; Lee JY, 2003, FEMS MICROBIOL LETT, V223, P185, DOI 10.1016/S0378-1097(03)00356-2; LESUISSE E, 1992, PLANT PHYSIOL, V100, P769, DOI 10.1104/pp.100.2.769; Logan B. E, 2008, MICROBIAL FUEL CELLS; Logan BE, 2006, ENVIRON SCI TECHNOL, V40, P5181, DOI 10.1021/es0605016; Logan BE, 2006, ENVIRON SCI TECHNOL, V40, P5172, DOI 10.1021/es0627592; Lopez-Lopez A, 1999, BIOTECHNOL BIOENG, V63, P79, DOI 10.1002/(SICI)1097-0290(19990405)63:1<79::AID-BIT8>3.0.CO;2-Z; Mano N, 2003, J AM CHEM SOC, V125, P15290, DOI 10.1021/ja038285d; Mano N, 2004, CHEMBIOCHEM, V5, P1703, DOI 10.1002/cbic.200400275; Marsili E, 2008, P NATL ACAD SCI USA, V105, P3968, DOI 10.1073/pnas.0710525105; May JM, 2004, AM J PHYSIOL-CELL PH, V286, pC1390, DOI 10.1152/ajpcell.00512.2003; Min BK, 2005, WATER RES, V39, P1675, DOI 10.1016/j.watres.2005.02.002; Myers CR, 1997, BBA-BIOMEMBRANES, V1326, P307, DOI 10.1016/S0005-2736(97)00034-5; Myers CR, 1997, J BACTERIOL, V179, P1143, DOI 10.1128/jb.179.4.1143-1152.1997; MYERS CR, 1990, J BACTERIOL, V172, P6232, DOI 10.1128/jb.172.11.6232-6238.1990; Newman DK, 2000, NATURE, V405, P94, DOI 10.1038/35011098; Park DH, 1999, J BACTERIOL, V181, P2403; Park DH, 1999, APPL ENVIRON MICROB, V65, P2912; Park DH, 2002, APPL MICROBIOL BIOT, V59, P58, DOI 10.1007/s00253-002-0972-1; Park HS, 2001, ANAEROBE, V7, P297, DOI 10.1006/anae.2001.0399; Pellissier M, 2008, ELECTROCHEM COMMUN, V10, P835, DOI 10.1016/j.elecom.2008.03.010; *PENN STAT U, 2008, 1 INT S MICR FUEL CE; Pham CA, 2003, FEMS MICROBIOL LETT, V223, P129, DOI 10.1016/S0378-1097(03)00354-9; Pinson J, 2005, CHEM SOC REV, V34, P429, DOI 10.1039/b406228k; Porat A, 2004, RES MICROBIOL, V155, P617, DOI 10.1016/j.resmic.2004.05.005; Potter MC, 1911, P R SOC LOND B-CONTA, V84, P260, DOI 10.1098/rspb.1911.0073; Prasad D, 2007, BIOSENS BIOELECTRON, V22, P2604, DOI 10.1016/j.bios.2006.10.028; Qiao Y, 2008, CHEM COMMUN, P1290, DOI 10.1039/b719955d; Rabaey K, 2005, TRENDS BIOTECHNOL, V23, P291, DOI 10.1016/j.tibtech.2005.04.008; Rabaey K, 2008, WATER SCI TECHNOL, V57, P655, DOI 10.2166/wst.2008.103; Rabaey K, 2005, ENVIRON SCI TECHNOL, V39, P3401, DOI 10.1021/es048563o; Rabaey K, 2004, APPL ENVIRON MICROB, V70, P5373, DOI 10.1128/AEM.70.9.5373-5382.2004; Reguera G, 2005, NATURE, V435, P1098, DOI 10.1038/nature03661; Rhoads A, 2005, ENVIRON SCI TECHNOL, V39, P4666, DOI 10.1021/es048386r; Ricci A, 2007, J SOLID STATE ELECTR, V11, P1511, DOI 10.1007/s10008-007-0339-8; Richter H, 2008, LANGMUIR, V24, P4376, DOI 10.1021/la703469y; Ringeisen BR, 2006, ENVIRON SCI TECHNOL, V40, P2629, DOI 10.1021/es052254w; Rosenbaum M, 2006, ANGEW CHEM INT EDIT, V45, P6658, DOI 10.1002/anie.200602021; SCHAETZLE O, UNPUB; Schroder U, 2007, PHYS CHEM CHEM PHYS, V9, P2619, DOI 10.1039/b703627m; SOLOMON EI, 1996, CHEM REV, V96, P2577; Soukharev V, 2004, J AM CHEM SOC, V126, P8368, DOI 10.1021/ja0475510; Sree NK, 2000, BIORESOURCE TECHNOL, V72, P43, DOI 10.1016/S0960-8524(99)90097-4; Strik DPBTB, 2008, INT J ENERG RES, V32, P870, DOI 10.1002/er.1397; Tender LM, 2008, J POWER SOURCES, V179, P571, DOI 10.1016/j.jpowsour.2007.12.123; Torres CI, 2008, BIOTECHNOL BIOENG, V100, P872, DOI 10.1002/bit.21821; Tsujimura S, 2002, ELECTROCHEMISTRY, V70, P940; Vaz-Dominguez C, 2008, BIOSENS BIOELECTRON, V24, P531, DOI 10.1016/j.bios.2008.05.002; Venkateswaran K, 1999, INT J SYST BACTERIOL, V49, P705, DOI 10.1099/00207713-49-2-705; Walker AL, 2006, J POWER SOURCES, V160, P123, DOI 10.1016/j.jpowsour.2006.01.077; Walker G.M., 1998, YEAST PHYSL BIOTECHN; Wartmann T, 2002, YEAST, V19, P849, DOI 10.1002/yea.880; Wilkinson S, 2000, AUTON ROBOT, V9, P99, DOI 10.1023/A:1008984516499; Wilkinson S, 2006, ELECTROANAL, V18, P2001, DOI 10.1002/elan.200603621; Xing DF, 2008, ENVIRON SCI TECHNOL, V42, P4146, DOI 10.1021/es800312v; Zhang T, 2008, ELECTROCHEM COMMUN, V10, P293, DOI 10.1016/j.elecom.2007.12.009; Zhao F, 2006, ENVIRON SCI TECHNOL, V40, P5193, DOI 10.1021/es060332p; Zhao JS, 2007, ANAL CHIM ACTA, V597, P67, DOI 10.1016/j.aca.2007.06.023; 2006, ENV SCI TECHNOL, V40 | AG44: 98 | AH44: 102 | AI44: 105 | AJ44: 1 | AK44: 109 | AL44: ROYAL SOC CHEMISTRY | AM44: CAMBRIDGE | AN44: THOMAS GRAHAM HOUSE, SCIENCE PARK, MILTON RD, CAMBRIDGE CB4 0WF, CAMBS, ENGLAND | AO44: 1754-5692 | AR44: ENERG ENVIRON SCI | AS44: Energy Environ. Sci. | AU44: 2008 | AV44: 1 | AW44: 6 | BB44: 607 | BC44: 620 | BE44: 10.1039/b810642h | BI44: 14 | BJ44: Chemistry, Multidisciplinary; Energy & Fuels; Engineering, Chemical; Environmental Sciences | BK44: Chemistry; Energy & Fuels; Engineering; Environmental Sciences & Ecology | BL44: 414TR | BM44: WOS:000263888600001 | BR44: 43703
A45: 44 | C45: B | D45: Kalyuzhnyi, S | F45: Varfolomeev, SD; Krykova, L; Zaikov, GE | H45: Kalyuzhnyi, Sergey | K45: ENERGY POTENTIAL OF ANAEROBIC DIGESTION OF WASTES PRODUCED IN RUSSIA VIA BIOGAS AND MICROBIAL FUEL CELL TECHNOLOGIES | L45: MOLECULAR AND NANOSCALE SYSTEMS FOR ENERGY CONVERSION | O45: English | P45: Proceedings Paper | Q45: Conference on Molecular and Nanoscale Systems for Energy Conversion | R45: OCT 01-03, 2007 | S45: Moscow, RUSSIA | W45: ELECTRON-TRANSFER | X45: The well-known microbiological process of anaerobic digestion (AD) generating biogas (mixture of methane and carbon dioxide) is now widely implemented for the production of renewable energy worldwide. However, this is not the case in Russia in spite of huge amounts of organic wastes (OW) suitable for AD. This paper firstly inventories major flows of OW from various sectors of the national economy (agriculture, industry, households, etc.) and estimates their biogas potential. Special attention is put on existing bottlenecks and barriers for implementation of biogas technology in the Russian socio-economic conditions. The second part of the paper is devoted to a new emerging technology based on AD microbial fuel cells (MFC). The current status of research in this field in our country is reviewed in comparison with worldwide developments. The possible niches for implementation of MFC technology in Russia (e.g., wastewater treatment) are pointed out, including its complements to conventional biogas processes. | Y45: Moscow MV Lomonosov State Univ, Fac Chem, Dept Chem Enzymol, Moscow, Russia | Z45: Kalyuzhnyi, S (reprint author), Moscow MV Lomonosov State Univ, Fac Chem, Dept Chem Enzymol, Moscow, Russia. | AB45: Kalyuzhnyi, Sergey/A-5007-2010 | AF45: Aelterman P, 2006, ENVIRON SCI TECHNOL, V40, P3388, DOI 10.1021/es0525511; ALFEROV SV, 2007, P INT C MOL NAN SYST, P180; [Anonymous], 2003, 1234R GOV RUSS FED; Bond DR, 2003, APPL ENVIRON MICROB, V69, P1548, DOI 10.1128/AEM.69.3.1548-1555.2003; Cherp O.M., 1996, PROBLEM MUNICIPAL SO; DUBROVSKY VC, 1988, METHANE DIGESTION AG, P11; FEDOROVICH VV, 2004, CATAL IND, P29; FEDOROVICH VV, 2007, P INT C MOL NAN SYST, P101; Gosselink JW, 2002, INT J HYDROGEN ENERG, V27, P1125, DOI 10.1016/S0360-3199(02)00092-7; GUIBELIN E, 2006, P IWA SPEC C SUST SL, P378; Gunter L. I., 2006, P IWA SPEC C SUST SL, P9; GURVICH VI, 2000, 2 INT C WAST MAN 5 8, P148; Kalyuzhnyi S, 2003, WATER SCI TECHNOL, V48, P37; KALYUZHNYI SV, 2004, CATAL IND, P38; KALYUZHNYI SV, 2006, P 5 ALL RUSS YOUNG S, P138; KHRAMENKOV SV, 2003, DEV MOSCOW SEWERAGE, P35; Kim BH, 1999, J MICROBIOL BIOTECHN, V9, P127; MAZHITOV TO, 2004, THESIS MOSCOW STATE; *MDS, 2000, 1382000 MDS; NOZHEVNIKOVA AN, 1995, ECOL CHEM, V4, P48; PANTSKHAVA E, 2007, AGROMARKET, P12; Park DH, 1999, J BACTERIOL, V181, P2403; Pham TH, 2006, ENG LIFE SCI, V6, P285, DOI 10.1002/elsc.200620121; Potter MC, 1911, P R SOC LOND B-CONTA, V84, P260, DOI 10.1098/rspb.1911.0073; Rabaey K, 2004, APPL ENVIRON MICROB, V70, P5373, DOI 10.1128/AEM.70.9.5373-5382.2004; Reguera G, 2005, NATURE, V435, P1098, DOI 10.1038/nature03661; 2005, AGROINDUSTRIAL COMPL; SURFACE UNDEGROUND W; IND PRODUCTION RUSSI | AG45: 29 | AH45: 0 | AI45: 0 | AJ45: 0 | AK45: 0 | AL45: NOVA SCIENCE PUBLISHERS, INC | AM45: HAUPPAUGE | AN45: 400 OSER AVE, STE 1600, HAUPPAUGE, NY 11788-3635 USA | AQ45: 978-1-60456-682-6 | AU45: 2008 | BB45: 1 | BC45: 12 | BI45: 12 | BJ45: Chemistry, Physical; Nanoscience & Nanotechnology; Materials Science, Multidisciplinary | BK45: Chemistry; Science & Technology - Other Topics; Materials Science | BL45: BIP99 | BM45: WOS:000261797400001 | BR45: 43703
A46: 45 | B46: 10.1016/j.electacta.2007.10.066 | C46: J | D46: Dumas, C; Basseguy, R; Bergel, A | H46: Dumas, Claire; Basseguy, Regine; Bergel, Alain | K46: DSA to grow electrochemically active biofilms of Geobacter sulfurreducens | L46: ELECTROCHIMICA ACTA | O46: English | P46: Article | V46: electroactive biofilm; Geobacter sulfurreducens; dimensionally stable anode (DSA); surface roughness; microbial fuel cell (MFC) | W46: MICROBIAL FUEL-CELLS; INITIAL CARBON-SOURCES; ELECTRICITY-GENERATION; ELECTRON-TRANSFER; FE(III)-REDUCING BACTERIUM; PROTEUS-VULGARIS; STAINLESS-STEEL; BIOFUEL CELLS; REDUCTION; MEMBRANE | X46: Biofilms of Geobacter sulfurreducens were grown on graphite and on dimensionally stable anodes (DSA) in medium that did not contain any soluble electron acceptor. Several working electrodes were individually addressed and placed in the same reactor to compare their electrochemical behaviour in exactly the same biochemical conditions. Under constant polarization at 0.20 V versus Ag/AgCl, the electrodes were able progressively to oxidize acetate (5 mM). and average current densities around 5 A m(-2) and 8 A m(-2) were sustained for days on DSA and graphite, respectively. Removing the biofilm from the electrodes led the current to zero, while changing the medium by fresh one did not disturb the current when contact to air was avoided. This confirmed that the biofilm was fully responsible for the electro-catalysis of acetate oxidation and the current was not due to the accumulation of compounds in the bulk. Cyclic voltammetries performed during chronoamperometry indicated that the oxidation started above 0.05 V versus Ag/AgCl. The difference in maximal current values obtained with DSA and graphite was not linked to the biofilm coverage ratios, which were of the same order of magnitude in the range of 62-78%. On the contrary, the difference in maximal current values matched the ratio of the average surface roughness of the materials, 5.6 mu m and 3.2 mu m for graphite and DSA, respectively. (C) 2007 Elsevier Ltd. All rights reserved. | Y46: [Dumas, Claire; Basseguy, Regine; Bergel, Alain] CNRS INPT, Lab Genie Chim, F-31106 Toulouse 1, France | Z46: Bergel, A (reprint author), CNRS INPT, Lab Genie Chim, 5 Rue Paulin Talabot,BP 1301, F-31106 Toulouse 1, France. | AA46: Alain.Bergel@ensiacet.fr | AB46: Dumas, Claire/B-8957-2012 | AC46: Dumas, Claire/0000-0002-1224-6054; BERGEL, Alain/0000-0002-0637-1828 | AF46: Aelterman P, 2006, ENVIRON SCI TECHNOL, V40, P3388, DOI 10.1021/es0525511; Afkar E, 2005, BMC MICROBIOL, V5, DOI 10.1186/1471-2180-5-41; Bond DR, 2002, SCIENCE, V295, P483, DOI 10.1126/science.1066771; Bond DR, 2003, APPL ENVIRON MICROB, V69, P1548, DOI 10.1128/AEM.69.3.1548-1555.2003; BUSALMEN JP, 2007, P 19 S BIOEL SOC TOU; CACCAVO F, 1994, APPL ENVIRON MICROB, V60, P3752; Chaudhuri SK, 2003, NAT BIOTECHNOL, V21, P1229, DOI 10.1038/nbt867; Choi Y, 2003, BIOELECTROCHEMISTRY, V59, P121, DOI 10.1016/S1567-5394(03)00018-5; Flint SH, 2000, J FOOD ENG, V43, P235, DOI 10.1016/S0260-8774(99)00157-0; Hilbert LR, 2003, INT BIODETER BIODEGR, V52, P175, DOI 10.1016/S0964-8305(03)00104-5; Holmes DE, 2006, ENVIRON MICROBIOL, V8, P1805, DOI 10.1111/j.1462-2920.2006.01065.x; Kim BH, 1999, J MICROBIOL BIOTECHN, V9, P127; Kim N, 2000, BIOTECHNOL BIOENG, V70, P109, DOI 10.1002/1097-0290(20001005)70:1<109::AID-BIT11>3.0.CO;2-M; Kim N, 2000, B KOR CHEM SOC, V21, P44; Lee SA, 2002, BIOELECTROCHEMISTRY, V57, P173, DOI 10.1016/S1567-5394(02)00115-9; Liu H, 2005, ENVIRON SCI TECHNOL, V39, P658, DOI 10.1021/es048927c; Liu H, 2004, ENVIRON SCI TECHNOL, V38, P4040, DOI 10.1021/es0499344; Liu H, 2005, ENVIRON SCI TECHNOL, V39, P5488, DOI 10.1021/es050316c; Logan BE, 2006, ENVIRON SCI TECHNOL, V40, P5181, DOI 10.1021/es0605016; Logan BE, 2006, TRENDS MICROBIOL, V14, P512, DOI 10.1016/j.tim.2006.10.003; Lovley D. R., 2006, CURR OPIN BIOTECH, V17, P1; LOVLEY DR, 2006, MICROBE, V1, P323; Methe BA, 2003, SCIENCE, V302, P1967, DOI 10.1126/science.1088727; Park DH, 2003, BIOTECHNOL BIOENG, V81, P348, DOI 10.1002/bit.10501; Park HI, 2005, PROCESS BIOCHEM, V40, P3383, DOI 10.1016/j.procbio.2005.03.017; Park HS, 2001, ANAEROBE, V7, P297, DOI 10.1006/anae.2001.0399; Pham CA, 2003, FEMS MICROBIOL LETT, V223, P129, DOI 10.1016/S0378-1097(03)00354-9; Potter MC, 1911, P R SOC LOND B-CONTA, V84, P260, DOI 10.1098/rspb.1911.0073; Rabaey K, 2005, TRENDS BIOTECHNOL, V23, P291, DOI 10.1016/j.tibtech.2005.04.008; Rabaey K, 2005, ENVIRON SCI TECHNOL, V39, P3401, DOI 10.1021/es048563o; Rabaey K, 2004, APPL ENVIRON MICROB, V70, P5373, DOI 10.1128/AEM.70.9.5373-5382.2004; Rabaey K, 2005, WATER SCI TECHNOL, V52, P515; Reguera G, 2006, APPL ENVIRON MICROB, V72, P7345, DOI 10.1128/AEM.01444-06; ROGINSKAYA YE, 2004, ELECTROCHIM ACTA, V38, P435; ROLLER SD, 1984, J CHEM TECH BIOT B, V34, P3; Scheuerman TR, 1998, J COLLOID INTERF SCI, V208, P23, DOI 10.1006/jcis.1998.5717; Seeliger S, 1998, J BACTERIOL, V180, P3686; SUZUKI S, 1983, ANN NY ACAD SCI, V413, P133, DOI 10.1111/j.1749-6632.1983.tb47884.x; Trasatti S, 2000, ELECTROCHIM ACTA, V45, P2377, DOI 10.1016/S0013-4686(00)00338-8; Zhang ER, 2006, J POWER SOURCES, V161, P820, DOI 10.1016/j.jpowsour.2006.05.004 | AG46: 40 | AH46: 47 | AI46: 50 | AJ46: 2 | AK46: 47 | AL46: PERGAMON-ELSEVIER SCIENCE LTD | AM46: OXFORD | AN46: THE BOULEVARD, LANGFORD LANE, KIDLINGTON, OXFORD OX5 1GB, ENGLAND | AO46: 0013-4686 | AR46: ELECTROCHIM ACTA | AS46: Electrochim. Acta | AT46: 45689 | AU46: 2008 | AV46: 53 | AW46: 7 | BB46: 3200 | BC46: 3209 | BE46: 10.1016/j.electacta.2007.10.066 | BI46: 10 | BJ46: Electrochemistry | BK46: Electrochemistry | BL46: 271QR | BM46: WOS:000253804300022 | BO46: Green Accepted | BR46: 43703
